{
  "sessionId": "dna_1752948069614",
  "pipeline": "DNA_SEQUENCING_MOCK",
  "timestamp": "2025-07-19T18:01:09.615Z",
  "patientInfo": {
    "name": "김태현",
    "dob": "",
    "enrollmentDate": "2025-01-01",
    "insurance": [
      {
        "company": "NH농협손해보험",
        "product": "",
        "start_date": "2025-01-01",
        "period": "all"
      }
    ]
  },
  "dna_analysis": {
    "layout_reconstruction": {
      "original_sentences": 115,
      "reconstructed_sentences": 115,
      "confidence_score": 0.7
    },
    "gene_extraction": {
      "total_genes": 1,
      "average_confidence": 0.6955727155051794,
      "extraction_summary": {
        "total_genes": 1,
        "average_confidence": 0.6955727155051794,
        "temporal_coverage": "2025-01-01",
        "spatial_coverage": [
          "병원"
        ],
        "medical_events": [
          "진단",
          "치료",
          "검사"
        ]
      }
    },
    "date_resolution": {
      "resolved_genes": 1,
      "temporal_anchors": 1,
      "resolution_confidence": 0.8
    },
    "causal_network": {
      "nodes": 1,
      "edges": 0,
      "confidence_score": 0.75,
      "critical_paths": 0
    },
    "report_generation": {
      "nine_items_completed": 9,
      "overall_confidence": 0.75,
      "validation_score": 0.8
    }
  },
  "results": {
    "report": "**내원일**: 2025-01-01\n\n**내원경위**: 응급내원\n\n**입퇴원기간**: 입원치료 시행\n\n**통원기간**: 1회 진료 확인\n\n**진단병명**: 2025-04-09 16:49:16\nCH\n해오름손해사정(주)\nPARAGE SUNRISE SURVEYORS & CLAIM ADJUSTERS CO., LTD 신촌세브란스병원\n의무기록사본\n총 1부\n(표지제외)\n빈경환\n\n세브란스병원\nSEVERANCE HOSPITAL 발행번호:\n2025-34780\n등록번호:\n7314152\n환자성명: 김태현\n용 도: 보험회사제출\n발급매수:\n57 매\n의무기록 사본 증명서\n이 사본은 의무기록 원본과 틀림이 없음을 증명합니다 이 사본은 위의 용도 외에는 사용할 수 없습니다 의무기록 사본 증명서\n2025년 03월 28일\n담당자:\n조예은\n담당자의 날인이 없는 것은 무효임\n연세대학교 의과대학\n연화대학교\n학과대학\n세브란스병원\n세브란스병원\nSEVERANCE HOSPITAL\n\n등록번호: 7314152\n주민등록번호: 651226-264**** 여/59세\n환자명 : 김태현\n병리번호\n세포병리진단 결과\nSC2502192\n의뢰과/임상의사:\n검사물접수일 :\n보고일\n:\n산부인과/김상운\n2025-01-21 08:33\n2025-01-23\n병동:\nOPD\n김태현 7314152\n[부인과 세포병리검사]\n검체유형: Cervix Liquid Based Cytology\n[세포병리학적 진단]\n◇ SPECIMEN ADEQUACY\nSatisfactory for evaluation; No endocervical/transformation zone component\n◇ INTERPRETATION/RESULT\nNegative for intraepithelial lesion or malignancy\n특수염색\n:\n면역조직화학염색 :\n슬라이드수\n:\n1\nBlock 수:\nScreener\n김지은\n병리의사\n:\n정민선\n연세대학교 세브란스병원 병리과 | 120-752 서울시 서대문구 성산로 250| Tel:02)2228-2623 | Fax:02)2227-7939\n작성자: 정민선\n1/1\n출력일: 2025-03-28\n세브란스병원\nSEVERANCE HOSPITAL\n출력자: 조예은\n원본대조필\n\n등록번호: 7314152\n주민등록번호: 651226-264**** 여/59세\n환자명: 김태현\n세포병리진단 결과\n병리번호\nSC2502193\n의뢰과/임상의사:\n검사물접수일 :\n산부인과/김상운\n2025-01-21 08:33\n병동: OPD\n김태현 7314152\n보고일\n2025-01-23\n[부인과 세포병리검사]\n검체유형: Cervix Liquid Based Cytology(검진목적)\n[세포병리학적 진단]\n◇ SPECIMEN ADEQUACY\nSatisfactory for evaluation\n◇ INTERPRETATION/RESULT\nNegative for intraepithelial lesion or malignancy\nReactive cellular changes\n특수염색\n:\n면역조직화학염색 :\n슬라이드수\n1\nBlock 수:\nScreener\n:\n김지은\n병리의사\n정민선\n출력일: 2025-03-28\n연세대학교 세브란스병원 병리과 | 120-752 서울시 서대문구 성산로 250| Tel:02)2228-2623 | Fax:02)2227-7939\n작성자: 정민선\n세브란스병원\nSEVERANCE HOSPITAL\n1/1\n출력자: 조예은\n원본대조필\n\n등록번호: 7314152\n주민등록번호: 651226-264****여/59세\n환자명: 김태현\n조직병리진단 결과\n병리번호\nSF2500412\n의뢰과/임상의사:\n검체채취일\n산부인과/김상운\n2025-01-31 14:23\n병동:\n퇴실\n김태현 7314152\n검사물접수일 :\n2025-01-31 14:29\n보고일\n[ Name Of Operation]\nOmentum, frozen biopsy\n[Pathological Diagnosis]\nSee SS25-05286\n특수염색\n면역조직화학염색 :\n면역형광\n2025-02-04\n분자병리\n기타염색\n슬라이드수\n0\n육안사진\n전자현미경\nZZ\nN\nN\nFrozen\nY\n병리의사\n류향주\n[ Gross Description]\nThe specimen submitted fresh for frozen section consists of a piece of soft tissue, labeled \"omentum\", measuring\n3.5x1.5x0.8cm <FROZEN SECTION DIAGNOSIS>\nPresence of carcinoma\n[동결절편진단의: 류향주]\nBlock\nFSP: p-all\n육안검사의사 : 류향주\n출력일: 2025-03-28\n연세대학교 세브란스병원 병리과 | 120-752 서울시 서대문구 성산로 250| Tel:02)2228-2623 | Fax:02)2227-7939\n작성자 : 류향주\n세브란스병원\nSEVERANCE HOSPITAL\n1/1\n출력자: 조예은\n원본대조필\n\n등록번호: 7314152\n주민등록번호: 651226-264****여/59세\n환자명: 김태현\n세포병리진단 결과\n병리번호\n:\nSC2503129\n의뢰과/임상의사:\n검사물접수일\n:\n산부인과/김상운\n2025-02-03 15:09\n병동:\n퇴실\n김태현 7314152\n보고일\n:\n2025-02-05\n[비부인과 세포병리검사]\n검체유형: Peritoneal Fluid(Intraoperative)-Liquid Based Cytology\n[세포병리학적 진단]\n◇ SPECIMEN ADEQUACY\nSatisfactory for evaluation\n◇ INTERPRETATION/RESULT\nPositive for malignancy, metastatic carcinoma\n특수염색\n면역조직화학염색 :\n슬라이드수\n:\n1\nBlock 수:\n1\nScreener\n천상구\n병리의사\n정민선\n연세대학교 세브란스병원 병리과 | 120-752 서울시 서대문구 성산로 250| Tel:02)2228-2623 | Fax:02)2227-7939\n작성자: 정민선\n1/1\n출력일: 2025-03-28\n세브란스병원\nSEVERANCE HOSPITAL\n출력자: 조예은\n원본대조필\n\n등록번호: 7314152\n주민등록번호: 651226-264****여/59세\n환자명 : 김태현\n조직병리진단 결과\n병리번호\n:\nSS2505286\n의뢰과/임상의사:\n검체채취일\n산부인과/김상운\n2025-01-31 15:03\n병동:\n퇴실\n김태현\n7314152\n검사물접수일\n2025-01-31 15:08\n보고일\n2025-02-11\n[ Name Of Operation]\nOmentum, diagnostic laparoscopy (GYN)\n[Pathological Diagnosis ]\nPresence of carcinoma, favoring high-grade serous carcinoma (HGSC)\nNote) The immunohistochemical stain results:\nWT-1: Positive\np53: Aberrant expression (overexpression)\nCK7: Focal positive\nCK20: Negative\nPAX8: Almost negative\np16: Increased expression\nER: Negative\nPR: Negative\nHNF1B: Negative\nCDK2: Negative\nㅇHRD Result: See attached documents *\n'본 결과는 의료법인 녹십자의료재단에 위탁한 검사 결과입니다 특수염색\n면역조직화학염색 :\nPAX8, WT 1,P53_P16,HNF1B,ER,PR,CK7,CDX-2,CK20\n면역형광\nHRD검사-위탁(녹십자),HRD검사-위탁(녹십자)\n분자병리\n기타염색\n슬라이드수\n6\n육안사진\nN\n전자현미경\nN\nFrozen\nN\n병리의사\n박진우\n[Gross Description]\nThe specimen consists of a product of Diagnostic laparoscopy (GYN), including multiple pieces of tissue labeled\n\"omentum\", measuring 10.0x5.0x1.2cm in aggregates Block\n1-5, p-some\n육안검사의사: 김현기\n[외부서식]\n연세대학교 세브란스병원 병리과 | 120-752 서울시 서대문구 성산로 250|Tel:02)2228-2623 | Fax:02)2227-7939\n작성자: 박진우\n출력일: 2025-03-28\n세브란스병원\nSEVERANCE HOSPITAL\n1/5\n출력자: 조예은\n원본대조필\n\n등록번호: 7314152\n주민등록번호: 651226-264**** 여/59세\n환자명: 김태현\n외래재진기록\n2025-01-20\n진료과\n산부인과\n주치의\n김상운\nProgress\n19세때 맹장 터져서 복막염 수술\n제왕절개 2회\n대소변 불편해서 검진함 : 위 대장내시경 정상\ncolpo pap HPV call\nadm baseline\n기록자명\n김상운(의사)\n전자서명자: 김상운\n세브란스병원\nSEVERANCE HOSPITAL\n0\n1/1\n출력일: 2025-03-28\n출력자: 조예은\n원본대조필\n\n등록번호: 7314152\n주민등록번호: 651226-264**** 여/59세\n환자명: 김태현\n영상검사 일반촬영\n검사명\nChest PA\n검사방법\n검사일자\n2025.01.20 16:05\n판독일자\n2025.01.20 16:59\nDescription\nNo active lung disease 판독의/전문의\n허진/허진/허진\n전자서명자: 허진\n세브란스병원\nSEVERANCE HOSPITAL\n영상검사 일반촬영\n촬영실\n암)촬영실 1호\n1/1\n출력일: 2025-03-28\n출력자: 조예은\n원본대조필\n\n등록번호: 7314152\n주민등록번호: 651226-264**** 여/59세\n환자명 : 김태현\n진료의뢰서\n연세대학교의과대학세브란스\n병원\n01055530410\n기본정보\n의뢰번호\n1239134425011700002\n수진자성명 김태현\n보험세부명 건강보험\n의뢰기관명 더바른내과의원\n주민등록번호 651226-*******\n보장기관기호\n의뢰할기관\n전화번호\n보장기관명\n의뢰정보\n회송환자 재의뢰(패스트트랙)\n의뢰유형\n타기관 의뢰\n진단의뢰\n검사의뢰\n의뢰사유\n시술 및 약물치료 의뢰\n환자 또는 가족의 요청\n수술의뢰\n기타\n의뢰사유기타\n환자상태 및 진료소견\n상병분류 C569\n난소의 악성 신생물, 상세불명 쪽 수정상병명 난소의 악성 신생물, 상세불명 쪽\n진료구분\n입원\n외래\n진료시작일\n진료종료일\n의뢰받을\n내과세부\n산부인과\n진료과목\n전문과목\n당뇨 2021년 진단후 LSM하고계신분\n본원에서 고지혈증약 리바로 2 mg 복약하시는분\n진료소견\n타 산부인과에서 폐경후 HRT하면서 해당 병원에서 칼슘약 드시는분\n검사내역\n하복부 묵직한 불편감으로 대,소변 보기 어려워 25년 1월2일 본원에서 위내시경했고 위축성위염있었고 조직검사에서 화생성\n위염확인되었습니다 당시 대장내시경 함께 진행했고 8mm 선종 2개 제거하였습니다 내시경상 큰 이상이 없음에도 하복부 묵직한 불편감과 대소변보기 불편하다고 해 골반암 배제위해 촬영한 타원 APCT에서\nmoderate amount of ascies r/o peritoneal carcinomatosis r/o associated Lt interiliac lymphadenopathy with bilateral\nperivoarian metastatic lesions or solid ovarin tumor 확인되어 귀원진료의뢰드립니다 과거력\n/투약력\n가족력\n/알러지 유무\n담당의사 정보\n담당의사명 김유나\n담당의사 면허번호 124024\n담당자명\n전화번호\n작성자: 최소윤\n세브란스병원\nSEVERANCE HOSPITAL\n진료의뢰서\n1/1\n출력일: 2025-03-28\n출력자: 조예은\n원본대조필\n\n등록번호: 7314152\n침습적 시술 기록 (Invasive procedure)\n주민등록번호: 651226-264****여/59세\n환자명 : 김태현\n2025-01-20\n내원구분\n외래\n입원\n시술 관련 정보\n시술전 진단명\n시술후 진단명\n시술명 EM cytology\n시행일자 2025-01-20\n시술구분 정규\nMass, pelvic; Primary peritoneal carcinomatosis;\nMass, pelvic; Primary peritoneal carcinomatosis;\n시술의사 이지은\n응급\n시술 전 평가내용\n의식상태\n명료(alert)\n환자 확인\n예\n아니오\n시술명 확인\n시술부위 표시\n예\n있음\n아니오\n없음\n시행의사 이지은\n사유\n표시누락 ㅇ 응급시술 Transfemoral catheterization\n영상유도검사\nNatural Orifice를 통한 수술 ㅇ 개방상처 ㅇ중심정맥관 삽입\nO Single Organ\n) 신생아/미숙아\n치아\n환자거절\n동의서\n있음 없음\n시술관련 검사결과 확인\n예 ㅇ아니오 해당없음\nAllergy\n□ 없음\n약\n식품\nRisk factors\n있음\n마취시행 여부\n시행\n없음\nㅇ 시행하지 않음\n□ 수술 및 시술 후 통증발생 가능성과 통증관리에 대해 설명함\n시술구분\n정규 ㅇ 응급\nTime out\n환자 확인\n시행함(정규시술) ㅇ 시행함(응급시술)○ 시행하지 않음(응급수술)\n시행 ㅇ기타\n시술 부위 확인\n시행 ○ 기타\n시술 방향 확인\n예정 시술명 확인\n사용예정 삽입물 확인\n사용예정 장비\n시행 ○ 해당 없음 ○ 기타\n시행 ㅇ기타\n없음 ㅇ있음(삽입물 기재)\n□ 없음 ☐ Ultrasonogram\nAngio-suite □ 기타\nLaser 장비\n□ 내시경 장비\n☐ C-arm\n참여자\n이지은\n시술과정 EM cytology exam was done by JE LEE, MD 시술과정 중 특이사항\nEstimated blood loss\n조직검사 의뢰 유무\n시술 후 평가\n있음\n없음\nminimal (<10 ml) 이\n예\n) ml\n아니오\n전자서명자: 이지은\n세브란스병원\nSEVERANCE HOSPITAL\n1/2\n출력일: 2025-03-28\n출력자: 조예은\n원본대조필\n\n등록번호: 7314152\n침습적 시술 기록 (Invasive procedure)\n주민등록번호: 651226-264**** 여/59세\n환자명: 김태현\n2025-01-20\n의식상태\n명료(alert)\n통증 여부\n없음\n있음\n통증 강도 4\n통증평가도구 NRS(Numeric Rating Scale)/NPIS(The Numerical Pain Intensity Scale)\n입실일시\n2025-01-20\n15:20\n퇴실일시\n2025-01-20\n15:40\n퇴실방법\n걸어서 ○ 휠체어 ㅇ눕는 차 ○ 기타\n퇴실한 곳\n집 타병원 기타\n귀가 시 이송 수단\n동행인\n자가 ○ 대중교통 항공 ○ 기타\n퇴실 시 교육내용\n보호자 의료진 이송팀 없음\n검사 후 합병증 및 주의사항, 추후관리, 응급상황시 연락처\n□ 기타\n전자서명자: 이지은\n세브란스병원\nSEVERANCE HOSPITAL\n2/2\n출력일: 2025-03-28\n출력자: 조예은\n원본대조필\n\n등록번호: 7314152\n주민등록번호: 651226-264**** 여/59세\n환자명: 김태현\n입원정보\n입원일자 2025-01-21\n입원과\n산부인과\n입원주치의 김상운\n퇴원정보\n퇴원일자 2025-01-23\n퇴원과 산부인과\n퇴원주치의 김상운\n최종진단명(*)\n순서\n한국질병\n구분\n확진\n진단명\n분류번호\n1 주진단\n확진\nPrimary peritoneal carcinomatosis\nC48.2\n과거진단명\n과거진단코드\n주호소 (★)\nBaseline study\n과거력 및 현재병력 본 59세 G3 P2 L2 DO A1 married woman은 DL, 당뇨전단계, s/p 복막염수술(19\n세) 외 특이 과거력 없는 분으로, 하복부 불편감으로 대,소변 보기 어려워 타병원 내\n원하여 EGD,Colonoscopy 시행하여 특이 소견 없음에도 증상 지속되어 시행한 APCT\nr/o peritoneal carcinomatosis r/o associated Lt interiliac lymphandecnopathy\nwith bilateral periovarian metastatic lesions or solid ovarian tumor\nfurther evaluation 및 proper management 위해 김상운 교수님께 refer, 금번\nbaseline study 시행 후 이상소견 없이 퇴원함 이상 진찰 소견 및 검사소견 (*)\nn-c\n투여된 약물 중 잔류효과로 퇴원 후 주의가 필요한 약물 (*) 없음 ㅇ있음\n경과요약 (*)\nbaseline study\n수술/처치명\nbaseline study\n수술/처치코드\nImplantable Medical Device 사용 여부 No\nYes\n치료결과 (*)\n|완쾌 ) 경쾌\n'48시간이내 사망\n호전안됨\nㅇ 진단뿐\nㅇ가망없는 퇴원\n활력증상\n혈압 97/71\n148시간이후\nmmHg 맥박수 65\n사망\n퇴원형태 (*)\n퇴원지시후\n・타병원전원\n회/분 체온 37.0 °C 호흡수 18\n자의 퇴원 ㅇ 탈원\n회/분\n향후 치료계획\n외래 추후관리\n재입원 2/3 재입원\n없음\n○ 기타\n전자서명자: 김상운\n세브란스병원\nSEVERANCE HOSPITAL\n퇴원요약\n1/2\n출력일: 2025-03-28\n출력자: 조예은\n원본대조필\n\n등록번호: 7314152\n주민등록번호: 651226-264**** 여/59세\n환자명 : 김태현\n담당 전공의사명\n없음\n기록자명\n김지환(의사)\n주치의사명\n김상운\n<약어 설명>\nA repair Anterior repair\nANC Antenatal care\nBO Bilateral oophorectomy\nBOC Bilateral ovarian cystectomy\nBS Bilateral salpingectomy\nC/S Cesarean section\nCPD Cephalopelvic disproportion\nDCB : Dilatation, curettage, biopsy\nET Embryo transplantation\nIDS Internal debulking operation\nIM Intramural lapa Laparoscopic\nLOC: Left ovarian cystectomy\nLS: Left salpingectomy\nP repair Posterior repair\nPALND: Para-aortic lymph node dissection\nPLD Pelvic lymphnode dissection\nPPD Postpartum day\nROC Right ovarian cystectomy\nROP Right occiput posterior\nRS Right salpingectomy\nSLND: Sentinel lymphnode dissection\nSPA Single port access\n퇴원요약\n전자서명자: 김상운\n2/2\n출력일: 2025-03-28\n출력자: 조예은\n세브란스병원\nSEVERANCE HOSPITAL\n원본대조필\n\n등록번호: 7314152\n주민등록번호 : 651226-264**** 여/59세\n환자명: 김태현\n입원일자\n2025-01-21\n입원과\n산부인과\n주호소\nPresent illness\nBaseline study\n입원주치의 김상운\n(19\n59 G3 P2 L2 DO A1 married woman DL,\ns/p\n세) 외 특이 과거력 없는 분으로, 하복부 불편감으로 대,소변 보기 어려워 타병원 내원\n하여 EGD,Colonoscopy 시행하여 특이 소견 없음에도 증상 지속되어 시행한 APCT 상\nr/o peritoneal carcinomatosis r/o associated Lt interiliac lymphandecnopathy with\nbilateral periovarian metastatic lesions or solid ovarian tumor of further\nevaluation proper management |\nrefer,\nbaseline study\n위해 입원함 Virgin\nNo Yes\n임신력\nG 3\nP 2 L 2 D0A 1\nPast history\nMenarche No\nMarriage\nYes\n16\nNo\nYes\nMenopause\nNo\nYes\n54\nLast delivery\nNo\nYes\n1996\nContraception method\nNone\nHusband-vasectomy\nPast OB-GYN history\nLast D & E history\nNo\nYes\nOral pill\n○ IUD\nOs/p LBTL or BTL\nOther\nLast PAP smear\nnone\n2025\nY 01\nM\nnl\nabnl\n-\nNSVD\nNo\nYes\nC/sec\nNo\nYes 2'93,'96\nInduced abortion\nNo\nYes\nSpontaneous abortion\nNo\nYes\nOthers\nPosthysterctomy status\nNo\nYes\nLNMP\n2024-12-27\nPMP\nMenstrual history\nRegularity\nInterval\nDuration\ndays\n(days)\n(days)\nAmount\nPain(VAS)\nMedico-surgical illness\n전자서명자: 김상운\n세브란스병원\nSEVERANCE HOSPITAL\n입원기록\n1/3\n출력일: 2025-03-28\n출력자: 조예은\n원본대조필\n\n등록번호: 7314152\n주민등록번호: 651226-264**** 여/59세\n환자명 : 김태현\n입원기록\nHypertension No\nYes\nDM\nNo\nYes\nHepatitis\nNo\nYes\nPul Tbc\nNo\nYes\nOperation history ☐ No\nYes\nOther Cancer history\nNONE\nCardiac disease\nNo\nYes\nNo\nYes\nOld CVA\nOther\nSocial history\nSmoking\nNo\nYes\nAlcohol\nNo\nYes\nAllergy\nDrug\nNo\nYes\n항생제\n진통제\n조영제\n기타\nFood 및 기타\nNo\nYes\nOther\n신체조사\nGeneral appearance\nSkin\nHEENT\nNeck\nChest/lung\nHeart\nAbdomen\nBack and extremity\nPelvic examination\n감염성질환 초기평가\n이상소견 없음\n이상소견 없음\n이상소견 없음\n이상소견 없음\n이상소견 없음\n이상소견 없음\n이상소견 없음\n・이상소견 없음\n이상소견 없음\n)이상소견 있음\n이상소견 있음\n이상소견 있음\n이상소견 있음\n이상소견 있음\n이상소견 있음\n이상소견 있음\n이상소견 있음\n이상소견 있음\n1 증상 및 기간\n]발열\n기간\n일전\n호흡기증상\n기간\n일전\n소화기증상\n기간\n일전\n2 최근 1달 이내 방문한 나라\n4 밀접 접촉자\n□ 해당없음 (미상환자 포함)\n3 최근 1달 이내 국내 신종감염병 위험지역 또는 병원 방문\n5 신종 감염병 의심환자\nPrimary peritoneal carcinomatosis\n추정진단\n전자서명자: 김상운\n해당없음\n없음\n있음\n없음\n있음\n|해당없음\n) 아니오\n예\n아니오\n예\n세브란스병원\nSEVERANCE HOSPITAL\n2/3\n출력일: 2025-03-28\n출력자: 조예은\n원본대조필\n\n등록번호: 7314152\n주민등록번호: 651226-264****여/59세\n환자명 : 김태현\nPlan\nOP\nGYN sono\nConservative management\nChemotherapy\nothers\nBaseline study\n퇴원계획\n퇴원 후 치료식이 여부\n추후 관리 계획\n☑ N ☐ Y\n| 가정간호사업소\n호스피스\n타 병원 전원\n외래\n사회 복지서비스 연계 필요성\n✓ N ☐ Y\n기타 퇴원시 요구사항\n치료계획\n+\nProblem\nGoal\n목표일\n수정목표일 계획일\n부\nPrimary peritoneal\ncarcinomatosis\nbaseline study without\ncomplication\n2025-01-28\n2025-01-21\n기록자명\n김지환(의사)\n<약어 설명>\nG: gravida\nP: para\nL: living\nD: dead\nA: Abortion\nabnl : abnormal\nDOE dyspnea on exertion\nGYN: Gynecology\nPAP Papanicolaou\nPMI point of maximum intensity\nHSIL High Grade Squamous Intraepithelial Lesion\nICS intercostal space\nPMP previous menstrual period\nIUD intrauterine device\nPul Tbc pulmonary tuberculosis\nA-V : Anteversion\nBTL bilateral tubal ligation\nC/sec : cesarian section\nLBTL laparoscopic bilateral tubal ligation RCC renal cell carcinoma\nLMCL Left Midclavicular Line\nRHB regular heart beat\nRT: Right\nLNMP last normal menstrual period\nLSIL: Low Grade Squamous Intraepithelial Lesion\nLT : Left\nM: Month\nCVA cerebrovascular accident\nD&E: Dilatation and evacuation\nDM diabetes mellitus\nnl: Normal\nR-V: Retroversion\nVAS Visual analog pain scale\nY: Year\nAG-H atypical glandular cells cannot exclude a high-grade squamous intraepithelial lesion\nAGUS atypical glandular cells of undetermined significance\nASC-H atypical squamous cells cannot exclude a high-grade squamous intraepithelial lesion\nASCUS atypical squamous cells of undetermined significance\n전자서명자: 김상운\n세브란스병원\nSEVERANCE HOSPITAL\n입원기록\n3/3\n출력일: 2025-03-28\n출력자: 조예은\n원본대조필\n\n등록번호: 7314152\n주민등록번호: 651226-264**** 여/59세\n환자명: 김태현\n연령 구분\n영유아기 학령전기\n학령기\n청소년기\n성인\n분류\n일반 ○ 산모 ㅇ정신\n현병력\n주 증상 및 내원 과정 금번 baseline study 위해 입원함 간호정보조사\n2025-01-21\n복용중인 약\n없음\n있음\n투약 상태\n1회 투여개수\n1회 투여량\n약품명\n횟수\n용법 및 투여시간\n약품코드 유효함량\n수량 단위\n용량 단위\n[DiCAmax[1T /]\n1\n1\nT\n1\n8am\nD2DICA01 1\nLivial[2.5mg/T]\n1\nT\n2.5\nmg\n1\n8am\n[Livalo[2mg/T]\n1\nT\n2\nmg\n1\n6pm\nD2LIVI01\n2.500\nD2LIVA02 2.000\n내원 시 환자 상태\n통증\n없음\n있음\n입원 전에 있었음\n과거력\n과거병력\n없음\n있음\n입원 및 수술 이력\n없음 있음 ㅇ 알 수 없음\n입원 및 수술 이력\n입원시 진단명 및 수술명\n복막염 수술\n자궁근종\n제왕절개 수술\n입원 및 수술 시기\n1984\n2000\n1993,1996\n가족력\n없음\n있음\n부모> 당뇨\n부> 심장질환\n음주력 Onondrinker\nex-drinker\ncurrent drinker\n흡연력\n음주력(종류, 양, 횟수/wk) 소주 1/2 병, 2~3회/주\n음주 시작 시기 21\nAllergy □ 없음 □ 약 □ 식품\n끊은 시기 1달 전\nnonsmoker ex-smoker\nO current smoker\n일반정보(심적/사회적/경제적/영적/문화적/종교적 평가)\n결혼 상태\n미혼 ) 기혼 ○ 별거 ㅇ 이혼 ㅇ사별 ㅇ 해당 없음\n종교\n없음 ○ 기독교 천주교 불교 ○ 기타\n원목 연락\n원함 )원하지 않음\n보호자 (Main caregiver)\n없음\n배우자\n부\n모\n자녀 □ 조부\n조모\n□ 형제\n□ 자매\n간병인 ]기타\n입원비 지불의 어려움\n있음 ㅇ 없음 ○ 기타\n입원비 지불과 관련한 사회 사업팀 상담 필요 ㅇ있음 없음 ○ 기타\n지난 2주동안 기분이 가라앉거나, 우울하거나, 희망이 없다고 느낀 기간\n없음 ○ 2~3일 이상 ○7일 이상 ○ 거의 매일 ㅇ 확인 불가능\n지난 2주동안 평소 하던 일에 대한 흥미가 없어지거나 즐거움을 느끼지 못한 기간\n없음 ○ 2~3일 이상 ○ 7일 이상 ○ 거의 매일 ○ 확인불가능\n정서 평가 0\n*The Patient Health Questionnaire -2(PHQ-2) (2003) 전자서명자: 이송미\n주 사용 언어 한국어 □ 영어 □ 일본어 □ 중국어 □ 러시아어\n1/3\n기타\n출력일: 2025-03-28\n출력자: 조예은\n세브란스병원\nSEVERANCE HOSPITAL\n원본대조필\n\n등록번호: 7314152\n주민등록번호: 651226-264**** 여/59세\n환자명 : 김태현\n간호정보조사\n2025-01-21\n읽고 쓰는데 어려움\n없음 ㅇ있음\n교육과 진료에 영향을 주는 가치와 신념(Value & belief)\nㅣ없음 ㅇ 있음\n퇴원\n퇴원 후 보호자 (Main care giver)\n배우자\n]자매\n□ 부\n간병인 기타\n모\n자녀\n□ 조부\n조모\n형제\n없음\n퇴원 예정지\n자택 ㅇ친척집 ○타병원\n요양시설 기타\n퇴원 예정 교통수단(Discharge transportation)\n자가 □ 대중 교통\n|기타\n□ 항공\n□ 구급차\n교육 요구도\n교육 대상자\n□ 환자\n보호자\n기타\n원하는 교육 내용\n선호하는 교육 방법\n질병 약물 □ 검사 □ 수술\n구두 유인물 □ 시범 보이기\n자가 간호\n영양\n□ 기타\n|시청각 자료\n영양 상태\n체중변화 1.0kg\n1개월간 체중변화 없음 ○ 증가함 |감소함\n최근 1주일간 식사량 변화 없음 ㅇ 증가 감소\n식이 주의 사항\n없음 ㅇ 열량 조절 체중 조절 ㅇ염분 제한 수분 제한 단백질 제한 지방 제한\n기타\n수면상태\n수면장애\n기능 평가\n없음\n잠들기 어려움 ㅇ수면 후 개운하지 않음 수면중 3회 이상 깸 원하는 시간보다 일찍 깸\n보조기 사용\n없음 ㅇ 목발 ㅇ 지팡이 Owalker ) 휠체어 ㅇ기타\n기능 평가\n일상생활 수행 능력\n식사\n독립적 수행 ㅇ부분 보조 필요 ㅇ 완전 보조\n독립적 수행 가능 ㅇ 준비 시 도움받아 독립적 수행 가능\n모든 과정에서 도움이 필요함 ㅇ 전혀 수행할 수 없음\nㅇ일부의 과정에서 도움이 필요함\n개인 위생\n|독립적 수행 가능 ㅇ준비 시 도움받아 독립적 수행 가능\n일부의 과정에서 도움이 필요함\n모든 과정에서 도움이 필요함 ㅇ 전혀 수행할 수 없음\n목욕\n독립적 수행 가능 ㅇ 감독하에 독립적 수행 가능 ㅇ 일부의 과정에서 도움이 필요함\n모든 과정에서 도움이 필요함 ㅇ 전혀 수행할 수 없음\n옷입기\n독립적 수행 가능 ㅇ 최소의 도움(단추, 지퍼 등)으로 독립적 수행 가능\n도움을 받아 입고 벗을 수 있음\n수행 시 약간의 참여가 가능함 ㅇ 전혀 수행할 수 없음\n화장실\n계단\n걷기\n독립적 수행 가능 ㅇ 감독하에 독립적 수행 가능 ㅇ일부의 과정에서 도움이 필요함\n모든 과정에서 도움이 필요함 ㅇ 전혀 수행할 수 없음\n독립적 수행 가능 ㅇ 감독하에 독립적 수행 가능 ㅇ Walking aid 사용 없이 일부의 과정에서 도움이 필요함\nWalking aid 사용을 포함하여 모든 과정에서 도움이 필요함 ㅇ 전혀 수행할 수 없음\n독립적 수행 가능 (휠체어를 제외한 walking aid 사용할 수 있음) ○ 도움이나 감시 없이는 50m 이상 혼자 걷지 못함\n) 지속적인 Walking aid와 자주 다른 사람의 도움이 필요함 ㅇ 지속적으로 한사람 이상의 도움이 필요함\n) 전적으로 도움이 필요함\n이동 (의자와 침대)\n'독립적 수행 가능 ㅇ 감독하에 독립적 수행 가능 ○이동시 일부의 과정에서 도움이 필요함\nㅇ 지속적으로 한 사람 이상의 도움이 필요함 ㅇ전적인 도움이 필요함\n배변 조절\n조절에 문제 없음 ㅇ조절이 잘 되나 가끔 문제가 발생함\n'자주 문제가 발생하며 기저귀의 도움이 필요함 ㅇ자세를 취해주고 배변 시 도움이 필요함\n변실금이 지속됨\n전자서명자: 이송미\n세브란스병원\nSEVERANCE HOSPITAL\n2/3\n출력일: 2025-03-28\n출력자: 조예은\n원본대조필\n\n등록번호: 7314152\n주민등록번호: 651226-264**** 여/59세\n환자명 : 김태현\n간호정보조사\n배뇨 조절\n조절에 문제 없음 ㅇ가끔 문제가 발생\n실금이 있으나 기구의 도움으로 해결\n낮에는 조절 가능하나 밤에는 도움 필요\n실금이 지속됨(유치 도뇨관)\n기능평가 점수 합계 100\n신체사정\n신경계\n시간 지남력\n장소 지남력\n있음\n있음\n|명확치 않음\n없음\n명확치 않음\n없음\n사람 지남력\n의사 소통\n있음 ㅇ 명확치 않음\n원만함\n없음\n어려움 ㅇ 불가능함\n마비 없음 ㅇ있음 ㅇ 확인 불가능\nWeakness\n없음 ㅇ있음 ㅇ 확인 불가능\n시각\n시각장애\n없음\n있음\n청각\n청각장애\n없음\n있음\n소화기계\n소화기 관련증상\n없음 있음\n순환기계\nPacemaker\n없음\n있음\n부종\n없음\n순환기 관련증상\n있음\n없음\n있음\n호흡기계\n호흡기 관련증상\n없음\n있음\n피부\n피부 온도\n따뜻함 ㅇ뜨거움\n차가움\n피부 습도\n적당함 ㅇ 건조함 ) 축축함\n피부색\n이상없음\n창백\n홍조 청색증\n황달\n피부 변화\n없음\n있음\n전자서명자: 이송미\n세브란스병원\nSEVERANCE HOSPITAL\n2025-01-21\n3/3\n출력일: 2025-03-28\n출력자: 조예은\n원본대조필\n\n등록번호: 7314152\n주민등록번호: 651226-264**** 여/59세\n환자명 : 김태현\n영상검사 CT& MR\n영상검사 CT& MR\n검사명\nCT GU (GYN) Abd+Pel (contrast)\n검사방법\n검사일자\n2025.01.21 20:02\n촬영실\nCT 20호(암병원 2층)\n판독일자\nDescription\n판독의/전문의\n2025.01.22 16:13\nClinical information: Primary peritoneal carcinomatosis\nCl: Abd-Pelvic MR과 비교판독임 IMP: PPC or bilateral HGSC with peritoneal carcinomatosis\nEXTENT:\nConglomerated nodular lesions with both adenexae and adjacent pelvic wall (RO/LO =\n4.8/4.7cm)\nMultiple seeding nodules with irregular thickening involving pelvic peritoneum, both\nparacolic gutters (arrows)\nSeeding nodules in Rt side omentum, transverse mesocolon/lesser omentum (arrows)\nDiffuse irregular thickening and seeding nodules in both subdphg peritoneum including\nhepato-renal recess, associated with ascites\nNo pathologic LNEs, ileus or parenchymal metastasis\nIntact both lower lungs and cardiophrenic area\n◆조영제◆\nlobrix 270 inj[150ml/Btl]-CT용 [lohexol 582.4mg/ml (요오드로서 270mg/ml)] [150ml/\nBtl]:1.0\n정대철/정대철/정대철\n전자서명자: 정대철\n1/1\n출력일: 2025-03-28\n출력자: 조예은\n세브란스병원\nSEVERANCE HOSPITAL\n원본대조필\n\n등록번호: 7314152\n주민등록번호: 651226-264**** 여/59세\n환자명 : 김태현\n검사명\n검사방법\n검사일자\n판독일자\nDescription\n영상검사 CT& MR\n영상검사 CT& MR\nMRI GU Abdomen (인접부위동시검사-비뇨) (noncontrast)\n2025.01.21 20:39\n2025.01.22 16:13\n촬영실\nMRI 78호(본관2층)\nClinical information: Primary peritoneal carcinomatosis\nImaging technique: Axial fat-suppressed T1Wl, axial T2Wl coronal T2WI Contrast media: Not used CI: APCT와 비교판독임 IMP: PPC or bilateral HGSC with peritoneal carcinomatosis\nEXTENT:\nConglomerated nodular lesions with both adenexae and adjacent pelvic wall (RO/LO =\n4.8/4.7cm)\nMultiple seeding nodules with irregular thickening involving pelvic peritoneum, both\nparacolic gutters (arrows)\nSeeding nodules in Rt side omentum, transverse mesocolon/lesser omentum (arrows)\nDiffuse irregular thickening and seeding nodules in both subdphg peritoneum including\nhepato-renal recess, associated with ascites\nNo pathologic LNEs, ileus or parenchymal metastasis\nIntact both lower lungs and cardiophrenic area\n판독의/전문의\n정대철/정대철/정대철\n전자서명자: 정대철\n1/1\n출력일: 2025-03-28\n출력자: 조예은\n세브란스병원\nSEVERANCE HOSPITAL\n원본대조필\n\n등록번호: 7314152\n주민등록번호: 651226-264****여/59세\n환자명: 김태현\n영상검사 CT& MR\n영상검사 CT&MR\n검사명\nMRI GYN Ovary & diffusion (contrast)\n검사방법\n검사일자\n판독일자\n2025.01.21 20:39\n2025.01.22 16:12\n촬영실\nMRI 78호(본관2층)\nDescription\n판독의/전문의\nClinical information: Primary peritoneal carcinomatosis\nImaging technique: Axial T1WI, T2WI, DWI; sagittal T2Wl; coronal T2Wl: contrast\nenhanced dynamic axial T1Wl, contrast enhanced axial/sagittal T1WI Contrast media: Used CI: APCT/MR 비교판독임 IMP: PPC or bilateral HGSC with peritoneal carcinomatosis\nEXTENT:\nConglomerated nodular lesions with both adenexae and adjacent pelvic wall (RO/LO =\n4.8/4.7cm)\nMultiple seeding nodules with irregular thickening involving pelvic peritoneum, both\nparacolic gutters (arrows)\nSeeding nodules in Rt side omentum, transverse mesocolon/lesser omentum (arrows)\nDiffuse irregular thickening and seeding nodules in both subdphg peritoneum including\nhepato-renal recess, associated with ascites\nNo pathologic LNES, ileus or parenchymal metastasis\nIntact both lower lungs and cardiophrenic area\n◆조영제\nGadovist prefilled inj[7.5ml/Syringe] [Gadobutrol 604.72mg/ml] [7.5 ml/Syringe]:1.0\n정대철/정대철/정대철\n전자서명자: 정대철\n1/1\n출력일: 2025-03-28\n출력자: 조예은\n세브란스병원\nSEVERANCE HOSPITAL\n원본대조필\n\n등록번호: 7314152\n주민등록번호: 651226-264****여/59세\n환자명 : 김태현\n영상검사 특수촬영 - 초음파\n영상검사 특수촬영-초음파\n검사명\nU/S 자동유방초음파 - 일반(Breast)\n검사방법\n검사일자\n판독일자\n2025.01.22 09:49\n2025.01.23 10:47\n촬영실\n암)자동유방초음파 검사실\nDescription\n판독의/전문의\nClinical Information: Primary peritoneal carcinomatosis\nUS examination was done with linear transducer> =10 MHz (central frequency) Screening US\nUS background echotexture: 2 - Mild fibroglandular\nRt breast 9시 30분 방향 9cm from nipple 위치에 10mm 크기의 mass 관찰되며\nmammogram 상 관찰된 mass density와 correlation 될 것으로 보임 해당 mass가 이전 2023-04 mammogram과 mammogram 상에서 큰 변화 없는 것을 고려\n하여 probably benign finding으로 assess함 1년 뒤 follow up 권함 그 외에 Rt breast에 small benign lesions 있음 No abnormal calcification or duct dilatation Imp: Category 3; Probable benign finding in Rt breast Advise: Follow up ABUS and mammogram after 1 year 윤지영/윤지영/윤지영\n전자서명자: 윤지영\n1/1\n출력일: 2025-03-28\n출력자: 조예은\n세브란스병원\nSEVERANCE HOSPITAL\n원본대조필\n\n등록번호: 7314152\n주민등록번호: 651226-264****여/59세\n환자명 : 김태현\n검사명\n영상검사 특수촬영 -투시\n영상검사 특수촬영-투시\nMammography (Both)\n검사방법\n검사일자\n2025.01.22 09:51\n판독일자\n2025.01.23 10:35\nDescription\n촬영실\n암)유방촬영 2호\nScreening mammogram\nGrade C Rt upper outer breast에 mass density 관찰되며 2023-04 외부 병원 사진과 변화 없음 US correlation 권함 Rt lower medial\nview 권함 Lt lower central aspect of calcification group magnification\nImp Category 0; Incomplete assessment for Rt breast mass and both breasts\ncalcifications Advise: US correlation and both magnification view 판독의/전문의\n윤지영/윤지영/윤지영\n전자서명자: 윤지영\n세브란스병원\nSEVERANCE HOSPITAL\n1/1\n출력일: 2025-03-28\n출력자: 조예은\n원본대조필 |\n\n등록번호: 7314152\n주민등록번호: 651226-264**\n[**** 여/59세\n환자명 : 김태현\n영상검사 일반촬영\n검사명\nAbdomen Flat, Upright\n검사방법\n검사일자\n판독일자\n2025.01.22 10:02\n2025.01.22 11:35\nDescription\nMild ileus bowel gas pattern\n판독의/전문의\n정보령/정보령/정보령\n전자서명자: 정보령\n세브란스병원\nSEVERANCE HOSPITAL\n영상검사 일반촬영\n촬영실\n암)촬영실 1호\n1/1\n출력일: 2025-03-28\n출력자: 조예은\n원본대조필\n\n등록번호: 7314152\n주민등록번호: 651226-264****여/59세\n환자명 : 김태현\n영상검사 특수촬영 - 핵의학\n영상검사 특수촬영-핵의학\n검사명\nPET-CT Whole Body Scan (Torso, GU, non-contrast)\n검사방법\n검사일자\n판독일자\n2025.01.23 13:22\n2025.01.24 08:32\n촬영실\nPET-CT 38호실(암병원)\nDescription\n판독의/전문의\nHx: Staging (presumed malignancy)\n2025-01 R/O Peritoneal carcinomatosis, R/O associated Lt internal iliac\nlymphandecnopathy with bilateral periovarian metastatic lesions or solid ovarian tumor\n(outside)\n2025-01-21 Cervix liquid cytology (pending) s/pop d/t Peritonitis (outside)\nCA 19-9 51.0 (2025-01-22)\nCA 125 293.0 (2025-01-22)\nHE4 155.0 (2025-01-22)\nTechnique:\nF-18 FDG was given to the patient intravenously PET imaging using a standard protocol was performed from the skull base to the\nproximal thigh The obtained images were reconstructed into axial, sagittal, and coronal planes Low-dose, non-contrast-enhanced CT scan was performed for attenuation correction <<<Findings and impressions>>>\nIncreased FDG uptake in the pelvic cavity, suspicious for ovarian malignancy Diffuse FDG uptake in the whole peritoneum, suggestive of carcinomatosis Increased FDG uptake in the right internal mammary LN, right hilar LNs, suggestive of LN\nmetastasis 강원준/강원준/강원준\n전자서명자: 강원준\n1/1\n출력일: 2025-03-28\n출력자: 조예은\n세브란스병원\nSEVERANCE HOSPITAL\n원본대조필\n\n등록번호: 7314152\n주민등록번호: 651226-264**** 여/59세\n환자명 : 김태현\n입원정보\n입원일자 2025-01-30\n입원과\n산부인과\n입원주치의 김상운\n퇴원정보\n퇴원일자 2025-02-02\n퇴원과 산부인과\n퇴원주치의 김상운\n최종진단명(*)\n순\n한국질병\n구분\n확진\n진단명\n분류번호\n1\n주진단\n확진 Primary peritoneal carcinomatosis\nC48.2\n2\n기타진단\n확진\nOvarian cancer\nC56.9\n과거진단명\n과거진단코드\n주호소 (*)\nOP\n과거력 및 현재병력 본 59세 G3 P2 L2 DO A1 married woman은 DL, 당뇨전단계, s/p 복막염수술(19\n세) 외 특이 과거력 없는 분으로, 하복부 불편감으로 대,소변 보기 어려워 타병원 내\n원하여 EGD,Colonoscopy 시행하여 특이 소견 없음에도 증상 지속되어 시행한 APCT\nr/o peritoneal carcinomatosis r/o associated Lt interiliac lymphandecnopathy\nwith bilateral periovarian metastatic lesions or solid ovarian tumor\nfurther evaluation 및 proper management 위해 김상운 교수님께 refer, baseline\nstudy 시행 받은 후 1/31 D-lapa 시행, 2/1 1st NAC [Genexol 175BSA+ Neoplatin\n5AUC] 시행 후 특이소견 없이 퇴원함 이상 진찰 소견 및 검사소견 (*)\nn-c\n투여된 약물 중 잔류효과로 퇴원 후 주의가 필요한 약물 (★)\n경과요약 (*)\n진단적 복강경검사 (부인과);\n없음\n있음\n1st NAC [Genexol 175BSA+ Neoplatin 5AUC] 2025.02.01\nHt: 158.7cm\n수술/처치명\n수술/처치코드\nWt: 52.5kg\nBSA: 1.52\nCCr: 66.06\nGenexol: 175BSA= 175*1.52 = 266mg\nNeoplatin: 5AUC=5*[66.06+25]= 455.3mg\nDiagnostic laparoscopy (GYN)\n5421\nImplantable Medical Device 사용 여부 No\nYes\n전자서명자: 김상운\n세브란스병원\nSEVERANCE HOSPITAL\n퇴원요약\n1/2\n출력일: 2025-03-28\n출력자: 조예은\n원본대조필\n\n등록번호: 7314152\n주민등록번호: 651226-264****여/59세\n환자명 : 김태현\n치료결과 (*)\n완쾌\n경쾌\n활력증상\n퇴원형태 (*)\n호전안됨 ㅇ 진단뿐\nㅇ48시간이내 사망 148시간 이후 사망\n혈압 114/75 mmHg 맥박수 71 회/분 체온 36.5 C 호흡수 20\n퇴원지시후 ㅇ타병원전원 ㅇ자의퇴원 탈원\n가망없는 퇴원\n회/분\n향후 치료계획\n외래 추후관리 안내받은 예약일에 외래 내원합니다 Pathology 확인 필요합니다 재입원\n없음\n기타\n담당 전공의사명\n없음\n기록자명\n문한나(의사)\n주치의사명\n김상운\n<약어 설명>\nA repair Anterior repair\nANC Antenatal care\nBO Bilateral oophorectomy\nBOC Bilateral ovarian cystectomy\nBS Bilateral salpingectomy\nC/S : Cesarean section\nCPD Cephalopelvic disproportion\nDCB: Dilatation, curettage, biopsy\nET: Embryo transplantation\nIDS Internal debulking operation\nIM: Intramural lapa: Laparoscopic\nLOC Left ovarian cystectomy\nLS: Left salpingectomy\nP repair Posterior repair\nPALND: Para-aortic lymph node dissection\nPLD Pelvic lymphnode dissection\nPPD Postpartum day\nROC Right ovarian cystectomy\nROP Right occiput posterior\nRS Right salpingectomy\nSLND Sentinel lymphnode dissection\nSPA Single port access\n퇴원요약\n전자서명자: 김상운\n2/2\n출력일: 2025-03-28\n출력자: 조예은\n세브란스병원\nSEVERANCE HOSPITAL\n원본대조필\n\n등록번호: 7314152\n주민등록번호: 651226-264**** 여/59세\n환자명 : 김태현\n수술일\n2025-01-31\n집도의\n김상운\n보조의(1)\n보조의(3)\n수술보조간호사 최진범\n수술전 진단명\n진단명\nPrimary peritoneal carcinomatosis\nOvarian cancer\n진단 부가 설명 s/p Appendectomy, c/sec 수술후 진단명\n진단명\nPrimary peritoneal carcinomatosis\nOvarian cancer\n보조의 (2)\n보조의(4)\n수술명\n진단 부가 설명 s/p Appendectomy, c/sec Omentoperitoneal and ovario-intestinal adhesion\n수술명\nDiagnostic laparoscopy (GYN)\nSingle-port laparoscopic adhesiolyssis and partial omentectomy including omental\ncake Anesthesia\nGEA\nSpinal\nOther\nPCA\nEpidural\nIV\nNot done\nPosition\nsupine\nlithotomy\nother\nPreparation and drap as usual sterile manner\nInsufflation\nGasless\nCO2 gas\nOther\nVerres needle use\nYes\nNo\nPelvic exam\nExternal genitalia\nfree\nother\nCervix\nnulliparous\nparous\nother\nUterus\n✓ A-V\n☐ R-V\nNormal size\n☐ Other Enlarged to\nweeks Other\nAdnexae\nfree\nother\nA sound was passed through cervical canal to\nTrocar for camera (05mm ○ 10mm\n☐ Supraumbilical\nUmbilical\n전자서명자: 김상운\n세브란스병원\nSEVERANCE HOSPITAL\nInfraumbilical\n✓ Other Single port\ncm depth\n12 mm)\n수술기록\n1/4\n출력일: 2025-03-28\n출력자: 조예은\n원본대조필\n\n등록번호: 7314152\n주민등록번호: 651226-264****여/59세\n환자명 : 김태현\nNumber of working port\n1\n2\n3\n4\n○ 5 6\nLocation of working port\n☐ Mcburney point\nCounter-Mcburney point\nSuprapubic\n5cm above the Mcburney point\n5cm above the counter-Mcburney point\n10cm above Mcburney point\nOperation finding\nOther\nUterus\nSize\nnormal size\nenlarged to\nweeks\nother\nShape\nglobular\nother\nMyoma\nNo\nYes\nAdenomyosis\nNo\nYes\nAdnexae\nRt Ovary\nnormal\nother\nnot visible due to adhesion\nRt Tube\nnormal\nother\nnot visible\nLt Ovary\nnormal\nother\nOvario-sigmoid colon adhesion,\nLt Tube\nnormal\nother\nOvario-sigmoid colon adhesion\nAdhesion\nNo\nYes\nRemarkable other findings\nOvario-sigmoid colon adhesion and omentoperitoneal adhesion was noted After\nadhsiolysis of omental cake was exposed and partial omentectomy was done Laparoscopic parameter\nSuperficial liver metastasis\n0\n2\nStomach infiltration\n0\n2\nBowel infiltration\n0\n2\nOmental cake\n0\n2\nPeritoneal carcinomatosis\n0\n2\nDiaphragmatic carcinomatosis\n0\n2\nTotal score\n8\nMesenteral retraction\n2\nSpecimen retrieval\nVia\nUmbilicus\nEndopouch 사용여부\nYes\nAny other troca but umbilicus\nNo\nVagina\nSpecific instrument 사용여부\nMorcellator\nEndoknife\nAntiadhesive agent\nNo\nYes Gardix Susulen\nAntihemorrhagic agent\nNo\nYes\nSurgiguard\nHemostasis with\nSuture\nCauterization\nHemostatic agent\nAbdominal wall closure\n-\nPeritoneum :\nCCG\nVicryl\nOther\n-\nFascia layer:\nVicryl\nSilk\nOther\n- Subcutaneous layer:\nNo\nVicryl\nSilk\nOther\n전자서명자: 김상운\n세브란스병원\nSEVERANCE HOSPITAL\n2/4\n수술기록\n출력일: 2025-03-28\n출력자: 조예은\n원본대조필\n\n등록번호: 7314152\n주민등록번호: 651226-264**** 여/59세\n환자명 : 김태현\n-\nSkin :\n☐ nylon\nstapler\nOther\nEstimated blood loss (cc)\n수술과정 중 특이사항\n10\nNo\nYes\nTissue to Pathology\nNo\nYes\nDrains\nNo\nYes\nSponge count correct\nNo\nYes\n전자서명자: 김상운\n세브란스병원\nSEVERANCE HOSPITAL\n수술기록\n3/4\n출력일: 2025-03-28\n출력자: 조예은\n원본대조필\n\n등록번호: 7314152\n주민등록번호: 651226-264****여/59세\n환자명: 김태현\n기록자명\n김상운\n수술기록\n전자서명자: 김상운\n4/4\n출력일: 2025-03-28\n세브란스병원\nSEVERANCE HOSPITAL\n출력자: 조예은\n원본대조필\n\n등록번호: 7314152\n주민등록번호: 651226-264**** 여/59세\n환자명 : 김태현\n입원일자\n2025-01-30\n입원과\n산부인과\n입원주치의 김상운\n주호소\nPresent illness\nOP\n59 G3 P2 L2 DO A1 married woman DL,\ns/p op d/t perforated\nappendix (19세), s/pc/s 외 특이 과거력 없는 분으로, 하복부 불편감으로 대,소변 보기\n어려워 타병원 내원하여 EGD,Colonoscopy 시행하여 특이 소견 없음에도 증상 지속되\nAPCT r/o peritoneal carcinomatosis r/o associated Lt interiliac\nlymphandecnopathy with bilateral periovarian metastatic lesions or solid ovarian\ntumor 확인되어 further evaluation 및 proper management 위해 김상운 교수님께\nrefer, baseline study 시행 받은 후 금번 D-lapa 시행 위해 입원함 Virgin\nNo\nYes\n임신력\nG\n3\nP 2 L 2 DOA 1\nPast history\nMenarche No\nYes\n16\nMenopause\nNo\nYes 54\nMarriage\nNo\nYes\nLast delivery\nNo\nYes 1996\nContraception method\nLast D & E history\nNo\nYes\nNone Oral pill\nOIUD\n○ s/p LBTL or BTL\nHusband-vasectomy\nOther\nPast OB-GYN history\nLast PAP smear ☐ none\n2025\nY 01\nM\nOnl\nabnl\n- NSVD\nNo\nYes\nC/sec\nNo\nYes 2'93,'96\nInduced abortion\nNo\nYes\nSpontaneous abortion No Yes\nOthers\nPosthysterctomy status\nNo\nYes\nLNMP\n2024-12-27\nPMP\nMenstrual history\nRegularity\nInterval\n(days)\nDuration\ndays\n(days)\nAmount\nPain(VAS)\nMedico-surgical illness\n전자서명자: 김상운\n세브란스병원\nSEVERANCE HOSPITAL\n입원기록\n1/4\n출력일: 2025-03-28\n출력자: 조예은\n원본대조필\n\n등록번호: 7314152\n주민등록번호: 651226-264**** 여/59세\n환자명 : 김태현\n입원기록\nHypertension No\nYes\nDM\nNo\nYes\nHepatitis\nNo\nYes\nPul Tbc\nNo\nYes\nOperation history No\nYes\nOther Cancer history\nNONE\nCardiac disease\nNo\nYes\nNo\nYes\nOld CVA\nOther\nSocial history\nSmoking\nNo\nYes\nAlcohol\n○ No\nYes\nAllergy\nDrug\nNo\nYes\n항생제\n진통제\n조영제\n기타\nFood 및 기타\nNo\nYes\nOther\n신체조사\nGeneral appearance\nSkin\nHEENT\nNeck\nChest/lung\nHeart\nAbdomen\nTenderness\nNo\n이상소견 없음\n・이상소견 없음\n이상소견 없음\n이상소견 없음\n이상소견 없음\n이상소견 없음\n이상소견 없음\n☐ direct\nBowel sound\nPalpation of organ\nNo\nliver\nkidney\nspleen\nuterus\nAbdomen\n전자서명자: 김상운\n세브란스병원\nSEVERANCE HOSPITAL\n이상소견 있음\n이상소견 있음\n이상소견 있음\n이상소견 있음\n이상소견 있음\n이상소견 있음\n이상소견 있음\nrebound\n2/4\n출력일: 2025-03-28\n출력자: 조예은\n원본대조필\n\n등록번호: 7314152\n주민등록번호: 651226-264****여/59세\n환자명 : 김태현\n입원기록\ns/pop d/t\nperforated appe'\ns/pc/s\nBack and extremity\n이상소견 없음\n이상소견 있음\nPelvic examination\n감염성질환 초기평가\n이상소견 없음\n이상소견 있음\n1 증상 및 기간\n□ 발열\n기간\n일전\n|호흡기증상\n기간\n일전\n소화기증상\n기간\n일전\n해당없음 (미상환자 포함)\n2 최근 1달 이내 방문한 나라\n3 최근 1달 이내 국내 신종감염병 위험지역 또는 병원 방문\n4 밀접 접촉자\n5 신종 감염병 의심환자\nPrimary peritoneal carcinomatosis\n해당없음\n|해당없음\n없음\n있음\n없음\n있음\n아니오 예\n예\n아니오\n추정진단\nPlan\n☑ OP\nGYN sono\nConservative management\nChemotherapy\nothers\n퇴원계획\n퇴원 후 치료식이 여부\nN ☐ Y\n추후 관리 계획\n]가정간호사업소\n호스피스\n타 병원 전원\n외래\n전자서명자: 김상운\n3/4\n출력일: 2025-03-28\n세브란스병원\nSEVERANCE HOSPITAL\n출력자: 조예은\n원본대조필\n\n등록번호: 7314152\n주민등록번호: 651226-264****여/59세\n환자명 : 김태현\n사회 복지서비스 연계 필요성\n✓ N ☐ Y\n기타 퇴원시 요구사항\n치료계획\n+\nProblem\nGoal\n부\n목표일\n수정목표일 계획일\nPrimary peritoneal\noperation without\n2025-02-06\n2025-01-30\ncarcinomatosis\ncomplication\n기록자명 이다혜(의사)\n<약어 설명>\nG: gravida\nP: para\nL: living\nD: dead\nA: Abortion\nabnl abnormal\nA-V Anteversion\nBTL bilateral tubal ligation\nC/sec cesarian section\nCVA cerebrovascular accident\nD&E Dilatation and evacuation\nDM diabetes mellitus\nDOE dyspnea on exertion\nGYN: Gynecology\nPAP Papanicolaou\nPMI point of maximum intensity\nHSIL High Grade Squamous Intraepithelial Lesion\nPMP previous menstrual period\nPul Tbc pulmonary tuberculosis\nICS intercostal space\nIUD intrauterine device\nLBTL laparoscopic bilateral tubal ligation RCC: renal cell carcinoma\nLMCL Left Midclavicular Line\nLNMP last normal menstrual period\nRHB regular heart beat\nRT: Right\nLSIL: Low Grade Squamous Intraepithelial Lesion\nLT: Left\nM: Month\nnl : Normal\nR-V Retroversion\nVAS Visual analog pain scale\nY: Year\nAG-H atypical glandular cells cannot exclude a high-grade squamous intraepithelial lesion\nAGUS atypical glandular cells of undetermined significance\nASC-H atypical squamous cells cannot exclude a high-grade squamous intraepithelial lesion\nASCUS atypical squamous cells of undetermined significance\n전자서명자: 김상운\n세브란스병원\nSEVERANCE HOSPITAL\n입원기록\n4/4\n출력일: 2025-03-28\n출력자: 조예은\n원본대조필\n\n등록번호: 7314152\n주민등록번호: 651226-264**** 여/59세\n환자명 : 김태현\n연령 구분\n영유아기 ) 학령전기\n학령기\n청소년기\n성인\n분류\n일반 ○ 산모 ㅇ정신\n현병력\n주 증상 및 내원 과정 금번 D-lapa 시행 위해 입원함 간호정보조사\n2025-01-30\n복용중인 약\n없음\n있음\n투약 상태\n1회 투여개수\n1회 투여량\n약품명\n횟수\n용법 및 투여시간\n약품코드 유효함량\n수량 단위\n용량 단위\n[Livial[2.5mg/T]\n1\nT\n2.5\nmg\n1\nDicamax D[1T/T]\n1\nT\n1\nT\n1\nPO 8am (1/17~자의 skip 중)\nPO 8am (1/17~ 자의 skip 중)\nLivalo[2mg/T]\n1\nT\n2\nmg\n1\nPO 8am (1/17~자의 skip 중)\nMontezal[10mg/1정] 1\nT\n10\nmg\n3\nPO\nTwolion[10mg/1정]\n1\nT\n10\nmg\n3\nPO\nMaxibupen ER[O.3g/11\nT\n13\n0.3\ng\n3\nPO\n[정]\n[Ambrocol[/1정]\n0.5\nT\n0\n3\nPO\nD2LIVI01 2.500\nD2DICA02 1,000\nDZLIVA02 2.000\nP00000000 10\n06864\nP00000000 10\n30644\nP00000000 0.3\n03177\nC00000000\n05982\nMoktin(일시품절)\n1\nC\n200\nmg\n3\nPO\n[200mg/C]\nOrocin[0.1g/1정]\n1\nT\n0.1\ng\n3\nPO\nD2MOKT01 200.000\nOFLX100TA 0.1\nBO192\n내원 시 환자 상태\n통증\n없음\n있음 ㅇ 입원 전에 있었음\n통증 부위 □ 전신통 □ 흉통 복통 □ 관절통 □ 두통 □ 요통 □ 상세부위\n통증 강도 2\n통증 양상 □ 둔함 쑤심 □ 퍼짐 □ 예리함 □ 찌르는듯함 |기타\n통증평가도구 NPIS(The Numerical Pain Intensity Scale)\n빈도\nㅇ 지속적\n) 간헐적 일정하지 않음\n지속기간 일정하지 않음\n악화 요인\n완화 요인\n과거력\n과거병력\n없음\n있음\n□ 고혈압\n입원 및 수술 이력\n당뇨 □ 결핵 □ 암\n없음 있음 ㅇ 알 수 없음\n간염 □ 경련 기타 DL, 당뇨전단계\n입원 및 수술 이력\n입원시 진단명 및 수술명\n입원 및 수술 시기\n복막염 수술\n제왕절개 수술\n1984\n1993,1996\n가족력\n없음 있음\n모: 자궁암\n음주력\nnondrinker ex-drinker\ncurrent drinker\nG\n흡연력\nnonsmoker ex-smoker\ncurrent smoker\nAllergy □ 없음 □ 약 □ 식품\n일반정보(심적/사회적/경제적/영적/문화/종교적 평가)\n결혼 상태\n미혼 기혼 ㅇ 별거 ㅇ 이혼 ㅇ사별 ○ 해당 없음\n종교\n없음 ○ 기독교 천주교 불교 ㅇ기타\n전자서명자: 윤경은\n세브란스병원\nSEVERANCE HOSPITAL\n1/3\n출력일: 2025-03-28\n출력자: 조예은\n원본대조필\n\n등록번호: 7314152\n주민등록번호: 651226-264**** 여/59세\n환자명 : 김태현\n간호정보조사\n2025-01-30\n원목 연락\n원함 원하지 않음\n보호자 (Main caregiver)\n□ 없음\n배우자\n부\n모\n자녀\n□ 조부\n조모\n형제\n□ 자매\n□ 간병인 □ 기타\n입원비 지불의 어려움\n있음 없음 ○ 기타\n입원비 지불과 관련한 사회 사업팀 상담 필요 ) 있음 없음 ○ 기타\n지난 2주동안 기분이 가라앉거나, 우울하거나, 희망이 없다고 느낀 기간\n없음 ○ 2~3일 이상 ○7일 이상 ○ 거의 매일 확인 불가능\n지난 2주동안 평소 하던 일에 대한 흥미가 없어지거나 즐거움을 느끼지 못한 기간\n없음 ○ 2~3일 이상 ○7일 이상 ○ 거의 매일 ○ 확인불가능\n정서 평가 0\n*The Patient Health Questionnaire -2(PHQ-2) (2003) 주 사용 언어 한국어 □ 영어 □ 일본어 □ 중국어 □ 러시아어 □ 기타\n읽고 쓰는데 어려움\n없음 ㅇ있음\n교육과 진료에 영향을 주는 가치와 신념(Value & belief)\n없음 있음\n퇴원\n퇴원 후 보호자 (Main care giver)\n배우자 □ □ 모 □ 자녀 □ 조부\n|자매 □ 간병인 □ 기타\n조모\n□ 형제\n없음\n퇴원 예정지\n자택 ㅇ 친척집\n타병원\n퇴원 예정 교통수단(Discharge transportation)\n요양시설 ㅇ기타\n자가 □ 대중 교통\n기타\n항공 □ 구급차\n교육 요구도\n교육 대상자\n원하는 교육 내용\n|환자\n질병\n보호자 □ 기타\n약물 □ 검사 □ 수술 |자가 간호\n영양 □ 기타\n선호하는 교육 방법 구두 □ 유인물 □ 시범 보이기 □ 시청각 자료\n영양 상태\n1개월간 체중변화 ㅣ없음 ㅇ 증가함 ㅇ 감소함\n체중변화 kg\n최근 1주일간 식사량 변화 없음 ○ 증가 •감소\n식이 주의 사항 「없음 ㅇ 열량 조절 ㅇ 체중 조절 ○ 염분 제한 ○ 수분 제한 ○ 단백질 제한 지방 제한\n수면상태\n기타\n수면장애\n기능 평가\n없음 ○ 잠들기 어려움 ○ 수면 후 개운하지 않음 수면중 3회 이상 깸 원하는 시간보다 일찍 깸\n보조기 사용\n기능 평가\n없음 '목발 ○ 지팡이 Owalker 휠체어 ○ 기타\n일상생활 수행 능력 '독립적 수행 ㅇ 부분 보조 필요 ㅇ 완전 보조\n식사\n|독립적 수행 가능 ㅇ준비 시 도움받아 독립적 수행 가능\n모든 과정에서 도움이 필요함 ㅇ 전혀 수행할 수 없음\nㅇ일부의 과정에서 도움이 필요함\n개인 위생\n독립적 수행 가능 ㅇ 준비 시 도움받아 독립적 수행 가능 ㅇ일부의 과정에서 도움이 필요함\n모든 과정에서 도움이 필요함 ㅇ 전혀 수행할 수 없음\n목욕\n독립적 수행 가능 ㅇ 감독하에 독립적 수행 가능 ○ 일부의 과정에서 도움이 필요함\n모든 과정에서 도움이 필요함 ㅇ 전혀 수행할 수 없음\n옷입기\n독립적 수행 가능 ㅇ 최소의 도움(단추, 지퍼 등)으로 독립적 수행 가능 ○ 도움을 받아 입고 벗을 수 있음\n수행 시 약간의 참여가 가능함 ㅇ 전혀 수행할 수 없음\n전자서명자: 윤경은\n세브란스병원\nSEVERANCE HOSPITAL\n2/3\n출력일: 2025-03-28\n출력자: 조예은\n원본대조필\n\n등록번호: 7314152\n주민등록번호: 651226-264**** 여/59세\n환자명: 김태현\n화장실\n독립적 수행 가능 ㅇ 감독하에 독립적 수행 가능\n모든 과정에서 도움이 필요함 ㅇ 전혀 수행할 수 없음\n일부의 과정에서 도움이 필요함\n계단\n걷기\n간호정보조사\n2025-01-30\n독립적 수행 가능 ㅇ 감독하에 독립적 수행 가능 O Walking aid 사용 없이 일부의 과정에서 도움이 필요함\nWalking aid 사용을 포함하여 모든 과정에서 도움이 필요함 ㅇ 전혀 수행할 수 없음\n) 독립적 수행 가능 (휠체어를 제외한 walking aid 사용할 수 있음) ○ 도움이나 감시 없이는 50m 이상 혼자 걷지 못함\n) 지속적인 Walking aid와 자주 다른 사람의 도움이 필요함 ㅇ 지속적으로 한사람 이상의 도움이 필요함\nㅇ 전적으로 도움이 필요함\n이동 (의자와 침대)\n독립적 수행 가능 ㅇ 감독하에 독립적 수행 가능 ㅇ 이동시 일부의 과정에서 도움이 필요함\n지속적으로 한 사람 이상의 도움이 필요함 ㅇ전적인 도움이 필요함\n배변 조절\n조절에 문제 없음 ㅇ조절이 잘 되나 가끔 문제가 발생함\n자주 문제가 발생하며 기저귀의 도움이 필요함 ㅇ자세를 취해주고 배변 시 도움이 필요함\n변실금이 지속됨\n배뇨 조절\n조절에 문제 없음 ㅇ가끔 문제가 발생\n실금이 있으나 기구의 도움으로 해결\nㅇ낮에는 조절 가능하나 밤에는 도움 필요\n실금이 지속됨(유치 도뇨관)\n기능평가 점수 합계 100\n신체사정\n신경계\n시간 지남력\n있음\n명확치 않음\n없음\n장소 지남력\n사람 지남력\n의사 소통\n있음\n있음\n원만함\n명확치 않음\n명확치 않음\n없음\n없음\n어려움 ㅇ 불가능함\n마비\n없음 있음\n확인 불가능\nWeakness\n없음\n있음 ㅇ 확인 불가능\n시각\n시각장애\n없음\n있음\n청각\n청각장애\n없음\n있음\n소화기계\n소화기 관련증상\n없음\n있음\n순환기계\nPacemaker\n없음\n있음\n부종\n없음\n있음\n순환기 관련증상\n없음\n) 있음\n호흡기계\n호흡기 관련증상\n없음\n있음\n피부\n피부 온도\n피부색\n따뜻함 뜨거움\n이상없음\n피부 변화\n없음\n) 차가움\n피부 습도\n창백 ) 홍조 ○ 청색증 ㅇ 황달\n있음\n적당함\n건조함\n축축함\n전자서명자: 윤경은\n3/3\n출력일: 2025-03-28\n출력자: 조예은\n세브란스병원\nSEVERANCE HOSPITAL\n원본대조필\n\n등록번호: 7314152\n주민등록번호: 651226-264**** 여/59세\n환자명: 김태현\n진료과\n산부인과\n주치의\n김상운\nProgress\n2025/1/31 D-lapa- ovarian cancer stage 4B\nPresence of carcinoma, favoring high-grade serous carcinoma\n(HGSC)\n2025/2/1 1st NAC [Genexol 175BSA+ Neoplatin 5AUC]\nviscum\ngBRCA1,2,\nHRD\nrec 2nd NAC akynzeo neulapeg\n진단명\n구분\n확진\n진단명\n주진단\n기타진단\nOvarian cancer\n확진 Primary peritoneal carcinomatosis\n확진\n기록자명\n김상운(의사)\n전자서명자: 김상운\n세브란스병원\nSEVERANCE HOSPITAL\n외래재진기록\n2025-02-17\n1/1\n출력일: 2025-03-28\n출력자: 조예은\n원본대조필\n\n등록번호: 7314152\n주민등록번호: 651226-264****여/59세\n환자명: 김태현\n영상검사 일반촬영\n영상검사 일반촬영\n검사명\nChest PA\n검사방법\n검사일자\n2025.02.17 13:49\n촬영실\n암)촬영실 2호\n판독일자\n2025.02.17 14:53\nDescription\nNo active lung disease 판독의/전문의\n허진/허진/허진\n전자서명자: 허진\n세브란스병원\nSEVERANCE HOSPITAL\n1/1\n출력일: 2025-03-28\n출력자: 조예은\n원본대조필\n\n등록번호: 7314152\n주민등록번호: 651226-264**\n*****여/59세\n환자명 : 김태현\n검사명\nBRCA1 sequencing[Whole blood]\n의뢰과\n산부인과\n의뢰의\n김상운\n검체접수일\n검체명\n진단명\n2025-02-17\nWhole blood\nOvarian cancer; Primary peritoneal carcinomatosis;\n검사결과\nNot detected\n상세정보 및 comment\n본 환자의 BRCA1 유전자 검사결과 의미있는 돌연변이는 관찰되지 않았습\n니다 유전성 유방암·난소암 증후군(Hereditary breast and ovarian cancer\nsyndrome; HBOC)은 BRCA1 혹은 BRCA2 유전자의 선천성 돌연변이에 의\n해서 발생하며 상염색체 우성으로 유전하여 돌연변이를 가진 환자에서는\n유방암, 난소암, 전립선암 및 췌장암의 위험도가 크게 증가하는 것으로 알\n려져 있습니다 본 검사는 BRCA1 유전자의 23개 단백합성 엑손(coding\nexon) 혹은 BRCA2 유전자의 27개 단백합성 엑손 및 인접한 인트론\n(flanking intron) 부위를 염기서열분석법으로 검사하며, 발현조절 부위\n(regulatory region) 또는 엑손에서 멀리 떨어진 인트론(deep intron)의 돌\n연변이는 검출할 수 없습니다 유전자 일부의 대규모 결실(large deletion)\n혹은 중복(duplication)도 일부 검출이 가능하나 엑손 1~2개 정도의 작은\n결실 혹은 증폭은 검출되지 않을 수 있습니다 <References>\nJ Natl Cancerlnst 2010: 102 (24): 1874-1878 N Engl J Med 2007: 357 (2): 115-123 Am J Hum Genet 2003: 72 (5): 1117-1130 <Databases used>\nOnline Mendelian Inheritance in Man (OMIM), Human Gene Mutation\nDatabase (HGMD), ClinVar, dbSNP, 1000 Genome, Exome Aggregation\nConsortium (ExAC), Exome Sequencing Project (ESP), Korean Reference\nGenome Database (KRGDB), Breast Cancer Information Core (BIC) 검사정보\n검사방법: 염기서열분석법\n표적유전자: BRCA1 (breast cancer 1, early onset) on chromosome\n17q21\n분석위치: coding exon (2-23) and flanking intron (exon-intron\nboundaries: ± 20 base pairs)\n대상질환: 유전성유방암-난소암 증후군(Hereditary breast and ovarian\ncancer syndrome; HBOC)\n유전양상: 상염색체우성 (Autosomal dominant)\n표준염기서열: NM_007294.3\n보고일\n2025-02-27\n검사자1\n강지웅\n전자서명자: 원동주\n세브란스병원\nSEVERANCE HOSPITAL\n진단유전 검사 결과\n2025-02-27\n직종 M.T 면허번호 38045\n원내번호 86140\n1/2\n출력일: 2025-03-28\n출력자: 조예은\n원본대조필\n\n등록번호: 7314152\n주민등록번호: 651226-264**** 여/59세\n환자명 : 김태현\n검사자2\n진단유전 검사 결과\n직종\n면허번호\n원내번호\n판독의\n원동주\n직종 M.D\n면허번호 120916\n원내번호\n확인자(전문의)1 원동주\n확인자(전문의)2\n직종\n직종\nM.D\n면허번호\n면허번호\n120916\n원내번호\n원내번호\n확인자(전문의)3\n직종\n면허번호\n원내번호\n확인자(전문의)4\n직종\n면허번호\n원내번호\n전자서명자: 원동주\n세브란스병원\nSEVERANCE HOSPITAL\n2/2\n2025-02-27\n출력일: 2025-03-28\n출력자: 조예은\n원본대조필\n\n등록번호: 7314152\n주민등록번호: 651226-264****여/59세\n환자명 : 김태현\n입원정보\n입원일자 2025-02-21\n입원과\n산부인과\n입원주치의 김상운\n퇴원정보\n퇴원일자 2025-02-22\n퇴원과 산부인과\n퇴원주치의 이용재\n최종진단명(*)\n순\n한국질병\n구분\n확진\n진단명\n서\n분류번호\n1 주진단\n확진 Primary peritoneal carcinomatosis\nC48.2\n2\n기타진단\n확진 Ovarian cancer\nC56.9\n과거진단명\n과거진단코드\n주호소 (★)\nCTX\n과거력 및 현재병력 본 59세 G3 P2 L2 DO A1 married woman은 DL, 당뇨전단계, s/pop d/t perforated\nappendix (19세), s/pc/s 외 특이 과거력 없는 분으로, 하복부 불편감으로 대,소변 보\n기 어려워 타병원 내원하여 EGD,Colonoscopy 시행하여 특이 소견 없음에도 증상 지\n속되어 시행한 APCT 상r/o peritoneal carcinomatosis r/o associated Lt interiliac\nlymphandecnopathy with bilateral periovarian metastatic lesions or solid ovarian\ntumor 확인되어 further evaluation 및 proper management 위해 김상운 교수님께\nrefer, s/p_D-lapa('25-1-31) 시행후 NAC C1 [Genexol 175BSA+ Neoplatin 5AUC]\n('25.02.01~) 후 퇴원한 분으로 2025.02.21 NAC C2 [Genexol 175BSA + Neoplatin\n5AUC] 시행 후 퇴원함 이상 진찰 소견 및 검사소견 (*)\nn-c\n투여된 약물 중 잔류효과로 퇴원 후 주의가 필요한 약물 (★) 없음 ㅇ있음\n경과요약 (*)\n수술/처치명\n수술/처치코드\n2025.02.21 NAC C2 [Genexol 175BSA+ Neoplatin 5AUC]\n2025.02.21 NAC C2 [Genexol 175BSA+ Neoplatin 5AUC]\nImplantable Medical Device 사용 여부 No\n퇴원요약\nYes\n치료결과 (*)\n완쾌\n경쾌\n호전안됨\n진단뿐 ㅇ가망없는 퇴원\n48시간이내 사망\n활력증상\n퇴원형태 (*)\n48시간이후 사망\n혈압 120/80 mmHg 맥박수 72 회/분\n퇴원지시후\n•자의퇴원\n•타병원전원\n체온 36.5 C 호흡수 20\nㅇ 탈원\n회/분\n향후 치료계획\n외래 추후관리\n재입원 3/14 opd\n없음\n전자서명자: 이용재\n세브란스병원\n1/2\n출력일: 2025-03-28\n출력자: 조예은\n원본대조필\nSEVERANCE HOSPITAL\n\n등록번호: 7314152\n주민등록번호: 651226-264**\n*****여/59세\n환자명 : 김태현\n퇴원요약\n기타\n담당 전공의사명\n없음\n기록자명\n김지환(의사)\n주치의사명\n이용재\n<약어 설명>\nA repair Anterior repair\nANC Antenatal care\nBO Bilateral oophorectomy\nBOC Bilateral ovarian cystectomy\nBS Bilateral salpingectomy\nC/S Cesarean section\nCPD Cephalopelvic disproportion\nDCB: Dilatation, curettage, biopsy\nET Embryo transplantation\nIDS Internal debulking operation\nIM : Intramural lapa: Laparoscopic\nLOC: Left ovarian cystectomy\nLS: Left salpingectomy\nP repair Posterior repair\nPALND: Para-aortic lymph node dissection\nPLD Pelvic lymphnode dissection\nPPD Postpartum day\nROC Right ovarian cystectomy\nROP Right occiput posterior\nRS Right salpingectomy\nSLND Sentinel lymphnode dissection\nSPA Single port access\n전자서명자: 이용재\n2/2\n출력일: 2025-03-28\n출력자: 조예은\n세브란스병원\nSEVERANCE HOSPITAL\n원본대조필\n\n등록번호: 7314152\n주민등록번호: 651226-264**** 여/59세\n환자명 : 김태현\n입원일자\n2025-02-21\n입원과\n산부인과\n입원주치의 김상운\n주호소\nPresent illness\nCTX\n59 G3 P2 L2 DO A1 married woman DL,\ns/p op d/t perforated\nappendix (19세), s/pc/s 외 특이 과거력 없는 분으로, 하복부 불편감으로 대,소변 보기\n어려워 타병원 내원하여 EGD,Colonoscopy 시행하여 특이 소견 없음에도 증상 지속되\nACT r/o peritoneal carcinomatosis r/o associated Lt interiliac\nlymphandecnopathy with bilateral periovarian metastatic lesions or solid ovarian\ntumor 확인되어 further evaluation 및 proper management 위해 김상운 교수님께\nrefer, s/p D-lapa ('25-1-31) ANAC C1 [Genexol 175BSA + Neoplatin 5AUC]\n('25.02.01~) 후 퇴원한 분으로 금번 C2 위해 입원함 Virgin\nNo\nYes\n임신력\nG 3\nP 2 L 2 DO A 1\nPast history\nMenarche\nNo\nYes\n16\nMenopause\nNo\nYes\n54\nMarriage\nNo\nYes\nLast delivery\nNo\nYes 1996\nContraception method\nLast D & E history\nNo Yes\nNone Oral pill\nHusband-vasectomy\nOIUD\nOther\nOs/p LBTL or BTL\nPast OB-GYN history\nLast PAP smear ☐ none\n2025\nnl\nY 01\nM\nabnl\n-\n-\nNSVD\nNo\nYes\nC/sec\nNo\nYes 2'93,'96\nInduced abortion\nNo\nYes\nSpontaneous abortion No\nYes\nOthers\nPosthysterctomy status\nNo\nYes\nLNMP 2024-12-27\nPMP\nMenstrual history\nRegularity\nInterval\n(days)\nDuration\ndays\n(days)\nAmount\nPain(VAS)\nMedico-surgical illness\n전자서명자: 김상운\n세브란스병원\nSEVERANCE HOSPITAL\n입원기록\n1/4\n출력일: 2025-03-28\n출력자: 조예은\n원본대조필\n\n등록번호: 7314152\n주민등록번호: 651226-264**** 여/59세\n환자명 : 김태현\n입원기록\nHypertension No\nYes\nDM\nNo Yes\nHepatitis\nNo\nYes\nPul Tbc\nNo\nYes\nOperation history ☐ No Other Cancer history\nYes\nCardiac disease\nNONE\nNo\n○ Yes\nNo\n> Yes\nOld CVA\nOther\nSocial history\nSmoking\nNo\nYes\nAlcohol\nNo\nYes\nAllergy\nDrug\nNo\nYes\n항생제\n진통제\n조영제\n|기타\nFood 및 기타\nNo\nYes\nOther\n신체조사\nGeneral appearance\nSkin\nHEENT\nNeck\nChest/lung\nHeart\nAbdomen\nTenderness\nNo\n이상소견 없음\n이상소견 없음\n이상소견 없음\n이상소견 없음\n이상소견 없음\n이상소견 없음\n・이상소견 없음\ndirect\nBowel sound\nnormoative\nPalpation of organ ☑ No liver\nkidney\nspleen\nuterus\nAbdomen\n이상소견 있음\n이상소견 있음\n이상소견 있음\n이상소견 있음\n이상소견 있음\n이상소견 있음\n이상소견 있음\n☐ rebound\n전자서명자: 김상운\n세브란스병원\n2/4\n출력일: 2025-03-28\n출력자: 조예은\n원본대조필\nSEVERANCE HOSPITAL\n\n등록번호: 7314152\n주민등록번호: 651226-264****여/59세\n환자명 : 김태현\n입원기록\ns/pop d/t\nperforated\nappe'\ns/pc/s\nBack and extremity\nPelvic examination\n이상소견 없음\n이상소견 있음\n이상소견 없음\n이상소견 있음\n감염성질환 초기평가\n1 증상 및 기간\n□ 발열\n기간\n일전\n호흡기증상\n기간\n일전\n|소화기증상\n기간\n일전\n4 밀접 접촉자\n□ 해당없음 (미상환자 포함)\n2 최근 1달 이내 방문한 나라\n3 최근 1달 이내 국내 신종감염병 위험지역 또는 병원 방문\n5 신종 감염병 의심환자\n추정진단\nPrimary peritoneal carcinomatosis\n해당없음\n없음\n있음\n없음\n있음\n해당없음\n아니오\n아니오 예\nPlan\nOP\nGYN sono\nConservative management\nChemotherapy\nothers\n퇴원계획\n퇴원 후 치료식이 여부\nN ☐ Y\n추후 관리 계획\n|가정간호사업소\n호스피스\n타 병원 전원\n외래\n전자서명자: 김상운\n3/4\n출력일: 2025-03-28\n세브란스병원\nSEVERANCE HOSPITAL\n출력자: 조예은\n원본대조필\n\n등록번호: 7314152\n주민등록번호: 651226-264**** 여/59세\n환자명: 김태현\n사회 복지서비스 연계 필요성\n✓ N ☐ Y\n기타 퇴원시 요구사항\n치료계획\n+\nEI\nProblem\nPrimary peritoneal\ncarcinomatosis\n기록자명\n김지환(의사)\n<약어 설명>\nG: gravida\nP: para\nL: living\nD: dead\nGoal\n목표일\nCTX AH ECOG GOG criteria 2025-02-28\n에 맞추어\n수정목표일 계획일\n2025-02-21\nDOE dyspnea on exertion\nPAP Papanicolaou\nPMI point of maximum intensity\nGYN: Gynecology\nHSIL High Grade Squamous Intraepithelial Lesion\nICS intercostal space\nA Abortion\nabnl abnormal\nA-V Anteversion\nBTL bilateral tubal ligation\nC/sec cesarian section\nIUD intrauterine device\nPMP previous menstrual period\nPul Tbc pulmonary tuberculosis\n:\nLBTL laparoscopic bilateral tubal ligation RCC: renal cell carcinoma\nLMCL Left Midclavicular Line\nLNMP last normal menstrual period\nRHB regular heart beat\nRT: Right\nLSIL: Low Grade Squamous Intraepithelial Lesion\nLT Left\nCVA cerebrovascular accident\nD&E Dilatation and evacuation\nDM diabetes mellitus\nM: Month\nnl: Normal\nR-V Retroversion\nVAS Visual analog pain scale\nY: Year\nAG-H atypical glandular cells cannot exclude a high-grade squamous intraepithelial lesion\nAGUS atypical glandular cells of undetermined significance\nASC-H atypical squamous cells cannot exclude a high-grade squamous intraepithelial lesion\nASCUS atypical squamous cells of undetermined significance\n입원기록\n전자서명자: 김상운\n세브란스병원\n4/4\n출력일: 2025-03-28\n출력자: 조예은\n원본대조필\nSEVERANCE HOSPITAL\n\n등록번호: 7314152\n주민등록번호 : 651226-264**** 여/59세\n환자명 : 김태현\n연령 구분\n|영유아기 ) 학령전기\n학령기\n청소년기\n성인\n분류\n일반 ○ 산모 ㅇ 정신\n현병력\n주 증상 및 내원 과정 금번 C2 위해 입원함 간호정보조사\n2025-02-21\n복용중인 약\n없음 있음\n투약 상태\n1회 투여개수\n1회 투여량\n약품명\n횟수\n용법 및 투여시간\n약품코드 유효함량\n수량 단위\n용량\n단위\nMagmil S [250 mg/T]\n1\nT\n250\nmg\n3\nPO\nD2MAGMO 250\nViscum Finj[0.02mg/\nA]\n1\nml\n0.02\nmg\n3\nS.C(월,수,금)\n2\nD1VISC02 0.020\n내원 시 환자 상태\n통증\n없음 있음\n입원 전에 있었음\n과거력\n과거병력\nㅇ 없음\n있음\n□ 고혈압\n입원 및 수술 이력\n당뇨 □ 결핵 □ 암 □ 간염\n없음 있음 ㅇ 알 수 없음\n□ 경련 | 기타 DL, 당뇨전단계\n입원 및 수술 이력\n입원시 진단명 및 수술명\n복막염 수술\n제왕절개 수술\nDiagnostic laparoscopy (GYN), NAC C1 [Genexol 175BSA+\n입원 및 수술 시기\n1984\n1993,1996\n25.01.30-2.2\nNeoplatin 5AUC]\n가족력\n없음 있음\n모: 자궁암\n음주력\nnondrinker\nex-drinker\ncurrent drinker\n흡연력\nAllergy\n약 □ 식품\n© nonsmoker ☐ ex-smoker ☐ current smoker\n□ 없음\n일반정보(심적/사회적/경제적/영적/문화/종교적 평가)\n결혼 상태 미혼 기혼 ㅇ 별거 ○ 이혼 ○사별 ㅇ 해당 없음\nㅇ없음 ○ 기독교 ○ 천주교 불교 ○ 기타\n종교\n원목 연락 원함 원하지 않음\n보호자 (Main caregiver)\n□ 없음 □ 배우자 □ 부\n□ 간병인 □ 기타\n모 □ 자녀\n□ 조부\n조모\n형제\n|자매\n입원비 지불의 어려움 ㅇ 있음 없음 ㅇ기타\n입원비 지불과 관련한 사회 사업팀 상담 필요\n지난 2주동안 기분이 가라앉거나, 우울하거나, 희망이 없다고 느낀 기간\n있음 없음 ○ 기타\n) 없음 ○ 2~3일 이상 ○7일 이상 ○ 거의 매일 ㅇ 확인 불가능\n지난 2주동안 평소 하던 일에 대한 흥미가 없어지거나 즐거움을 느끼지 못한 기간\n없음 ○ 2~3일 이상 ○ 7일 이상 ○ 거의 매일 ○ 확인불가능\n정서 평가 0\n*The Patient Health Questionnaire-2(PHQ-2) (2003) 주 사용 언어 한국어\n영어 □ 일본어 □ 중국어 □ 러시아어\n기타\n전자서명자: 이송미\n1/3\n출력일: 2025-03-28\n출력자: 조예은\n세브란스병원\n원본대조필\nSEVERANCE HOSPITAL\n\n등록번호: 7314152\n주민등록번호: 651226-264****여/59세\n환자명 : 김태현\n간호정보조사\n2025-02-21\n읽고 쓰는데 어려움\n없음 ㅇ있음\n교육과 진료에 영향을 주는 가치와 신념(Value & belief)\n없음 있음\n퇴원\n퇴원 후 보호자 (Main care giver) □ 배우자\n□ 부\n|자매\n간병인\n모 □ 자녀\n기타\n□ 조부\n조모\n형제\n없음\n퇴원 예정지\n자택 ㅇ 친척집\n타병원\n요양시설 기타\n퇴원 예정 교통수단(Discharge transportation)\n자가\n대중 교통\n항공\n□ 구급차\n|기타\n교육 요구도\n교육 대상자\n원하는 교육 내용\n선호하는 교육 방법\n영양 상태\n□ 환자 보호자\n질병 약물 □ 검사 □ 수술 |자가 간호\n구두 □ 유인물 □ 시범 보이기 □ 시청각 자료\n기타\n영양 □ 기타\n1개월간 체중변화 「없음 ㅇ 증가함 ㅇ 감소함\n체중변화 kg\n) 감소\n최근 1주일간 식사량 변화 없음 ㅇ 증가\n식이 주의 사항 ● 없음 ○ 열량 조절 ㅇ 체중 조절 ㅇ 염분 제한 ㅇ 수분 제한 ㅇ 단백질 제한 지방 제한\n수면상태\n기타\n수면장애\n기능 평가\n없음 ○ 잠들기 어려움 ㅇ 수면 후 개운하지 않음 수면중 3회 이상 깸 원하는 시간보다 일찍 깸\n보조기 사용\n기능 평가\n없음 ㅇ 목발 ㅇ 지팡이 Owalker ○ 휠체어 ○ 기타\n일상생활 수행 능력 ) 독립적 수행 부분 보조 필요 ㅇ 완전 보조\n식사\n개인 위생\n목욕\n옷입기\n화장실\n계단\n걷기\n독립적 수행 가능 ㅇ 준비 시 도움받아 독립적 수행 가능 ㅇ일부의 과정에서 도움이 필요함\n모든 과정에서 도움이 필요함 ㅇ 전혀 수행할 수 없음\n독립적 수행 가능 ㅇ준비 시 도움받아 독립적 수행 가능 ㅇ일부의 과정에서 도움이 필요함\n모든 과정에서 도움이 필요함 ㅇ 전혀 수행할 수 없음\n독립적 수행 가능 ㅇ 감독하에 독립적 수행 가능 ㅇ 일부의 과정에서 도움이 필요함\n모든 과정에서 도움이 필요함 ㅇ 전혀 수행할 수 없음\n독립적 수행 가능 ㅇ 최소의 도움(단추, 지퍼 등)으로 독립적 수행 가능 ○ 도움을 받아 입고 벗을 수 있음\n|수행 시 약간의 참여가 가능함 ㅇ 전혀 수행할 수 없음\n독립적 수행 가능 ㅇ 감독하에 독립적 수행 가능 ○일부의 과정에서 도움이 필요함\n모든 과정에서 도움이 필요함 ㅇ 전혀 수행할 수 없음\n「독립적 수행 가능 ○ 감독하에 독립적 수행 가능 Owalking aid 사용 없이 일부의 과정에서 도움이 필요함\nWalking aid 사용을 포함하여 모든 과정에서 도움이 필요함 ㅇ 전혀 수행할 수 없음\n독립적 수행 가능 (휠체어를 제외한 walking aid 사용할 수 있음) ㅇ 도움이나 감시 없이는 50m 이상 혼자 걷지 못함\n지속적인 Walking aid와 자주 다른 사람의 도움이 필요함 ㅇ 지속적으로 한사람 이상의 도움이 필요함\nㆍ전적으로 도움이 필요함\n이동 (의자와 침대)\n「독립적 수행 가능 ㅇ 감독하에 독립적 수행 가능 ○이동시 일부의 과정에서 도움이 필요함\n)지속적으로 한 사람 이상의 도움이 필요함 ㅇ 전적인 도움이 필요함\n배변 조절\n조절에 문제 없음\n)조절이 잘 되나 가끔 문제가 발생함\n'자주 문제가 발생하며 기저귀의 도움이 필요함 ㅇ자세를 취해주고 배변 시 도움이 필요함\n변실금이 지속됨\n전자서명자: 이송미\n세브란스병원\nSEVERANCE HOSPITAL\n2/3\n출력일: 2025-03-28\n출력자: 조예은\n원본대조필\n\n등록번호: 7314152\n주민등록번호: 651226-264**** 여/59세\n환자명: 김태현\n간호정보조사\n2025-02-21\n배뇨 조절\n조절에 문제 없음 ㅇ가끔 문제가 발생\n실금이 있으나 기구의 도움으로 해결\n낮에는 조절 가능하나 밤에는 도움 필요\n실금이 지속됨(유치 도뇨관)\n기능평가 점수 합계 100\n신체사정\n신경계\n시간 지남력\n장소 지남력\n사람 지남력\n의사 소통\n있음\n있음\n명확치 않음\n명확치 않음\n없음\n없음\n있음 ㅇ 명확치 않음\n원만함\n없음\n) 어려움 ○ 불가능함\n마비\n없음 있음 ㅇ 확인 불가능\nWeakness\n없음\n있음 ㅇ 확인 불가능\n시각\n시각장애\n없음\n있음\n청각\n청각장애\n없음\n있음\n소화기계\n소화기 관련증상\n없음\n있음\n순환기계\nPacemaker\n없음\n있음\n부종\n없음\n순환기 관련증상\n있음\n없음\n있음\n호흡기계\n호흡기 관련증상\n없음\n있음\n피부\n피부 온도\n따뜻함 ㅇ뜨거움\n차가움\n피부 습도\n•\n적당함\n건조함\n축축함\n피부색\n이상없음\n피부 변화\n창백\n없음 ㅇ있음\n) 홍조 ○ 청색증\n황달\n전자서명자: 이송미\n세브란스병원\nSEVERANCE HOSPITAL\n3/3\n출력일: 2025-03-28\n출력자: 조예은\n원본대조필\n\n등록번호: 7314152\n주민등록번호: 651226-264****여/59세\n환자명 : 김태현\n입원정보\n입원일자 2025-03-14\n입원과 산부인과\n퇴원정보\n입원주치의 김상운\n퇴원일자 2025-03-15\n퇴원과\n산부인과\n퇴원주치의 남은지\n최종진단명(*)\n순\n한국질병\n구분\n확진\n진단명\n서\n분류번호\n1 주진단\n확진\nPrimary peritoneal carcinomatosis\nC48.2\n2\n기타진단 확진\nOvarian cancer\nC56.9\n과거진단명\n과거진단코드\n주호소 (*)\nCTX\n과거력 및 현재병력 본 59세 G3 P2 L2 DO A1 married woman은 DL, 당뇨전단계, s/pop d/t perforated\nappendix (19세), s/pc/s 외 특이 과거력 없는 분으로, 하복부 불편감으로 대,소변 보\n기 어려워 타병원 내원하여 EGD,Colonoscopy 시행하여 특이 소견 없음에도 증상 지\n속되어 시행한 APCT 상r/o peritoneal carcinomatosis r/o associated Lt interiliac\nlymphandecnopathy with bilateral periovarian metastatic lesions or solid ovarian\ntumor 확인되어 further evaluation 및 proper management 위해 김상운 교수님께\nrefer, s/p D-lapa('25-1-31) 시행후 NAC C2 [Genexol 175BSA+ Neoplatin 5AUC]\n('25.02.01~) 후 퇴원한 분으로 금번 C3 시행 후 이상소견 없이 퇴원함 이상 진찰 소견 및 검사소견 (*)\nn-c\n투여된 약물 중 잔류효과로 퇴원 후 주의가 필요한 약물 (★)\n없음 있음\n경과요약 (*)\nNAC C3 [Genexol 175BSA+ Neoplatin 5AUC]\n수술/처치명\nNAC C3 [Genexol 175BSA+ Neoplatin 5AUC]\n수술/처치코드\nImplantable Medical Device 사용 여부 No Yes\n치료결과 (*)\n완쾌\n활력증상\n퇴원형태 (*)\n경쾌 호전안됨 ㅇ진단뿐\nㅇ48시간이내 사망 48시간 이후 사망\n혈압 120/80 mmHg 맥박수 72 회/분\n퇴원지시후 ㅇ타병원전원 ㅇ자의퇴원\n가망없는 퇴원\n체온 36.5 °℃ 호흡수 20 회/분\nㅇ 탈원\n향후 치료계획\n「외래 추후관리 2주후 영상 검사/3주후 외래내원하여 수술일 결정\n전자서명자: 남은지\n세브란스병원\nSEVERANCE HOSPITAL\n재입원\n없음\n퇴원요약\n1/2\n출력일: 2025-03-28\n출력자: 조예은\n원본대조필 |\n\n등록번호: 7314152\n주민등록번호: 651226-264**** 여/59세\n환자명 : 김태현\n퇴원요약\n기타\n담당 전공의사명\n없음\n기록자명\n김지환(의사)\n주치의사명\n남은지\n<약어 설명>\nA repair Anterior repair\nANC Antenatal care\nBO Bilateral oophorectomy\nBOC Bilateral ovarian cystectomy\nBS : Bilateral salpingectomy\nC/S Cesarean section\n:\nCPD Cephalopelvic disproportion\nDCB: Dilatation, curettage, biopsy\nET Embryo transplantation\nIDS Internal debulking operation\nIM Intramural lapa: Laparoscopic\nLOC Left ovarian cystectomy\nLS: Left salpingectomy\nP repair Posterior repair\nPALND: Para-aortic lymph node dissection\nPLD Pelvic lymphnode dissection\nPPD Postpartum day\nROC Right ovarian cystectomy\nROP Right occiput posterior\nRS Right salpingectomy\nSLND: Sentinel lymphnode dissection\nSPA Single port access\n전자서명자: 남은지\n2/2\n출력일: 2025-03-28\n출력자: 조예은\n세브란스병원\nSEVERANCE HOSPITAL\n원본대조필\n\n등록번호: 7314152\n주민등록번호: 651226-264**** 여/59세\n환자명 : 김태현\n연령 구분\n분류\n영유아기 학령전기 학령기 |청소년기\n일반 ○ 산모 정신\n성인\n현병력\n주 증상 및 내원 과정 금번 C3 위해 입원함 간호정보조사\n2025-03-14\n복용중인 약\n없음 있음\n투약 상태\n1회 투여개수\n1회 투여량\n약품명\n횟수\n용법 및 투여시간\n약품코드 유효함량\nMagmil S [250 mg/T]\n수량 단위\n2\n용량\n단위\nT\n500\nmg\n3\nPO\n2\nMegace F susp(취급자 1\nPack\n5\nml\n1\nPO (7am)\nD2MAGMO 250\nD3MEGA06 5\n[주의) [5ml/Pack]\n[A]\nViscum Finj[0.02mg/ 1\n내원 시 환자 상태\n0.02\nmg\n3\nS.C(월,수,금) 9:30am\nD1VISC02 0.02\n통증\n없음 ㅇ있음\n입원 전에 있었음\n과거력\n과거병력\n없음\n있음\n□ 고혈압\n입원 및 수술 이력\n당뇨 □ 결핵 □ 암 □ 간염\n없음\n있음 ㅇ 알 수 없음\n경련 □ 기타 DL, 당뇨전단계\n입원 및 수술 이력\n입원시 진단명 및 수술명\n복막염 수술\n제왕절개 수술\nDiagnostic laparoscopy (GYN), NAC C1 [Genexol 175BSA+\nNeoplatin 5AUC]\nNAC C2 [Genexol 175BSA+ Neoplatin 5AUC]\n입원 및 수술 시기\n1984\n1993,1996\n25.01.30-2.2\n(25.02.01~)\n가족력\n없음 | 있음\n모: 자궁암\n음주력\nex-drinker\ncurrent drinker\n흡연력\ncurrent smoker\nOnondrinker\nnonsmoker O ex-smoker\nAllergy □ 없음 □ 약 □ 식품\n일반정보(심적/사회적/경제적/영적/문화/종교적 평가)\n결혼 상태 ㅇ 미혼 기혼 ㅇ 별거 ㅇ 이혼 ㅇ 사별 ㅇ 해당 없음\n종교\n없음 ○ 기독교 천주교 불교 ㅇ기타\n원목 연락 ㅇ원함 원하지 않음\n보호자 (Main care giver) □ 없음\n배우자 □ 부\n모\n자녀\n조부\n조모\n형제\n자매\n□ 간병인 □ 기타\n입원비 지불의 어려움 ㅇ있음 없음 ㅇ기타\n입원비 지불과 관련한 사회 사업팀 상담 필요 ㅇ 있음 없음 ㅇ기타\n지난 2주동안 기분이 가라앉거나, 우울하거나, 희망이 없다고 느낀 기간\n없음 ○ 2~3일 이상 ○7일 이상 ○ 거의 매일 확인 불가능\n지난 2주동안 평소 하던 일에 대한 흥미가 없어지거나 즐거움을 느끼지 못한 기간\n없음 ○ 2~3일 이상 ○7일 이상 ○ 거의 매일 ○ 확인불가능\n정서 평가 0\n전자서명자: 권대연\n세브란스병원\nSEVERANCE HOSPITAL\n1/3\n출력일: 2025-03-28\n출력자: 조예은\n원본대조필\n\n등록번호: 7314152\n주민등록번호: 651226-264****여/59세\n간호정보조사\n2025-03-14\n환자명 : 김태현\n*The Patient Health Questionnaire -2(PHQ-2) (2003) 주 사용 언어 한국어\n읽고 쓰는데 어려움\n영어 □ 일본어 중국어 □ 러시아어 □ 기타\n없음 ㅇ있음\n교육과 진료에 영향을 주는 가치와 신념(Value & belief)\n없음 있음\n퇴원\n퇴원 후 보호자 (Main care giver)\n배우자 □ 부\n모\n자녀 □ 조부\n조모\n형제\n자매 □ 간병인\n기타\n없음\n퇴원 예정지\n•자택 ㅇ 친척집 ○ 타병원\n퇴원 예정 교통수단(Discharge transportation)\n요양시설 기타\n자가 □ 대중 교통\n기타\n□ 항공\n□ 구급차\n교육 요구도\n교육 대상자\n|환자\n보호자\n기타\n원하는 교육 내용\n√ 질병\n약물 □ 검사 □ 수술\n□자가 간호\n시청각 자료\n영양\n기타\n선호하는 교육 방법 구두 □ 유인물 □ 시범 보이기\n영양 상태\n1개월간 체중변화 없음 ㅇ 증가함 ㅇ 감소함\n체중변화\nkg\n최근 1주일간 식사량 변화 없음 ㅇ 증가 감소\n식이 주의 사항 없음 ㅇ 열량 조절 체중 조절 염분 제한 수분 제한 단백질 제한 지방 제한\n기타\n수면상태\n수면장애\n기능 평가\n없음\n잠들기 어려움 ㅇ수면 후 개운하지 않음 수면중 3회 이상 깸\n)원하는 시간보다 일찍 깸\n보조기 사용\n없음 목발 지팡이 Owalker ○ 휠체어 ㅇ기타\n기능 평가\n일상생활 수행 능력\n식사\n독립적 수행 ㅇ부분 보조 필요 ㅇ완전 보조\n독립적 수행 가능 ㅇ 준비 시 도움받아 독립적 수행 가능\n모든 과정에서 도움이 필요함 ㅇ 전혀 수행할 수 없음\n일부의 과정에서 도움이 필요함\n개인 위생\n독립적 수행 가능 ㅇ준비 시 도움받아 독립적 수행 가능\n모든 과정에서 도움이 필요함 ㅇ 전혀 수행할 수 없음\n일부의 과정에서 도움이 필요함\n목욕\n독립적 수행 가능 ㅇ 감독하에 독립적 수행 가능 ㅇ 일부의 과정에서 도움이 필요함\n모든 과정에서 도움이 필요함 ㅇ 전혀 수행할 수 없음\n옷입기\n독립적 수행 가능 ㅇ 최소의 도움(단추, 지퍼 등)으로 독립적 수행 가능\n수행 시 약간의 참여가 가능함 ㅇ 전혀 수행할 수 없음\n도움을 받아 입고 벗을 수 있음\n화장실\n계단\n걷기\n독립적 수행 가능 ㅇ 감독하에 독립적 수행 가능 ○일부의 과정에서 도움이 필요함\n모든 과정에서 도움이 필요함 ㅇ 전혀 수행할 수 없음\n독립적 수행 가능 ㅇ 감독하에 독립적 수행 가능 OWalking aid 사용 없이 일부의 과정에서 도움이 필요함\nWalking aid 사용을 포함하여 모든 과정에서 도움이 필요함 ㅇ 전혀 수행할 수 없음\n독립적 수행 가능 (휠체어를 제외한 walking aid 사용할 수 있음) ㅇ 도움이나 감시 없이는 50m 이상 혼자 걷지 못함\n) 지속적인 Walking aid와 자주 다른 사람의 도움이 필요함 ㅇ 지속적으로 한사람 이상의 도움이 필요함\n전적으로 도움이 필요함\n이동 (의자와 침대)\n'독립적 수행 가능 ㅇ 감독하에 독립적 수행 가능 ○이동시 일부의 과정에서 도움이 필요함\nㅇ 지속적으로 한 사람 이상의 도움이 필요함 ㅇ 전적인 도움이 필요함\n전자서명자: 권대연\n세브란스병원\nSEVERANCE HOSPITAL\n2/3\n출력일: 2025-03-28\n출력자: 조예은\n원본대조필\n\n등록번호: 7314152\n주민등록번호: 651226-264**** 여/59세\n환자명 : 김태현\n배변 조절\n조절에 문제 없음 ㅇ조절이 잘 되나 가끔 문제가 발생함\n간호정보조사\n2025-03-14\n자주 문제가 발생하며 기저귀의 도움이 필요함 ○ 자세를 취해주고 배변 시 도움이 필요함\n변실금이 지속됨\n배뇨 조절\n조절에 문제 없음 ㅇ가끔 문제가 발생\nㅇ실금이 있으나 기구의 도움으로 해결\nㅇ낮에는 조절 가능하나 밤에는 도움 필요\n실금이 지속됨(유치 도뇨관)\n기능평가 점수 합계 100\n신체사정\n신경계\n시간 지남력\n있음\n명확치 않음\n없음\n장소 지남력\n사람 지남력\n의사 소통\n있음\n있음\n원만함\n명확치 않음\n없음\nㅇ명확치 않음 ㅇ 없음\n어려움 ㅇ 불가능함\n마비\n없음 있음\n「확인 불가능\nWeakness\n없음 ㅇ있음 ㅇ 확인 불가능\n시각\n시각장애\n없음 있음\n청각\n청각장애\n없음 있음\n소화기계\n소화기 관련증상\n없음\n있음\n순환기계\nPacemaker\n없음\n있음\n부종\n없음\n순환기 관련증상\n있음\n없음\n있음\n호흡기계\n호흡기 관련증상\n없음\n있음\n피부\n피부 온도\n피부색\n따뜻함 뜨거움 ㅇ 차가움\n피부 변화\n이상없음 ㅇ창백 ㅇ 홍조 ㅇ 청색증\n없음 ㅇ있음\n피부 습도\n황달\n적당함\n) 건조함\n축축함\n전자서명자: 권대연\n3/3\n출력일: 2025-03-28\n출력자: 조예은\n세브란스병원\nSEVERANCE HOSPITAL\n원본대조필\n\n등록번호: 7314152\n주민등록번호: 651226-264**** 여/59세\n환자명 : 김태현\n영상검사 일반촬영\n검사명\nChest PA\n검사방법\n검사일자\n판독일자\nDescription\n2025.03.14 11:11\n2025.03.15 09:44\nNo active lung disease 판독의/전문의\n손진우/손진우/손진우\n전자서명자: 손진우\n세브란스병원\nSEVERANCE HOSPITAL\n영상검사 일반촬영\n촬영실\n암)촬영실 4호(흉부)\n1/1\n출력일: 2025-03-28\n출력자: 조예은\n원본대조필\n\n**검사내용및결과**: 검사 정보 없음\n\n**치료사항**: 보존적 치료\n\n**과거력**: 과거력 확인됨\n\n**기타사항**: 환자명: 김태현, DNA 시퀀싱 처리: 1개 유전자 분석",
    "nine_items": {
      "내원일": "2025-01-01",
      "내원경위": "응급내원",
      "입퇴원기간": "입원치료 시행",
      "통원기간": "1회 진료 확인",
      "진단병명": "2025-04-09 16:49:16\nCH\n해오름손해사정(주)\nPARAGE SUNRISE SURVEYORS & CLAIM ADJUSTERS CO., LTD 신촌세브란스병원\n의무기록사본\n총 1부\n(표지제외)\n빈경환\n\n세브란스병원\nSEVERANCE HOSPITAL 발행번호:\n2025-34780\n등록번호:\n7314152\n환자성명: 김태현\n용 도: 보험회사제출\n발급매수:\n57 매\n의무기록 사본 증명서\n이 사본은 의무기록 원본과 틀림이 없음을 증명합니다 이 사본은 위의 용도 외에는 사용할 수 없습니다 의무기록 사본 증명서\n2025년 03월 28일\n담당자:\n조예은\n담당자의 날인이 없는 것은 무효임\n연세대학교 의과대학\n연화대학교\n학과대학\n세브란스병원\n세브란스병원\nSEVERANCE HOSPITAL\n\n등록번호: 7314152\n주민등록번호: 651226-264**** 여/59세\n환자명 : 김태현\n병리번호\n세포병리진단 결과\nSC2502192\n의뢰과/임상의사:\n검사물접수일 :\n보고일\n:\n산부인과/김상운\n2025-01-21 08:33\n2025-01-23\n병동:\nOPD\n김태현 7314152\n[부인과 세포병리검사]\n검체유형: Cervix Liquid Based Cytology\n[세포병리학적 진단]\n◇ SPECIMEN ADEQUACY\nSatisfactory for evaluation; No endocervical/transformation zone component\n◇ INTERPRETATION/RESULT\nNegative for intraepithelial lesion or malignancy\n특수염색\n:\n면역조직화학염색 :\n슬라이드수\n:\n1\nBlock 수:\nScreener\n김지은\n병리의사\n:\n정민선\n연세대학교 세브란스병원 병리과 | 120-752 서울시 서대문구 성산로 250| Tel:02)2228-2623 | Fax:02)2227-7939\n작성자: 정민선\n1/1\n출력일: 2025-03-28\n세브란스병원\nSEVERANCE HOSPITAL\n출력자: 조예은\n원본대조필\n\n등록번호: 7314152\n주민등록번호: 651226-264**** 여/59세\n환자명: 김태현\n세포병리진단 결과\n병리번호\nSC2502193\n의뢰과/임상의사:\n검사물접수일 :\n산부인과/김상운\n2025-01-21 08:33\n병동: OPD\n김태현 7314152\n보고일\n2025-01-23\n[부인과 세포병리검사]\n검체유형: Cervix Liquid Based Cytology(검진목적)\n[세포병리학적 진단]\n◇ SPECIMEN ADEQUACY\nSatisfactory for evaluation\n◇ INTERPRETATION/RESULT\nNegative for intraepithelial lesion or malignancy\nReactive cellular changes\n특수염색\n:\n면역조직화학염색 :\n슬라이드수\n1\nBlock 수:\nScreener\n:\n김지은\n병리의사\n정민선\n출력일: 2025-03-28\n연세대학교 세브란스병원 병리과 | 120-752 서울시 서대문구 성산로 250| Tel:02)2228-2623 | Fax:02)2227-7939\n작성자: 정민선\n세브란스병원\nSEVERANCE HOSPITAL\n1/1\n출력자: 조예은\n원본대조필\n\n등록번호: 7314152\n주민등록번호: 651226-264****여/59세\n환자명: 김태현\n조직병리진단 결과\n병리번호\nSF2500412\n의뢰과/임상의사:\n검체채취일\n산부인과/김상운\n2025-01-31 14:23\n병동:\n퇴실\n김태현 7314152\n검사물접수일 :\n2025-01-31 14:29\n보고일\n[ Name Of Operation]\nOmentum, frozen biopsy\n[Pathological Diagnosis]\nSee SS25-05286\n특수염색\n면역조직화학염색 :\n면역형광\n2025-02-04\n분자병리\n기타염색\n슬라이드수\n0\n육안사진\n전자현미경\nZZ\nN\nN\nFrozen\nY\n병리의사\n류향주\n[ Gross Description]\nThe specimen submitted fresh for frozen section consists of a piece of soft tissue, labeled \"omentum\", measuring\n3.5x1.5x0.8cm <FROZEN SECTION DIAGNOSIS>\nPresence of carcinoma\n[동결절편진단의: 류향주]\nBlock\nFSP: p-all\n육안검사의사 : 류향주\n출력일: 2025-03-28\n연세대학교 세브란스병원 병리과 | 120-752 서울시 서대문구 성산로 250| Tel:02)2228-2623 | Fax:02)2227-7939\n작성자 : 류향주\n세브란스병원\nSEVERANCE HOSPITAL\n1/1\n출력자: 조예은\n원본대조필\n\n등록번호: 7314152\n주민등록번호: 651226-264****여/59세\n환자명: 김태현\n세포병리진단 결과\n병리번호\n:\nSC2503129\n의뢰과/임상의사:\n검사물접수일\n:\n산부인과/김상운\n2025-02-03 15:09\n병동:\n퇴실\n김태현 7314152\n보고일\n:\n2025-02-05\n[비부인과 세포병리검사]\n검체유형: Peritoneal Fluid(Intraoperative)-Liquid Based Cytology\n[세포병리학적 진단]\n◇ SPECIMEN ADEQUACY\nSatisfactory for evaluation\n◇ INTERPRETATION/RESULT\nPositive for malignancy, metastatic carcinoma\n특수염색\n면역조직화학염색 :\n슬라이드수\n:\n1\nBlock 수:\n1\nScreener\n천상구\n병리의사\n정민선\n연세대학교 세브란스병원 병리과 | 120-752 서울시 서대문구 성산로 250| Tel:02)2228-2623 | Fax:02)2227-7939\n작성자: 정민선\n1/1\n출력일: 2025-03-28\n세브란스병원\nSEVERANCE HOSPITAL\n출력자: 조예은\n원본대조필\n\n등록번호: 7314152\n주민등록번호: 651226-264****여/59세\n환자명 : 김태현\n조직병리진단 결과\n병리번호\n:\nSS2505286\n의뢰과/임상의사:\n검체채취일\n산부인과/김상운\n2025-01-31 15:03\n병동:\n퇴실\n김태현\n7314152\n검사물접수일\n2025-01-31 15:08\n보고일\n2025-02-11\n[ Name Of Operation]\nOmentum, diagnostic laparoscopy (GYN)\n[Pathological Diagnosis ]\nPresence of carcinoma, favoring high-grade serous carcinoma (HGSC)\nNote) The immunohistochemical stain results:\nWT-1: Positive\np53: Aberrant expression (overexpression)\nCK7: Focal positive\nCK20: Negative\nPAX8: Almost negative\np16: Increased expression\nER: Negative\nPR: Negative\nHNF1B: Negative\nCDK2: Negative\nㅇHRD Result: See attached documents *\n'본 결과는 의료법인 녹십자의료재단에 위탁한 검사 결과입니다 특수염색\n면역조직화학염색 :\nPAX8, WT 1,P53_P16,HNF1B,ER,PR,CK7,CDX-2,CK20\n면역형광\nHRD검사-위탁(녹십자),HRD검사-위탁(녹십자)\n분자병리\n기타염색\n슬라이드수\n6\n육안사진\nN\n전자현미경\nN\nFrozen\nN\n병리의사\n박진우\n[Gross Description]\nThe specimen consists of a product of Diagnostic laparoscopy (GYN), including multiple pieces of tissue labeled\n\"omentum\", measuring 10.0x5.0x1.2cm in aggregates Block\n1-5, p-some\n육안검사의사: 김현기\n[외부서식]\n연세대학교 세브란스병원 병리과 | 120-752 서울시 서대문구 성산로 250|Tel:02)2228-2623 | Fax:02)2227-7939\n작성자: 박진우\n출력일: 2025-03-28\n세브란스병원\nSEVERANCE HOSPITAL\n1/5\n출력자: 조예은\n원본대조필\n\n등록번호: 7314152\n주민등록번호: 651226-264**** 여/59세\n환자명: 김태현\n외래재진기록\n2025-01-20\n진료과\n산부인과\n주치의\n김상운\nProgress\n19세때 맹장 터져서 복막염 수술\n제왕절개 2회\n대소변 불편해서 검진함 : 위 대장내시경 정상\ncolpo pap HPV call\nadm baseline\n기록자명\n김상운(의사)\n전자서명자: 김상운\n세브란스병원\nSEVERANCE HOSPITAL\n0\n1/1\n출력일: 2025-03-28\n출력자: 조예은\n원본대조필\n\n등록번호: 7314152\n주민등록번호: 651226-264**** 여/59세\n환자명: 김태현\n영상검사 일반촬영\n검사명\nChest PA\n검사방법\n검사일자\n2025.01.20 16:05\n판독일자\n2025.01.20 16:59\nDescription\nNo active lung disease 판독의/전문의\n허진/허진/허진\n전자서명자: 허진\n세브란스병원\nSEVERANCE HOSPITAL\n영상검사 일반촬영\n촬영실\n암)촬영실 1호\n1/1\n출력일: 2025-03-28\n출력자: 조예은\n원본대조필\n\n등록번호: 7314152\n주민등록번호: 651226-264**** 여/59세\n환자명 : 김태현\n진료의뢰서\n연세대학교의과대학세브란스\n병원\n01055530410\n기본정보\n의뢰번호\n1239134425011700002\n수진자성명 김태현\n보험세부명 건강보험\n의뢰기관명 더바른내과의원\n주민등록번호 651226-*******\n보장기관기호\n의뢰할기관\n전화번호\n보장기관명\n의뢰정보\n회송환자 재의뢰(패스트트랙)\n의뢰유형\n타기관 의뢰\n진단의뢰\n검사의뢰\n의뢰사유\n시술 및 약물치료 의뢰\n환자 또는 가족의 요청\n수술의뢰\n기타\n의뢰사유기타\n환자상태 및 진료소견\n상병분류 C569\n난소의 악성 신생물, 상세불명 쪽 수정상병명 난소의 악성 신생물, 상세불명 쪽\n진료구분\n입원\n외래\n진료시작일\n진료종료일\n의뢰받을\n내과세부\n산부인과\n진료과목\n전문과목\n당뇨 2021년 진단후 LSM하고계신분\n본원에서 고지혈증약 리바로 2 mg 복약하시는분\n진료소견\n타 산부인과에서 폐경후 HRT하면서 해당 병원에서 칼슘약 드시는분\n검사내역\n하복부 묵직한 불편감으로 대,소변 보기 어려워 25년 1월2일 본원에서 위내시경했고 위축성위염있었고 조직검사에서 화생성\n위염확인되었습니다 당시 대장내시경 함께 진행했고 8mm 선종 2개 제거하였습니다 내시경상 큰 이상이 없음에도 하복부 묵직한 불편감과 대소변보기 불편하다고 해 골반암 배제위해 촬영한 타원 APCT에서\nmoderate amount of ascies r/o peritoneal carcinomatosis r/o associated Lt interiliac lymphadenopathy with bilateral\nperivoarian metastatic lesions or solid ovarin tumor 확인되어 귀원진료의뢰드립니다 과거력\n/투약력\n가족력\n/알러지 유무\n담당의사 정보\n담당의사명 김유나\n담당의사 면허번호 124024\n담당자명\n전화번호\n작성자: 최소윤\n세브란스병원\nSEVERANCE HOSPITAL\n진료의뢰서\n1/1\n출력일: 2025-03-28\n출력자: 조예은\n원본대조필\n\n등록번호: 7314152\n침습적 시술 기록 (Invasive procedure)\n주민등록번호: 651226-264****여/59세\n환자명 : 김태현\n2025-01-20\n내원구분\n외래\n입원\n시술 관련 정보\n시술전 진단명\n시술후 진단명\n시술명 EM cytology\n시행일자 2025-01-20\n시술구분 정규\nMass, pelvic; Primary peritoneal carcinomatosis;\nMass, pelvic; Primary peritoneal carcinomatosis;\n시술의사 이지은\n응급\n시술 전 평가내용\n의식상태\n명료(alert)\n환자 확인\n예\n아니오\n시술명 확인\n시술부위 표시\n예\n있음\n아니오\n없음\n시행의사 이지은\n사유\n표시누락 ㅇ 응급시술 Transfemoral catheterization\n영상유도검사\nNatural Orifice를 통한 수술 ㅇ 개방상처 ㅇ중심정맥관 삽입\nO Single Organ\n) 신생아/미숙아\n치아\n환자거절\n동의서\n있음 없음\n시술관련 검사결과 확인\n예 ㅇ아니오 해당없음\nAllergy\n□ 없음\n약\n식품\nRisk factors\n있음\n마취시행 여부\n시행\n없음\nㅇ 시행하지 않음\n□ 수술 및 시술 후 통증발생 가능성과 통증관리에 대해 설명함\n시술구분\n정규 ㅇ 응급\nTime out\n환자 확인\n시행함(정규시술) ㅇ 시행함(응급시술)○ 시행하지 않음(응급수술)\n시행 ㅇ기타\n시술 부위 확인\n시행 ○ 기타\n시술 방향 확인\n예정 시술명 확인\n사용예정 삽입물 확인\n사용예정 장비\n시행 ○ 해당 없음 ○ 기타\n시행 ㅇ기타\n없음 ㅇ있음(삽입물 기재)\n□ 없음 ☐ Ultrasonogram\nAngio-suite □ 기타\nLaser 장비\n□ 내시경 장비\n☐ C-arm\n참여자\n이지은\n시술과정 EM cytology exam was done by JE LEE, MD 시술과정 중 특이사항\nEstimated blood loss\n조직검사 의뢰 유무\n시술 후 평가\n있음\n없음\nminimal (<10 ml) 이\n예\n) ml\n아니오\n전자서명자: 이지은\n세브란스병원\nSEVERANCE HOSPITAL\n1/2\n출력일: 2025-03-28\n출력자: 조예은\n원본대조필\n\n등록번호: 7314152\n침습적 시술 기록 (Invasive procedure)\n주민등록번호: 651226-264**** 여/59세\n환자명: 김태현\n2025-01-20\n의식상태\n명료(alert)\n통증 여부\n없음\n있음\n통증 강도 4\n통증평가도구 NRS(Numeric Rating Scale)/NPIS(The Numerical Pain Intensity Scale)\n입실일시\n2025-01-20\n15:20\n퇴실일시\n2025-01-20\n15:40\n퇴실방법\n걸어서 ○ 휠체어 ㅇ눕는 차 ○ 기타\n퇴실한 곳\n집 타병원 기타\n귀가 시 이송 수단\n동행인\n자가 ○ 대중교통 항공 ○ 기타\n퇴실 시 교육내용\n보호자 의료진 이송팀 없음\n검사 후 합병증 및 주의사항, 추후관리, 응급상황시 연락처\n□ 기타\n전자서명자: 이지은\n세브란스병원\nSEVERANCE HOSPITAL\n2/2\n출력일: 2025-03-28\n출력자: 조예은\n원본대조필\n\n등록번호: 7314152\n주민등록번호: 651226-264**** 여/59세\n환자명: 김태현\n입원정보\n입원일자 2025-01-21\n입원과\n산부인과\n입원주치의 김상운\n퇴원정보\n퇴원일자 2025-01-23\n퇴원과 산부인과\n퇴원주치의 김상운\n최종진단명(*)\n순서\n한국질병\n구분\n확진\n진단명\n분류번호\n1 주진단\n확진\nPrimary peritoneal carcinomatosis\nC48.2\n과거진단명\n과거진단코드\n주호소 (★)\nBaseline study\n과거력 및 현재병력 본 59세 G3 P2 L2 DO A1 married woman은 DL, 당뇨전단계, s/p 복막염수술(19\n세) 외 특이 과거력 없는 분으로, 하복부 불편감으로 대,소변 보기 어려워 타병원 내\n원하여 EGD,Colonoscopy 시행하여 특이 소견 없음에도 증상 지속되어 시행한 APCT\nr/o peritoneal carcinomatosis r/o associated Lt interiliac lymphandecnopathy\nwith bilateral periovarian metastatic lesions or solid ovarian tumor\nfurther evaluation 및 proper management 위해 김상운 교수님께 refer, 금번\nbaseline study 시행 후 이상소견 없이 퇴원함 이상 진찰 소견 및 검사소견 (*)\nn-c\n투여된 약물 중 잔류효과로 퇴원 후 주의가 필요한 약물 (*) 없음 ㅇ있음\n경과요약 (*)\nbaseline study\n수술/처치명\nbaseline study\n수술/처치코드\nImplantable Medical Device 사용 여부 No\nYes\n치료결과 (*)\n|완쾌 ) 경쾌\n'48시간이내 사망\n호전안됨\nㅇ 진단뿐\nㅇ가망없는 퇴원\n활력증상\n혈압 97/71\n148시간이후\nmmHg 맥박수 65\n사망\n퇴원형태 (*)\n퇴원지시후\n・타병원전원\n회/분 체온 37.0 °C 호흡수 18\n자의 퇴원 ㅇ 탈원\n회/분\n향후 치료계획\n외래 추후관리\n재입원 2/3 재입원\n없음\n○ 기타\n전자서명자: 김상운\n세브란스병원\nSEVERANCE HOSPITAL\n퇴원요약\n1/2\n출력일: 2025-03-28\n출력자: 조예은\n원본대조필\n\n등록번호: 7314152\n주민등록번호: 651226-264**** 여/59세\n환자명 : 김태현\n담당 전공의사명\n없음\n기록자명\n김지환(의사)\n주치의사명\n김상운\n<약어 설명>\nA repair Anterior repair\nANC Antenatal care\nBO Bilateral oophorectomy\nBOC Bilateral ovarian cystectomy\nBS Bilateral salpingectomy\nC/S Cesarean section\nCPD Cephalopelvic disproportion\nDCB : Dilatation, curettage, biopsy\nET Embryo transplantation\nIDS Internal debulking operation\nIM Intramural lapa Laparoscopic\nLOC: Left ovarian cystectomy\nLS: Left salpingectomy\nP repair Posterior repair\nPALND: Para-aortic lymph node dissection\nPLD Pelvic lymphnode dissection\nPPD Postpartum day\nROC Right ovarian cystectomy\nROP Right occiput posterior\nRS Right salpingectomy\nSLND: Sentinel lymphnode dissection\nSPA Single port access\n퇴원요약\n전자서명자: 김상운\n2/2\n출력일: 2025-03-28\n출력자: 조예은\n세브란스병원\nSEVERANCE HOSPITAL\n원본대조필\n\n등록번호: 7314152\n주민등록번호 : 651226-264**** 여/59세\n환자명: 김태현\n입원일자\n2025-01-21\n입원과\n산부인과\n주호소\nPresent illness\nBaseline study\n입원주치의 김상운\n(19\n59 G3 P2 L2 DO A1 married woman DL,\ns/p\n세) 외 특이 과거력 없는 분으로, 하복부 불편감으로 대,소변 보기 어려워 타병원 내원\n하여 EGD,Colonoscopy 시행하여 특이 소견 없음에도 증상 지속되어 시행한 APCT 상\nr/o peritoneal carcinomatosis r/o associated Lt interiliac lymphandecnopathy with\nbilateral periovarian metastatic lesions or solid ovarian tumor of further\nevaluation proper management |\nrefer,\nbaseline study\n위해 입원함 Virgin\nNo Yes\n임신력\nG 3\nP 2 L 2 D0A 1\nPast history\nMenarche No\nMarriage\nYes\n16\nNo\nYes\nMenopause\nNo\nYes\n54\nLast delivery\nNo\nYes\n1996\nContraception method\nNone\nHusband-vasectomy\nPast OB-GYN history\nLast D & E history\nNo\nYes\nOral pill\n○ IUD\nOs/p LBTL or BTL\nOther\nLast PAP smear\nnone\n2025\nY 01\nM\nnl\nabnl\n-\nNSVD\nNo\nYes\nC/sec\nNo\nYes 2'93,'96\nInduced abortion\nNo\nYes\nSpontaneous abortion\nNo\nYes\nOthers\nPosthysterctomy status\nNo\nYes\nLNMP\n2024-12-27\nPMP\nMenstrual history\nRegularity\nInterval\nDuration\ndays\n(days)\n(days)\nAmount\nPain(VAS)\nMedico-surgical illness\n전자서명자: 김상운\n세브란스병원\nSEVERANCE HOSPITAL\n입원기록\n1/3\n출력일: 2025-03-28\n출력자: 조예은\n원본대조필\n\n등록번호: 7314152\n주민등록번호: 651226-264**** 여/59세\n환자명 : 김태현\n입원기록\nHypertension No\nYes\nDM\nNo\nYes\nHepatitis\nNo\nYes\nPul Tbc\nNo\nYes\nOperation history ☐ No\nYes\nOther Cancer history\nNONE\nCardiac disease\nNo\nYes\nNo\nYes\nOld CVA\nOther\nSocial history\nSmoking\nNo\nYes\nAlcohol\nNo\nYes\nAllergy\nDrug\nNo\nYes\n항생제\n진통제\n조영제\n기타\nFood 및 기타\nNo\nYes\nOther\n신체조사\nGeneral appearance\nSkin\nHEENT\nNeck\nChest/lung\nHeart\nAbdomen\nBack and extremity\nPelvic examination\n감염성질환 초기평가\n이상소견 없음\n이상소견 없음\n이상소견 없음\n이상소견 없음\n이상소견 없음\n이상소견 없음\n이상소견 없음\n・이상소견 없음\n이상소견 없음\n)이상소견 있음\n이상소견 있음\n이상소견 있음\n이상소견 있음\n이상소견 있음\n이상소견 있음\n이상소견 있음\n이상소견 있음\n이상소견 있음\n1 증상 및 기간\n]발열\n기간\n일전\n호흡기증상\n기간\n일전\n소화기증상\n기간\n일전\n2 최근 1달 이내 방문한 나라\n4 밀접 접촉자\n□ 해당없음 (미상환자 포함)\n3 최근 1달 이내 국내 신종감염병 위험지역 또는 병원 방문\n5 신종 감염병 의심환자\nPrimary peritoneal carcinomatosis\n추정진단\n전자서명자: 김상운\n해당없음\n없음\n있음\n없음\n있음\n|해당없음\n) 아니오\n예\n아니오\n예\n세브란스병원\nSEVERANCE HOSPITAL\n2/3\n출력일: 2025-03-28\n출력자: 조예은\n원본대조필\n\n등록번호: 7314152\n주민등록번호: 651226-264****여/59세\n환자명 : 김태현\nPlan\nOP\nGYN sono\nConservative management\nChemotherapy\nothers\nBaseline study\n퇴원계획\n퇴원 후 치료식이 여부\n추후 관리 계획\n☑ N ☐ Y\n| 가정간호사업소\n호스피스\n타 병원 전원\n외래\n사회 복지서비스 연계 필요성\n✓ N ☐ Y\n기타 퇴원시 요구사항\n치료계획\n+\nProblem\nGoal\n목표일\n수정목표일 계획일\n부\nPrimary peritoneal\ncarcinomatosis\nbaseline study without\ncomplication\n2025-01-28\n2025-01-21\n기록자명\n김지환(의사)\n<약어 설명>\nG: gravida\nP: para\nL: living\nD: dead\nA: Abortion\nabnl : abnormal\nDOE dyspnea on exertion\nGYN: Gynecology\nPAP Papanicolaou\nPMI point of maximum intensity\nHSIL High Grade Squamous Intraepithelial Lesion\nICS intercostal space\nPMP previous menstrual period\nIUD intrauterine device\nPul Tbc pulmonary tuberculosis\nA-V : Anteversion\nBTL bilateral tubal ligation\nC/sec : cesarian section\nLBTL laparoscopic bilateral tubal ligation RCC renal cell carcinoma\nLMCL Left Midclavicular Line\nRHB regular heart beat\nRT: Right\nLNMP last normal menstrual period\nLSIL: Low Grade Squamous Intraepithelial Lesion\nLT : Left\nM: Month\nCVA cerebrovascular accident\nD&E: Dilatation and evacuation\nDM diabetes mellitus\nnl: Normal\nR-V: Retroversion\nVAS Visual analog pain scale\nY: Year\nAG-H atypical glandular cells cannot exclude a high-grade squamous intraepithelial lesion\nAGUS atypical glandular cells of undetermined significance\nASC-H atypical squamous cells cannot exclude a high-grade squamous intraepithelial lesion\nASCUS atypical squamous cells of undetermined significance\n전자서명자: 김상운\n세브란스병원\nSEVERANCE HOSPITAL\n입원기록\n3/3\n출력일: 2025-03-28\n출력자: 조예은\n원본대조필\n\n등록번호: 7314152\n주민등록번호: 651226-264**** 여/59세\n환자명: 김태현\n연령 구분\n영유아기 학령전기\n학령기\n청소년기\n성인\n분류\n일반 ○ 산모 ㅇ정신\n현병력\n주 증상 및 내원 과정 금번 baseline study 위해 입원함 간호정보조사\n2025-01-21\n복용중인 약\n없음\n있음\n투약 상태\n1회 투여개수\n1회 투여량\n약품명\n횟수\n용법 및 투여시간\n약품코드 유효함량\n수량 단위\n용량 단위\n[DiCAmax[1T /]\n1\n1\nT\n1\n8am\nD2DICA01 1\nLivial[2.5mg/T]\n1\nT\n2.5\nmg\n1\n8am\n[Livalo[2mg/T]\n1\nT\n2\nmg\n1\n6pm\nD2LIVI01\n2.500\nD2LIVA02 2.000\n내원 시 환자 상태\n통증\n없음\n있음\n입원 전에 있었음\n과거력\n과거병력\n없음\n있음\n입원 및 수술 이력\n없음 있음 ㅇ 알 수 없음\n입원 및 수술 이력\n입원시 진단명 및 수술명\n복막염 수술\n자궁근종\n제왕절개 수술\n입원 및 수술 시기\n1984\n2000\n1993,1996\n가족력\n없음\n있음\n부모> 당뇨\n부> 심장질환\n음주력 Onondrinker\nex-drinker\ncurrent drinker\n흡연력\n음주력(종류, 양, 횟수/wk) 소주 1/2 병, 2~3회/주\n음주 시작 시기 21\nAllergy □ 없음 □ 약 □ 식품\n끊은 시기 1달 전\nnonsmoker ex-smoker\nO current smoker\n일반정보(심적/사회적/경제적/영적/문화적/종교적 평가)\n결혼 상태\n미혼 ) 기혼 ○ 별거 ㅇ 이혼 ㅇ사별 ㅇ 해당 없음\n종교\n없음 ○ 기독교 천주교 불교 ○ 기타\n원목 연락\n원함 )원하지 않음\n보호자 (Main caregiver)\n없음\n배우자\n부\n모\n자녀 □ 조부\n조모\n□ 형제\n□ 자매\n간병인 ]기타\n입원비 지불의 어려움\n있음 ㅇ 없음 ○ 기타\n입원비 지불과 관련한 사회 사업팀 상담 필요 ㅇ있음 없음 ○ 기타\n지난 2주동안 기분이 가라앉거나, 우울하거나, 희망이 없다고 느낀 기간\n없음 ○ 2~3일 이상 ○7일 이상 ○ 거의 매일 ㅇ 확인 불가능\n지난 2주동안 평소 하던 일에 대한 흥미가 없어지거나 즐거움을 느끼지 못한 기간\n없음 ○ 2~3일 이상 ○ 7일 이상 ○ 거의 매일 ○ 확인불가능\n정서 평가 0\n*The Patient Health Questionnaire -2(PHQ-2) (2003) 전자서명자: 이송미\n주 사용 언어 한국어 □ 영어 □ 일본어 □ 중국어 □ 러시아어\n1/3\n기타\n출력일: 2025-03-28\n출력자: 조예은\n세브란스병원\nSEVERANCE HOSPITAL\n원본대조필\n\n등록번호: 7314152\n주민등록번호: 651226-264**** 여/59세\n환자명 : 김태현\n간호정보조사\n2025-01-21\n읽고 쓰는데 어려움\n없음 ㅇ있음\n교육과 진료에 영향을 주는 가치와 신념(Value & belief)\nㅣ없음 ㅇ 있음\n퇴원\n퇴원 후 보호자 (Main care giver)\n배우자\n]자매\n□ 부\n간병인 기타\n모\n자녀\n□ 조부\n조모\n형제\n없음\n퇴원 예정지\n자택 ㅇ친척집 ○타병원\n요양시설 기타\n퇴원 예정 교통수단(Discharge transportation)\n자가 □ 대중 교통\n|기타\n□ 항공\n□ 구급차\n교육 요구도\n교육 대상자\n□ 환자\n보호자\n기타\n원하는 교육 내용\n선호하는 교육 방법\n질병 약물 □ 검사 □ 수술\n구두 유인물 □ 시범 보이기\n자가 간호\n영양\n□ 기타\n|시청각 자료\n영양 상태\n체중변화 1.0kg\n1개월간 체중변화 없음 ○ 증가함 |감소함\n최근 1주일간 식사량 변화 없음 ㅇ 증가 감소\n식이 주의 사항\n없음 ㅇ 열량 조절 체중 조절 ㅇ염분 제한 수분 제한 단백질 제한 지방 제한\n기타\n수면상태\n수면장애\n기능 평가\n없음\n잠들기 어려움 ㅇ수면 후 개운하지 않음 수면중 3회 이상 깸 원하는 시간보다 일찍 깸\n보조기 사용\n없음 ㅇ 목발 ㅇ 지팡이 Owalker ) 휠체어 ㅇ기타\n기능 평가\n일상생활 수행 능력\n식사\n독립적 수행 ㅇ부분 보조 필요 ㅇ 완전 보조\n독립적 수행 가능 ㅇ 준비 시 도움받아 독립적 수행 가능\n모든 과정에서 도움이 필요함 ㅇ 전혀 수행할 수 없음\nㅇ일부의 과정에서 도움이 필요함\n개인 위생\n|독립적 수행 가능 ㅇ준비 시 도움받아 독립적 수행 가능\n일부의 과정에서 도움이 필요함\n모든 과정에서 도움이 필요함 ㅇ 전혀 수행할 수 없음\n목욕\n독립적 수행 가능 ㅇ 감독하에 독립적 수행 가능 ㅇ 일부의 과정에서 도움이 필요함\n모든 과정에서 도움이 필요함 ㅇ 전혀 수행할 수 없음\n옷입기\n독립적 수행 가능 ㅇ 최소의 도움(단추, 지퍼 등)으로 독립적 수행 가능\n도움을 받아 입고 벗을 수 있음\n수행 시 약간의 참여가 가능함 ㅇ 전혀 수행할 수 없음\n화장실\n계단\n걷기\n독립적 수행 가능 ㅇ 감독하에 독립적 수행 가능 ㅇ일부의 과정에서 도움이 필요함\n모든 과정에서 도움이 필요함 ㅇ 전혀 수행할 수 없음\n독립적 수행 가능 ㅇ 감독하에 독립적 수행 가능 ㅇ Walking aid 사용 없이 일부의 과정에서 도움이 필요함\nWalking aid 사용을 포함하여 모든 과정에서 도움이 필요함 ㅇ 전혀 수행할 수 없음\n독립적 수행 가능 (휠체어를 제외한 walking aid 사용할 수 있음) ○ 도움이나 감시 없이는 50m 이상 혼자 걷지 못함\n) 지속적인 Walking aid와 자주 다른 사람의 도움이 필요함 ㅇ 지속적으로 한사람 이상의 도움이 필요함\n) 전적으로 도움이 필요함\n이동 (의자와 침대)\n'독립적 수행 가능 ㅇ 감독하에 독립적 수행 가능 ○이동시 일부의 과정에서 도움이 필요함\nㅇ 지속적으로 한 사람 이상의 도움이 필요함 ㅇ전적인 도움이 필요함\n배변 조절\n조절에 문제 없음 ㅇ조절이 잘 되나 가끔 문제가 발생함\n'자주 문제가 발생하며 기저귀의 도움이 필요함 ㅇ자세를 취해주고 배변 시 도움이 필요함\n변실금이 지속됨\n전자서명자: 이송미\n세브란스병원\nSEVERANCE HOSPITAL\n2/3\n출력일: 2025-03-28\n출력자: 조예은\n원본대조필\n\n등록번호: 7314152\n주민등록번호: 651226-264**** 여/59세\n환자명 : 김태현\n간호정보조사\n배뇨 조절\n조절에 문제 없음 ㅇ가끔 문제가 발생\n실금이 있으나 기구의 도움으로 해결\n낮에는 조절 가능하나 밤에는 도움 필요\n실금이 지속됨(유치 도뇨관)\n기능평가 점수 합계 100\n신체사정\n신경계\n시간 지남력\n장소 지남력\n있음\n있음\n|명확치 않음\n없음\n명확치 않음\n없음\n사람 지남력\n의사 소통\n있음 ㅇ 명확치 않음\n원만함\n없음\n어려움 ㅇ 불가능함\n마비 없음 ㅇ있음 ㅇ 확인 불가능\nWeakness\n없음 ㅇ있음 ㅇ 확인 불가능\n시각\n시각장애\n없음\n있음\n청각\n청각장애\n없음\n있음\n소화기계\n소화기 관련증상\n없음 있음\n순환기계\nPacemaker\n없음\n있음\n부종\n없음\n순환기 관련증상\n있음\n없음\n있음\n호흡기계\n호흡기 관련증상\n없음\n있음\n피부\n피부 온도\n따뜻함 ㅇ뜨거움\n차가움\n피부 습도\n적당함 ㅇ 건조함 ) 축축함\n피부색\n이상없음\n창백\n홍조 청색증\n황달\n피부 변화\n없음\n있음\n전자서명자: 이송미\n세브란스병원\nSEVERANCE HOSPITAL\n2025-01-21\n3/3\n출력일: 2025-03-28\n출력자: 조예은\n원본대조필\n\n등록번호: 7314152\n주민등록번호: 651226-264**** 여/59세\n환자명 : 김태현\n영상검사 CT& MR\n영상검사 CT& MR\n검사명\nCT GU (GYN) Abd+Pel (contrast)\n검사방법\n검사일자\n2025.01.21 20:02\n촬영실\nCT 20호(암병원 2층)\n판독일자\nDescription\n판독의/전문의\n2025.01.22 16:13\nClinical information: Primary peritoneal carcinomatosis\nCl: Abd-Pelvic MR과 비교판독임 IMP: PPC or bilateral HGSC with peritoneal carcinomatosis\nEXTENT:\nConglomerated nodular lesions with both adenexae and adjacent pelvic wall (RO/LO =\n4.8/4.7cm)\nMultiple seeding nodules with irregular thickening involving pelvic peritoneum, both\nparacolic gutters (arrows)\nSeeding nodules in Rt side omentum, transverse mesocolon/lesser omentum (arrows)\nDiffuse irregular thickening and seeding nodules in both subdphg peritoneum including\nhepato-renal recess, associated with ascites\nNo pathologic LNEs, ileus or parenchymal metastasis\nIntact both lower lungs and cardiophrenic area\n◆조영제◆\nlobrix 270 inj[150ml/Btl]-CT용 [lohexol 582.4mg/ml (요오드로서 270mg/ml)] [150ml/\nBtl]:1.0\n정대철/정대철/정대철\n전자서명자: 정대철\n1/1\n출력일: 2025-03-28\n출력자: 조예은\n세브란스병원\nSEVERANCE HOSPITAL\n원본대조필\n\n등록번호: 7314152\n주민등록번호: 651226-264**** 여/59세\n환자명 : 김태현\n검사명\n검사방법\n검사일자\n판독일자\nDescription\n영상검사 CT& MR\n영상검사 CT& MR\nMRI GU Abdomen (인접부위동시검사-비뇨) (noncontrast)\n2025.01.21 20:39\n2025.01.22 16:13\n촬영실\nMRI 78호(본관2층)\nClinical information: Primary peritoneal carcinomatosis\nImaging technique: Axial fat-suppressed T1Wl, axial T2Wl coronal T2WI Contrast media: Not used CI: APCT와 비교판독임 IMP: PPC or bilateral HGSC with peritoneal carcinomatosis\nEXTENT:\nConglomerated nodular lesions with both adenexae and adjacent pelvic wall (RO/LO =\n4.8/4.7cm)\nMultiple seeding nodules with irregular thickening involving pelvic peritoneum, both\nparacolic gutters (arrows)\nSeeding nodules in Rt side omentum, transverse mesocolon/lesser omentum (arrows)\nDiffuse irregular thickening and seeding nodules in both subdphg peritoneum including\nhepato-renal recess, associated with ascites\nNo pathologic LNEs, ileus or parenchymal metastasis\nIntact both lower lungs and cardiophrenic area\n판독의/전문의\n정대철/정대철/정대철\n전자서명자: 정대철\n1/1\n출력일: 2025-03-28\n출력자: 조예은\n세브란스병원\nSEVERANCE HOSPITAL\n원본대조필\n\n등록번호: 7314152\n주민등록번호: 651226-264****여/59세\n환자명: 김태현\n영상검사 CT& MR\n영상검사 CT&MR\n검사명\nMRI GYN Ovary & diffusion (contrast)\n검사방법\n검사일자\n판독일자\n2025.01.21 20:39\n2025.01.22 16:12\n촬영실\nMRI 78호(본관2층)\nDescription\n판독의/전문의\nClinical information: Primary peritoneal carcinomatosis\nImaging technique: Axial T1WI, T2WI, DWI; sagittal T2Wl; coronal T2Wl: contrast\nenhanced dynamic axial T1Wl, contrast enhanced axial/sagittal T1WI Contrast media: Used CI: APCT/MR 비교판독임 IMP: PPC or bilateral HGSC with peritoneal carcinomatosis\nEXTENT:\nConglomerated nodular lesions with both adenexae and adjacent pelvic wall (RO/LO =\n4.8/4.7cm)\nMultiple seeding nodules with irregular thickening involving pelvic peritoneum, both\nparacolic gutters (arrows)\nSeeding nodules in Rt side omentum, transverse mesocolon/lesser omentum (arrows)\nDiffuse irregular thickening and seeding nodules in both subdphg peritoneum including\nhepato-renal recess, associated with ascites\nNo pathologic LNES, ileus or parenchymal metastasis\nIntact both lower lungs and cardiophrenic area\n◆조영제\nGadovist prefilled inj[7.5ml/Syringe] [Gadobutrol 604.72mg/ml] [7.5 ml/Syringe]:1.0\n정대철/정대철/정대철\n전자서명자: 정대철\n1/1\n출력일: 2025-03-28\n출력자: 조예은\n세브란스병원\nSEVERANCE HOSPITAL\n원본대조필\n\n등록번호: 7314152\n주민등록번호: 651226-264****여/59세\n환자명 : 김태현\n영상검사 특수촬영 - 초음파\n영상검사 특수촬영-초음파\n검사명\nU/S 자동유방초음파 - 일반(Breast)\n검사방법\n검사일자\n판독일자\n2025.01.22 09:49\n2025.01.23 10:47\n촬영실\n암)자동유방초음파 검사실\nDescription\n판독의/전문의\nClinical Information: Primary peritoneal carcinomatosis\nUS examination was done with linear transducer> =10 MHz (central frequency) Screening US\nUS background echotexture: 2 - Mild fibroglandular\nRt breast 9시 30분 방향 9cm from nipple 위치에 10mm 크기의 mass 관찰되며\nmammogram 상 관찰된 mass density와 correlation 될 것으로 보임 해당 mass가 이전 2023-04 mammogram과 mammogram 상에서 큰 변화 없는 것을 고려\n하여 probably benign finding으로 assess함 1년 뒤 follow up 권함 그 외에 Rt breast에 small benign lesions 있음 No abnormal calcification or duct dilatation Imp: Category 3; Probable benign finding in Rt breast Advise: Follow up ABUS and mammogram after 1 year 윤지영/윤지영/윤지영\n전자서명자: 윤지영\n1/1\n출력일: 2025-03-28\n출력자: 조예은\n세브란스병원\nSEVERANCE HOSPITAL\n원본대조필\n\n등록번호: 7314152\n주민등록번호: 651226-264****여/59세\n환자명 : 김태현\n검사명\n영상검사 특수촬영 -투시\n영상검사 특수촬영-투시\nMammography (Both)\n검사방법\n검사일자\n2025.01.22 09:51\n판독일자\n2025.01.23 10:35\nDescription\n촬영실\n암)유방촬영 2호\nScreening mammogram\nGrade C Rt upper outer breast에 mass density 관찰되며 2023-04 외부 병원 사진과 변화 없음 US correlation 권함 Rt lower medial\nview 권함 Lt lower central aspect of calcification group magnification\nImp Category 0; Incomplete assessment for Rt breast mass and both breasts\ncalcifications Advise: US correlation and both magnification view 판독의/전문의\n윤지영/윤지영/윤지영\n전자서명자: 윤지영\n세브란스병원\nSEVERANCE HOSPITAL\n1/1\n출력일: 2025-03-28\n출력자: 조예은\n원본대조필 |\n\n등록번호: 7314152\n주민등록번호: 651226-264**\n[**** 여/59세\n환자명 : 김태현\n영상검사 일반촬영\n검사명\nAbdomen Flat, Upright\n검사방법\n검사일자\n판독일자\n2025.01.22 10:02\n2025.01.22 11:35\nDescription\nMild ileus bowel gas pattern\n판독의/전문의\n정보령/정보령/정보령\n전자서명자: 정보령\n세브란스병원\nSEVERANCE HOSPITAL\n영상검사 일반촬영\n촬영실\n암)촬영실 1호\n1/1\n출력일: 2025-03-28\n출력자: 조예은\n원본대조필\n\n등록번호: 7314152\n주민등록번호: 651226-264****여/59세\n환자명 : 김태현\n영상검사 특수촬영 - 핵의학\n영상검사 특수촬영-핵의학\n검사명\nPET-CT Whole Body Scan (Torso, GU, non-contrast)\n검사방법\n검사일자\n판독일자\n2025.01.23 13:22\n2025.01.24 08:32\n촬영실\nPET-CT 38호실(암병원)\nDescription\n판독의/전문의\nHx: Staging (presumed malignancy)\n2025-01 R/O Peritoneal carcinomatosis, R/O associated Lt internal iliac\nlymphandecnopathy with bilateral periovarian metastatic lesions or solid ovarian tumor\n(outside)\n2025-01-21 Cervix liquid cytology (pending) s/pop d/t Peritonitis (outside)\nCA 19-9 51.0 (2025-01-22)\nCA 125 293.0 (2025-01-22)\nHE4 155.0 (2025-01-22)\nTechnique:\nF-18 FDG was given to the patient intravenously PET imaging using a standard protocol was performed from the skull base to the\nproximal thigh The obtained images were reconstructed into axial, sagittal, and coronal planes Low-dose, non-contrast-enhanced CT scan was performed for attenuation correction <<<Findings and impressions>>>\nIncreased FDG uptake in the pelvic cavity, suspicious for ovarian malignancy Diffuse FDG uptake in the whole peritoneum, suggestive of carcinomatosis Increased FDG uptake in the right internal mammary LN, right hilar LNs, suggestive of LN\nmetastasis 강원준/강원준/강원준\n전자서명자: 강원준\n1/1\n출력일: 2025-03-28\n출력자: 조예은\n세브란스병원\nSEVERANCE HOSPITAL\n원본대조필\n\n등록번호: 7314152\n주민등록번호: 651226-264**** 여/59세\n환자명 : 김태현\n입원정보\n입원일자 2025-01-30\n입원과\n산부인과\n입원주치의 김상운\n퇴원정보\n퇴원일자 2025-02-02\n퇴원과 산부인과\n퇴원주치의 김상운\n최종진단명(*)\n순\n한국질병\n구분\n확진\n진단명\n분류번호\n1\n주진단\n확진 Primary peritoneal carcinomatosis\nC48.2\n2\n기타진단\n확진\nOvarian cancer\nC56.9\n과거진단명\n과거진단코드\n주호소 (*)\nOP\n과거력 및 현재병력 본 59세 G3 P2 L2 DO A1 married woman은 DL, 당뇨전단계, s/p 복막염수술(19\n세) 외 특이 과거력 없는 분으로, 하복부 불편감으로 대,소변 보기 어려워 타병원 내\n원하여 EGD,Colonoscopy 시행하여 특이 소견 없음에도 증상 지속되어 시행한 APCT\nr/o peritoneal carcinomatosis r/o associated Lt interiliac lymphandecnopathy\nwith bilateral periovarian metastatic lesions or solid ovarian tumor\nfurther evaluation 및 proper management 위해 김상운 교수님께 refer, baseline\nstudy 시행 받은 후 1/31 D-lapa 시행, 2/1 1st NAC [Genexol 175BSA+ Neoplatin\n5AUC] 시행 후 특이소견 없이 퇴원함 이상 진찰 소견 및 검사소견 (*)\nn-c\n투여된 약물 중 잔류효과로 퇴원 후 주의가 필요한 약물 (★)\n경과요약 (*)\n진단적 복강경검사 (부인과);\n없음\n있음\n1st NAC [Genexol 175BSA+ Neoplatin 5AUC] 2025.02.01\nHt: 158.7cm\n수술/처치명\n수술/처치코드\nWt: 52.5kg\nBSA: 1.52\nCCr: 66.06\nGenexol: 175BSA= 175*1.52 = 266mg\nNeoplatin: 5AUC=5*[66.06+25]= 455.3mg\nDiagnostic laparoscopy (GYN)\n5421\nImplantable Medical Device 사용 여부 No\nYes\n전자서명자: 김상운\n세브란스병원\nSEVERANCE HOSPITAL\n퇴원요약\n1/2\n출력일: 2025-03-28\n출력자: 조예은\n원본대조필\n\n등록번호: 7314152\n주민등록번호: 651226-264****여/59세\n환자명 : 김태현\n치료결과 (*)\n완쾌\n경쾌\n활력증상\n퇴원형태 (*)\n호전안됨 ㅇ 진단뿐\nㅇ48시간이내 사망 148시간 이후 사망\n혈압 114/75 mmHg 맥박수 71 회/분 체온 36.5 C 호흡수 20\n퇴원지시후 ㅇ타병원전원 ㅇ자의퇴원 탈원\n가망없는 퇴원\n회/분\n향후 치료계획\n외래 추후관리 안내받은 예약일에 외래 내원합니다 Pathology 확인 필요합니다 재입원\n없음\n기타\n담당 전공의사명\n없음\n기록자명\n문한나(의사)\n주치의사명\n김상운\n<약어 설명>\nA repair Anterior repair\nANC Antenatal care\nBO Bilateral oophorectomy\nBOC Bilateral ovarian cystectomy\nBS Bilateral salpingectomy\nC/S : Cesarean section\nCPD Cephalopelvic disproportion\nDCB: Dilatation, curettage, biopsy\nET: Embryo transplantation\nIDS Internal debulking operation\nIM: Intramural lapa: Laparoscopic\nLOC Left ovarian cystectomy\nLS: Left salpingectomy\nP repair Posterior repair\nPALND: Para-aortic lymph node dissection\nPLD Pelvic lymphnode dissection\nPPD Postpartum day\nROC Right ovarian cystectomy\nROP Right occiput posterior\nRS Right salpingectomy\nSLND Sentinel lymphnode dissection\nSPA Single port access\n퇴원요약\n전자서명자: 김상운\n2/2\n출력일: 2025-03-28\n출력자: 조예은\n세브란스병원\nSEVERANCE HOSPITAL\n원본대조필\n\n등록번호: 7314152\n주민등록번호: 651226-264**** 여/59세\n환자명 : 김태현\n수술일\n2025-01-31\n집도의\n김상운\n보조의(1)\n보조의(3)\n수술보조간호사 최진범\n수술전 진단명\n진단명\nPrimary peritoneal carcinomatosis\nOvarian cancer\n진단 부가 설명 s/p Appendectomy, c/sec 수술후 진단명\n진단명\nPrimary peritoneal carcinomatosis\nOvarian cancer\n보조의 (2)\n보조의(4)\n수술명\n진단 부가 설명 s/p Appendectomy, c/sec Omentoperitoneal and ovario-intestinal adhesion\n수술명\nDiagnostic laparoscopy (GYN)\nSingle-port laparoscopic adhesiolyssis and partial omentectomy including omental\ncake Anesthesia\nGEA\nSpinal\nOther\nPCA\nEpidural\nIV\nNot done\nPosition\nsupine\nlithotomy\nother\nPreparation and drap as usual sterile manner\nInsufflation\nGasless\nCO2 gas\nOther\nVerres needle use\nYes\nNo\nPelvic exam\nExternal genitalia\nfree\nother\nCervix\nnulliparous\nparous\nother\nUterus\n✓ A-V\n☐ R-V\nNormal size\n☐ Other Enlarged to\nweeks Other\nAdnexae\nfree\nother\nA sound was passed through cervical canal to\nTrocar for camera (05mm ○ 10mm\n☐ Supraumbilical\nUmbilical\n전자서명자: 김상운\n세브란스병원\nSEVERANCE HOSPITAL\nInfraumbilical\n✓ Other Single port\ncm depth\n12 mm)\n수술기록\n1/4\n출력일: 2025-03-28\n출력자: 조예은\n원본대조필\n\n등록번호: 7314152\n주민등록번호: 651226-264****여/59세\n환자명 : 김태현\nNumber of working port\n1\n2\n3\n4\n○ 5 6\nLocation of working port\n☐ Mcburney point\nCounter-Mcburney point\nSuprapubic\n5cm above the Mcburney point\n5cm above the counter-Mcburney point\n10cm above Mcburney point\nOperation finding\nOther\nUterus\nSize\nnormal size\nenlarged to\nweeks\nother\nShape\nglobular\nother\nMyoma\nNo\nYes\nAdenomyosis\nNo\nYes\nAdnexae\nRt Ovary\nnormal\nother\nnot visible due to adhesion\nRt Tube\nnormal\nother\nnot visible\nLt Ovary\nnormal\nother\nOvario-sigmoid colon adhesion,\nLt Tube\nnormal\nother\nOvario-sigmoid colon adhesion\nAdhesion\nNo\nYes\nRemarkable other findings\nOvario-sigmoid colon adhesion and omentoperitoneal adhesion was noted After\nadhsiolysis of omental cake was exposed and partial omentectomy was done Laparoscopic parameter\nSuperficial liver metastasis\n0\n2\nStomach infiltration\n0\n2\nBowel infiltration\n0\n2\nOmental cake\n0\n2\nPeritoneal carcinomatosis\n0\n2\nDiaphragmatic carcinomatosis\n0\n2\nTotal score\n8\nMesenteral retraction\n2\nSpecimen retrieval\nVia\nUmbilicus\nEndopouch 사용여부\nYes\nAny other troca but umbilicus\nNo\nVagina\nSpecific instrument 사용여부\nMorcellator\nEndoknife\nAntiadhesive agent\nNo\nYes Gardix Susulen\nAntihemorrhagic agent\nNo\nYes\nSurgiguard\nHemostasis with\nSuture\nCauterization\nHemostatic agent\nAbdominal wall closure\n-\nPeritoneum :\nCCG\nVicryl\nOther\n-\nFascia layer:\nVicryl\nSilk\nOther\n- Subcutaneous layer:\nNo\nVicryl\nSilk\nOther\n전자서명자: 김상운\n세브란스병원\nSEVERANCE HOSPITAL\n2/4\n수술기록\n출력일: 2025-03-28\n출력자: 조예은\n원본대조필\n\n등록번호: 7314152\n주민등록번호: 651226-264**** 여/59세\n환자명 : 김태현\n-\nSkin :\n☐ nylon\nstapler\nOther\nEstimated blood loss (cc)\n수술과정 중 특이사항\n10\nNo\nYes\nTissue to Pathology\nNo\nYes\nDrains\nNo\nYes\nSponge count correct\nNo\nYes\n전자서명자: 김상운\n세브란스병원\nSEVERANCE HOSPITAL\n수술기록\n3/4\n출력일: 2025-03-28\n출력자: 조예은\n원본대조필\n\n등록번호: 7314152\n주민등록번호: 651226-264****여/59세\n환자명: 김태현\n기록자명\n김상운\n수술기록\n전자서명자: 김상운\n4/4\n출력일: 2025-03-28\n세브란스병원\nSEVERANCE HOSPITAL\n출력자: 조예은\n원본대조필\n\n등록번호: 7314152\n주민등록번호: 651226-264**** 여/59세\n환자명 : 김태현\n입원일자\n2025-01-30\n입원과\n산부인과\n입원주치의 김상운\n주호소\nPresent illness\nOP\n59 G3 P2 L2 DO A1 married woman DL,\ns/p op d/t perforated\nappendix (19세), s/pc/s 외 특이 과거력 없는 분으로, 하복부 불편감으로 대,소변 보기\n어려워 타병원 내원하여 EGD,Colonoscopy 시행하여 특이 소견 없음에도 증상 지속되\nAPCT r/o peritoneal carcinomatosis r/o associated Lt interiliac\nlymphandecnopathy with bilateral periovarian metastatic lesions or solid ovarian\ntumor 확인되어 further evaluation 및 proper management 위해 김상운 교수님께\nrefer, baseline study 시행 받은 후 금번 D-lapa 시행 위해 입원함 Virgin\nNo\nYes\n임신력\nG\n3\nP 2 L 2 DOA 1\nPast history\nMenarche No\nYes\n16\nMenopause\nNo\nYes 54\nMarriage\nNo\nYes\nLast delivery\nNo\nYes 1996\nContraception method\nLast D & E history\nNo\nYes\nNone Oral pill\nOIUD\n○ s/p LBTL or BTL\nHusband-vasectomy\nOther\nPast OB-GYN history\nLast PAP smear ☐ none\n2025\nY 01\nM\nOnl\nabnl\n- NSVD\nNo\nYes\nC/sec\nNo\nYes 2'93,'96\nInduced abortion\nNo\nYes\nSpontaneous abortion No Yes\nOthers\nPosthysterctomy status\nNo\nYes\nLNMP\n2024-12-27\nPMP\nMenstrual history\nRegularity\nInterval\n(days)\nDuration\ndays\n(days)\nAmount\nPain(VAS)\nMedico-surgical illness\n전자서명자: 김상운\n세브란스병원\nSEVERANCE HOSPITAL\n입원기록\n1/4\n출력일: 2025-03-28\n출력자: 조예은\n원본대조필\n\n등록번호: 7314152\n주민등록번호: 651226-264**** 여/59세\n환자명 : 김태현\n입원기록\nHypertension No\nYes\nDM\nNo\nYes\nHepatitis\nNo\nYes\nPul Tbc\nNo\nYes\nOperation history No\nYes\nOther Cancer history\nNONE\nCardiac disease\nNo\nYes\nNo\nYes\nOld CVA\nOther\nSocial history\nSmoking\nNo\nYes\nAlcohol\n○ No\nYes\nAllergy\nDrug\nNo\nYes\n항생제\n진통제\n조영제\n기타\nFood 및 기타\nNo\nYes\nOther\n신체조사\nGeneral appearance\nSkin\nHEENT\nNeck\nChest/lung\nHeart\nAbdomen\nTenderness\nNo\n이상소견 없음\n・이상소견 없음\n이상소견 없음\n이상소견 없음\n이상소견 없음\n이상소견 없음\n이상소견 없음\n☐ direct\nBowel sound\nPalpation of organ\nNo\nliver\nkidney\nspleen\nuterus\nAbdomen\n전자서명자: 김상운\n세브란스병원\nSEVERANCE HOSPITAL\n이상소견 있음\n이상소견 있음\n이상소견 있음\n이상소견 있음\n이상소견 있음\n이상소견 있음\n이상소견 있음\nrebound\n2/4\n출력일: 2025-03-28\n출력자: 조예은\n원본대조필\n\n등록번호: 7314152\n주민등록번호: 651226-264****여/59세\n환자명 : 김태현\n입원기록\ns/pop d/t\nperforated appe'\ns/pc/s\nBack and extremity\n이상소견 없음\n이상소견 있음\nPelvic examination\n감염성질환 초기평가\n이상소견 없음\n이상소견 있음\n1 증상 및 기간\n□ 발열\n기간\n일전\n|호흡기증상\n기간\n일전\n소화기증상\n기간\n일전\n해당없음 (미상환자 포함)\n2 최근 1달 이내 방문한 나라\n3 최근 1달 이내 국내 신종감염병 위험지역 또는 병원 방문\n4 밀접 접촉자\n5 신종 감염병 의심환자\nPrimary peritoneal carcinomatosis\n해당없음\n|해당없음\n없음\n있음\n없음\n있음\n아니오 예\n예\n아니오\n추정진단\nPlan\n☑ OP\nGYN sono\nConservative management\nChemotherapy\nothers\n퇴원계획\n퇴원 후 치료식이 여부\nN ☐ Y\n추후 관리 계획\n]가정간호사업소\n호스피스\n타 병원 전원\n외래\n전자서명자: 김상운\n3/4\n출력일: 2025-03-28\n세브란스병원\nSEVERANCE HOSPITAL\n출력자: 조예은\n원본대조필\n\n등록번호: 7314152\n주민등록번호: 651226-264****여/59세\n환자명 : 김태현\n사회 복지서비스 연계 필요성\n✓ N ☐ Y\n기타 퇴원시 요구사항\n치료계획\n+\nProblem\nGoal\n부\n목표일\n수정목표일 계획일\nPrimary peritoneal\noperation without\n2025-02-06\n2025-01-30\ncarcinomatosis\ncomplication\n기록자명 이다혜(의사)\n<약어 설명>\nG: gravida\nP: para\nL: living\nD: dead\nA: Abortion\nabnl abnormal\nA-V Anteversion\nBTL bilateral tubal ligation\nC/sec cesarian section\nCVA cerebrovascular accident\nD&E Dilatation and evacuation\nDM diabetes mellitus\nDOE dyspnea on exertion\nGYN: Gynecology\nPAP Papanicolaou\nPMI point of maximum intensity\nHSIL High Grade Squamous Intraepithelial Lesion\nPMP previous menstrual period\nPul Tbc pulmonary tuberculosis\nICS intercostal space\nIUD intrauterine device\nLBTL laparoscopic bilateral tubal ligation RCC: renal cell carcinoma\nLMCL Left Midclavicular Line\nLNMP last normal menstrual period\nRHB regular heart beat\nRT: Right\nLSIL: Low Grade Squamous Intraepithelial Lesion\nLT: Left\nM: Month\nnl : Normal\nR-V Retroversion\nVAS Visual analog pain scale\nY: Year\nAG-H atypical glandular cells cannot exclude a high-grade squamous intraepithelial lesion\nAGUS atypical glandular cells of undetermined significance\nASC-H atypical squamous cells cannot exclude a high-grade squamous intraepithelial lesion\nASCUS atypical squamous cells of undetermined significance\n전자서명자: 김상운\n세브란스병원\nSEVERANCE HOSPITAL\n입원기록\n4/4\n출력일: 2025-03-28\n출력자: 조예은\n원본대조필\n\n등록번호: 7314152\n주민등록번호: 651226-264**** 여/59세\n환자명 : 김태현\n연령 구분\n영유아기 ) 학령전기\n학령기\n청소년기\n성인\n분류\n일반 ○ 산모 ㅇ정신\n현병력\n주 증상 및 내원 과정 금번 D-lapa 시행 위해 입원함 간호정보조사\n2025-01-30\n복용중인 약\n없음\n있음\n투약 상태\n1회 투여개수\n1회 투여량\n약품명\n횟수\n용법 및 투여시간\n약품코드 유효함량\n수량 단위\n용량 단위\n[Livial[2.5mg/T]\n1\nT\n2.5\nmg\n1\nDicamax D[1T/T]\n1\nT\n1\nT\n1\nPO 8am (1/17~자의 skip 중)\nPO 8am (1/17~ 자의 skip 중)\nLivalo[2mg/T]\n1\nT\n2\nmg\n1\nPO 8am (1/17~자의 skip 중)\nMontezal[10mg/1정] 1\nT\n10\nmg\n3\nPO\nTwolion[10mg/1정]\n1\nT\n10\nmg\n3\nPO\nMaxibupen ER[O.3g/11\nT\n13\n0.3\ng\n3\nPO\n[정]\n[Ambrocol[/1정]\n0.5\nT\n0\n3\nPO\nD2LIVI01 2.500\nD2DICA02 1,000\nDZLIVA02 2.000\nP00000000 10\n06864\nP00000000 10\n30644\nP00000000 0.3\n03177\nC00000000\n05982\nMoktin(일시품절)\n1\nC\n200\nmg\n3\nPO\n[200mg/C]\nOrocin[0.1g/1정]\n1\nT\n0.1\ng\n3\nPO\nD2MOKT01 200.000\nOFLX100TA 0.1\nBO192\n내원 시 환자 상태\n통증\n없음\n있음 ㅇ 입원 전에 있었음\n통증 부위 □ 전신통 □ 흉통 복통 □ 관절통 □ 두통 □ 요통 □ 상세부위\n통증 강도 2\n통증 양상 □ 둔함 쑤심 □ 퍼짐 □ 예리함 □ 찌르는듯함 |기타\n통증평가도구 NPIS(The Numerical Pain Intensity Scale)\n빈도\nㅇ 지속적\n) 간헐적 일정하지 않음\n지속기간 일정하지 않음\n악화 요인\n완화 요인\n과거력\n과거병력\n없음\n있음\n□ 고혈압\n입원 및 수술 이력\n당뇨 □ 결핵 □ 암\n없음 있음 ㅇ 알 수 없음\n간염 □ 경련 기타 DL, 당뇨전단계\n입원 및 수술 이력\n입원시 진단명 및 수술명\n입원 및 수술 시기\n복막염 수술\n제왕절개 수술\n1984\n1993,1996\n가족력\n없음 있음\n모: 자궁암\n음주력\nnondrinker ex-drinker\ncurrent drinker\nG\n흡연력\nnonsmoker ex-smoker\ncurrent smoker\nAllergy □ 없음 □ 약 □ 식품\n일반정보(심적/사회적/경제적/영적/문화/종교적 평가)\n결혼 상태\n미혼 기혼 ㅇ 별거 ㅇ 이혼 ㅇ사별 ○ 해당 없음\n종교\n없음 ○ 기독교 천주교 불교 ㅇ기타\n전자서명자: 윤경은\n세브란스병원\nSEVERANCE HOSPITAL\n1/3\n출력일: 2025-03-28\n출력자: 조예은\n원본대조필\n\n등록번호: 7314152\n주민등록번호: 651226-264**** 여/59세\n환자명 : 김태현\n간호정보조사\n2025-01-30\n원목 연락\n원함 원하지 않음\n보호자 (Main caregiver)\n□ 없음\n배우자\n부\n모\n자녀\n□ 조부\n조모\n형제\n□ 자매\n□ 간병인 □ 기타\n입원비 지불의 어려움\n있음 없음 ○ 기타\n입원비 지불과 관련한 사회 사업팀 상담 필요 ) 있음 없음 ○ 기타\n지난 2주동안 기분이 가라앉거나, 우울하거나, 희망이 없다고 느낀 기간\n없음 ○ 2~3일 이상 ○7일 이상 ○ 거의 매일 확인 불가능\n지난 2주동안 평소 하던 일에 대한 흥미가 없어지거나 즐거움을 느끼지 못한 기간\n없음 ○ 2~3일 이상 ○7일 이상 ○ 거의 매일 ○ 확인불가능\n정서 평가 0\n*The Patient Health Questionnaire -2(PHQ-2) (2003) 주 사용 언어 한국어 □ 영어 □ 일본어 □ 중국어 □ 러시아어 □ 기타\n읽고 쓰는데 어려움\n없음 ㅇ있음\n교육과 진료에 영향을 주는 가치와 신념(Value & belief)\n없음 있음\n퇴원\n퇴원 후 보호자 (Main care giver)\n배우자 □ □ 모 □ 자녀 □ 조부\n|자매 □ 간병인 □ 기타\n조모\n□ 형제\n없음\n퇴원 예정지\n자택 ㅇ 친척집\n타병원\n퇴원 예정 교통수단(Discharge transportation)\n요양시설 ㅇ기타\n자가 □ 대중 교통\n기타\n항공 □ 구급차\n교육 요구도\n교육 대상자\n원하는 교육 내용\n|환자\n질병\n보호자 □ 기타\n약물 □ 검사 □ 수술 |자가 간호\n영양 □ 기타\n선호하는 교육 방법 구두 □ 유인물 □ 시범 보이기 □ 시청각 자료\n영양 상태\n1개월간 체중변화 ㅣ없음 ㅇ 증가함 ㅇ 감소함\n체중변화 kg\n최근 1주일간 식사량 변화 없음 ○ 증가 •감소\n식이 주의 사항 「없음 ㅇ 열량 조절 ㅇ 체중 조절 ○ 염분 제한 ○ 수분 제한 ○ 단백질 제한 지방 제한\n수면상태\n기타\n수면장애\n기능 평가\n없음 ○ 잠들기 어려움 ○ 수면 후 개운하지 않음 수면중 3회 이상 깸 원하는 시간보다 일찍 깸\n보조기 사용\n기능 평가\n없음 '목발 ○ 지팡이 Owalker 휠체어 ○ 기타\n일상생활 수행 능력 '독립적 수행 ㅇ 부분 보조 필요 ㅇ 완전 보조\n식사\n|독립적 수행 가능 ㅇ준비 시 도움받아 독립적 수행 가능\n모든 과정에서 도움이 필요함 ㅇ 전혀 수행할 수 없음\nㅇ일부의 과정에서 도움이 필요함\n개인 위생\n독립적 수행 가능 ㅇ 준비 시 도움받아 독립적 수행 가능 ㅇ일부의 과정에서 도움이 필요함\n모든 과정에서 도움이 필요함 ㅇ 전혀 수행할 수 없음\n목욕\n독립적 수행 가능 ㅇ 감독하에 독립적 수행 가능 ○ 일부의 과정에서 도움이 필요함\n모든 과정에서 도움이 필요함 ㅇ 전혀 수행할 수 없음\n옷입기\n독립적 수행 가능 ㅇ 최소의 도움(단추, 지퍼 등)으로 독립적 수행 가능 ○ 도움을 받아 입고 벗을 수 있음\n수행 시 약간의 참여가 가능함 ㅇ 전혀 수행할 수 없음\n전자서명자: 윤경은\n세브란스병원\nSEVERANCE HOSPITAL\n2/3\n출력일: 2025-03-28\n출력자: 조예은\n원본대조필\n\n등록번호: 7314152\n주민등록번호: 651226-264**** 여/59세\n환자명: 김태현\n화장실\n독립적 수행 가능 ㅇ 감독하에 독립적 수행 가능\n모든 과정에서 도움이 필요함 ㅇ 전혀 수행할 수 없음\n일부의 과정에서 도움이 필요함\n계단\n걷기\n간호정보조사\n2025-01-30\n독립적 수행 가능 ㅇ 감독하에 독립적 수행 가능 O Walking aid 사용 없이 일부의 과정에서 도움이 필요함\nWalking aid 사용을 포함하여 모든 과정에서 도움이 필요함 ㅇ 전혀 수행할 수 없음\n) 독립적 수행 가능 (휠체어를 제외한 walking aid 사용할 수 있음) ○ 도움이나 감시 없이는 50m 이상 혼자 걷지 못함\n) 지속적인 Walking aid와 자주 다른 사람의 도움이 필요함 ㅇ 지속적으로 한사람 이상의 도움이 필요함\nㅇ 전적으로 도움이 필요함\n이동 (의자와 침대)\n독립적 수행 가능 ㅇ 감독하에 독립적 수행 가능 ㅇ 이동시 일부의 과정에서 도움이 필요함\n지속적으로 한 사람 이상의 도움이 필요함 ㅇ전적인 도움이 필요함\n배변 조절\n조절에 문제 없음 ㅇ조절이 잘 되나 가끔 문제가 발생함\n자주 문제가 발생하며 기저귀의 도움이 필요함 ㅇ자세를 취해주고 배변 시 도움이 필요함\n변실금이 지속됨\n배뇨 조절\n조절에 문제 없음 ㅇ가끔 문제가 발생\n실금이 있으나 기구의 도움으로 해결\nㅇ낮에는 조절 가능하나 밤에는 도움 필요\n실금이 지속됨(유치 도뇨관)\n기능평가 점수 합계 100\n신체사정\n신경계\n시간 지남력\n있음\n명확치 않음\n없음\n장소 지남력\n사람 지남력\n의사 소통\n있음\n있음\n원만함\n명확치 않음\n명확치 않음\n없음\n없음\n어려움 ㅇ 불가능함\n마비\n없음 있음\n확인 불가능\nWeakness\n없음\n있음 ㅇ 확인 불가능\n시각\n시각장애\n없음\n있음\n청각\n청각장애\n없음\n있음\n소화기계\n소화기 관련증상\n없음\n있음\n순환기계\nPacemaker\n없음\n있음\n부종\n없음\n있음\n순환기 관련증상\n없음\n) 있음\n호흡기계\n호흡기 관련증상\n없음\n있음\n피부\n피부 온도\n피부색\n따뜻함 뜨거움\n이상없음\n피부 변화\n없음\n) 차가움\n피부 습도\n창백 ) 홍조 ○ 청색증 ㅇ 황달\n있음\n적당함\n건조함\n축축함\n전자서명자: 윤경은\n3/3\n출력일: 2025-03-28\n출력자: 조예은\n세브란스병원\nSEVERANCE HOSPITAL\n원본대조필\n\n등록번호: 7314152\n주민등록번호: 651226-264**** 여/59세\n환자명: 김태현\n진료과\n산부인과\n주치의\n김상운\nProgress\n2025/1/31 D-lapa- ovarian cancer stage 4B\nPresence of carcinoma, favoring high-grade serous carcinoma\n(HGSC)\n2025/2/1 1st NAC [Genexol 175BSA+ Neoplatin 5AUC]\nviscum\ngBRCA1,2,\nHRD\nrec 2nd NAC akynzeo neulapeg\n진단명\n구분\n확진\n진단명\n주진단\n기타진단\nOvarian cancer\n확진 Primary peritoneal carcinomatosis\n확진\n기록자명\n김상운(의사)\n전자서명자: 김상운\n세브란스병원\nSEVERANCE HOSPITAL\n외래재진기록\n2025-02-17\n1/1\n출력일: 2025-03-28\n출력자: 조예은\n원본대조필\n\n등록번호: 7314152\n주민등록번호: 651226-264****여/59세\n환자명: 김태현\n영상검사 일반촬영\n영상검사 일반촬영\n검사명\nChest PA\n검사방법\n검사일자\n2025.02.17 13:49\n촬영실\n암)촬영실 2호\n판독일자\n2025.02.17 14:53\nDescription\nNo active lung disease 판독의/전문의\n허진/허진/허진\n전자서명자: 허진\n세브란스병원\nSEVERANCE HOSPITAL\n1/1\n출력일: 2025-03-28\n출력자: 조예은\n원본대조필\n\n등록번호: 7314152\n주민등록번호: 651226-264**\n*****여/59세\n환자명 : 김태현\n검사명\nBRCA1 sequencing[Whole blood]\n의뢰과\n산부인과\n의뢰의\n김상운\n검체접수일\n검체명\n진단명\n2025-02-17\nWhole blood\nOvarian cancer; Primary peritoneal carcinomatosis;\n검사결과\nNot detected\n상세정보 및 comment\n본 환자의 BRCA1 유전자 검사결과 의미있는 돌연변이는 관찰되지 않았습\n니다 유전성 유방암·난소암 증후군(Hereditary breast and ovarian cancer\nsyndrome; HBOC)은 BRCA1 혹은 BRCA2 유전자의 선천성 돌연변이에 의\n해서 발생하며 상염색체 우성으로 유전하여 돌연변이를 가진 환자에서는\n유방암, 난소암, 전립선암 및 췌장암의 위험도가 크게 증가하는 것으로 알\n려져 있습니다 본 검사는 BRCA1 유전자의 23개 단백합성 엑손(coding\nexon) 혹은 BRCA2 유전자의 27개 단백합성 엑손 및 인접한 인트론\n(flanking intron) 부위를 염기서열분석법으로 검사하며, 발현조절 부위\n(regulatory region) 또는 엑손에서 멀리 떨어진 인트론(deep intron)의 돌\n연변이는 검출할 수 없습니다 유전자 일부의 대규모 결실(large deletion)\n혹은 중복(duplication)도 일부 검출이 가능하나 엑손 1~2개 정도의 작은\n결실 혹은 증폭은 검출되지 않을 수 있습니다 <References>\nJ Natl Cancerlnst 2010: 102 (24): 1874-1878 N Engl J Med 2007: 357 (2): 115-123 Am J Hum Genet 2003: 72 (5): 1117-1130 <Databases used>\nOnline Mendelian Inheritance in Man (OMIM), Human Gene Mutation\nDatabase (HGMD), ClinVar, dbSNP, 1000 Genome, Exome Aggregation\nConsortium (ExAC), Exome Sequencing Project (ESP), Korean Reference\nGenome Database (KRGDB), Breast Cancer Information Core (BIC) 검사정보\n검사방법: 염기서열분석법\n표적유전자: BRCA1 (breast cancer 1, early onset) on chromosome\n17q21\n분석위치: coding exon (2-23) and flanking intron (exon-intron\nboundaries: ± 20 base pairs)\n대상질환: 유전성유방암-난소암 증후군(Hereditary breast and ovarian\ncancer syndrome; HBOC)\n유전양상: 상염색체우성 (Autosomal dominant)\n표준염기서열: NM_007294.3\n보고일\n2025-02-27\n검사자1\n강지웅\n전자서명자: 원동주\n세브란스병원\nSEVERANCE HOSPITAL\n진단유전 검사 결과\n2025-02-27\n직종 M.T 면허번호 38045\n원내번호 86140\n1/2\n출력일: 2025-03-28\n출력자: 조예은\n원본대조필\n\n등록번호: 7314152\n주민등록번호: 651226-264**** 여/59세\n환자명 : 김태현\n검사자2\n진단유전 검사 결과\n직종\n면허번호\n원내번호\n판독의\n원동주\n직종 M.D\n면허번호 120916\n원내번호\n확인자(전문의)1 원동주\n확인자(전문의)2\n직종\n직종\nM.D\n면허번호\n면허번호\n120916\n원내번호\n원내번호\n확인자(전문의)3\n직종\n면허번호\n원내번호\n확인자(전문의)4\n직종\n면허번호\n원내번호\n전자서명자: 원동주\n세브란스병원\nSEVERANCE HOSPITAL\n2/2\n2025-02-27\n출력일: 2025-03-28\n출력자: 조예은\n원본대조필\n\n등록번호: 7314152\n주민등록번호: 651226-264****여/59세\n환자명 : 김태현\n입원정보\n입원일자 2025-02-21\n입원과\n산부인과\n입원주치의 김상운\n퇴원정보\n퇴원일자 2025-02-22\n퇴원과 산부인과\n퇴원주치의 이용재\n최종진단명(*)\n순\n한국질병\n구분\n확진\n진단명\n서\n분류번호\n1 주진단\n확진 Primary peritoneal carcinomatosis\nC48.2\n2\n기타진단\n확진 Ovarian cancer\nC56.9\n과거진단명\n과거진단코드\n주호소 (★)\nCTX\n과거력 및 현재병력 본 59세 G3 P2 L2 DO A1 married woman은 DL, 당뇨전단계, s/pop d/t perforated\nappendix (19세), s/pc/s 외 특이 과거력 없는 분으로, 하복부 불편감으로 대,소변 보\n기 어려워 타병원 내원하여 EGD,Colonoscopy 시행하여 특이 소견 없음에도 증상 지\n속되어 시행한 APCT 상r/o peritoneal carcinomatosis r/o associated Lt interiliac\nlymphandecnopathy with bilateral periovarian metastatic lesions or solid ovarian\ntumor 확인되어 further evaluation 및 proper management 위해 김상운 교수님께\nrefer, s/p_D-lapa('25-1-31) 시행후 NAC C1 [Genexol 175BSA+ Neoplatin 5AUC]\n('25.02.01~) 후 퇴원한 분으로 2025.02.21 NAC C2 [Genexol 175BSA + Neoplatin\n5AUC] 시행 후 퇴원함 이상 진찰 소견 및 검사소견 (*)\nn-c\n투여된 약물 중 잔류효과로 퇴원 후 주의가 필요한 약물 (★) 없음 ㅇ있음\n경과요약 (*)\n수술/처치명\n수술/처치코드\n2025.02.21 NAC C2 [Genexol 175BSA+ Neoplatin 5AUC]\n2025.02.21 NAC C2 [Genexol 175BSA+ Neoplatin 5AUC]\nImplantable Medical Device 사용 여부 No\n퇴원요약\nYes\n치료결과 (*)\n완쾌\n경쾌\n호전안됨\n진단뿐 ㅇ가망없는 퇴원\n48시간이내 사망\n활력증상\n퇴원형태 (*)\n48시간이후 사망\n혈압 120/80 mmHg 맥박수 72 회/분\n퇴원지시후\n•자의퇴원\n•타병원전원\n체온 36.5 C 호흡수 20\nㅇ 탈원\n회/분\n향후 치료계획\n외래 추후관리\n재입원 3/14 opd\n없음\n전자서명자: 이용재\n세브란스병원\n1/2\n출력일: 2025-03-28\n출력자: 조예은\n원본대조필\nSEVERANCE HOSPITAL\n\n등록번호: 7314152\n주민등록번호: 651226-264**\n*****여/59세\n환자명 : 김태현\n퇴원요약\n기타\n담당 전공의사명\n없음\n기록자명\n김지환(의사)\n주치의사명\n이용재\n<약어 설명>\nA repair Anterior repair\nANC Antenatal care\nBO Bilateral oophorectomy\nBOC Bilateral ovarian cystectomy\nBS Bilateral salpingectomy\nC/S Cesarean section\nCPD Cephalopelvic disproportion\nDCB: Dilatation, curettage, biopsy\nET Embryo transplantation\nIDS Internal debulking operation\nIM : Intramural lapa: Laparoscopic\nLOC: Left ovarian cystectomy\nLS: Left salpingectomy\nP repair Posterior repair\nPALND: Para-aortic lymph node dissection\nPLD Pelvic lymphnode dissection\nPPD Postpartum day\nROC Right ovarian cystectomy\nROP Right occiput posterior\nRS Right salpingectomy\nSLND Sentinel lymphnode dissection\nSPA Single port access\n전자서명자: 이용재\n2/2\n출력일: 2025-03-28\n출력자: 조예은\n세브란스병원\nSEVERANCE HOSPITAL\n원본대조필\n\n등록번호: 7314152\n주민등록번호: 651226-264**** 여/59세\n환자명 : 김태현\n입원일자\n2025-02-21\n입원과\n산부인과\n입원주치의 김상운\n주호소\nPresent illness\nCTX\n59 G3 P2 L2 DO A1 married woman DL,\ns/p op d/t perforated\nappendix (19세), s/pc/s 외 특이 과거력 없는 분으로, 하복부 불편감으로 대,소변 보기\n어려워 타병원 내원하여 EGD,Colonoscopy 시행하여 특이 소견 없음에도 증상 지속되\nACT r/o peritoneal carcinomatosis r/o associated Lt interiliac\nlymphandecnopathy with bilateral periovarian metastatic lesions or solid ovarian\ntumor 확인되어 further evaluation 및 proper management 위해 김상운 교수님께\nrefer, s/p D-lapa ('25-1-31) ANAC C1 [Genexol 175BSA + Neoplatin 5AUC]\n('25.02.01~) 후 퇴원한 분으로 금번 C2 위해 입원함 Virgin\nNo\nYes\n임신력\nG 3\nP 2 L 2 DO A 1\nPast history\nMenarche\nNo\nYes\n16\nMenopause\nNo\nYes\n54\nMarriage\nNo\nYes\nLast delivery\nNo\nYes 1996\nContraception method\nLast D & E history\nNo Yes\nNone Oral pill\nHusband-vasectomy\nOIUD\nOther\nOs/p LBTL or BTL\nPast OB-GYN history\nLast PAP smear ☐ none\n2025\nnl\nY 01\nM\nabnl\n-\n-\nNSVD\nNo\nYes\nC/sec\nNo\nYes 2'93,'96\nInduced abortion\nNo\nYes\nSpontaneous abortion No\nYes\nOthers\nPosthysterctomy status\nNo\nYes\nLNMP 2024-12-27\nPMP\nMenstrual history\nRegularity\nInterval\n(days)\nDuration\ndays\n(days)\nAmount\nPain(VAS)\nMedico-surgical illness\n전자서명자: 김상운\n세브란스병원\nSEVERANCE HOSPITAL\n입원기록\n1/4\n출력일: 2025-03-28\n출력자: 조예은\n원본대조필\n\n등록번호: 7314152\n주민등록번호: 651226-264**** 여/59세\n환자명 : 김태현\n입원기록\nHypertension No\nYes\nDM\nNo Yes\nHepatitis\nNo\nYes\nPul Tbc\nNo\nYes\nOperation history ☐ No Other Cancer history\nYes\nCardiac disease\nNONE\nNo\n○ Yes\nNo\n> Yes\nOld CVA\nOther\nSocial history\nSmoking\nNo\nYes\nAlcohol\nNo\nYes\nAllergy\nDrug\nNo\nYes\n항생제\n진통제\n조영제\n|기타\nFood 및 기타\nNo\nYes\nOther\n신체조사\nGeneral appearance\nSkin\nHEENT\nNeck\nChest/lung\nHeart\nAbdomen\nTenderness\nNo\n이상소견 없음\n이상소견 없음\n이상소견 없음\n이상소견 없음\n이상소견 없음\n이상소견 없음\n・이상소견 없음\ndirect\nBowel sound\nnormoative\nPalpation of organ ☑ No liver\nkidney\nspleen\nuterus\nAbdomen\n이상소견 있음\n이상소견 있음\n이상소견 있음\n이상소견 있음\n이상소견 있음\n이상소견 있음\n이상소견 있음\n☐ rebound\n전자서명자: 김상운\n세브란스병원\n2/4\n출력일: 2025-03-28\n출력자: 조예은\n원본대조필\nSEVERANCE HOSPITAL\n\n등록번호: 7314152\n주민등록번호: 651226-264****여/59세\n환자명 : 김태현\n입원기록\ns/pop d/t\nperforated\nappe'\ns/pc/s\nBack and extremity\nPelvic examination\n이상소견 없음\n이상소견 있음\n이상소견 없음\n이상소견 있음\n감염성질환 초기평가\n1 증상 및 기간\n□ 발열\n기간\n일전\n호흡기증상\n기간\n일전\n|소화기증상\n기간\n일전\n4 밀접 접촉자\n□ 해당없음 (미상환자 포함)\n2 최근 1달 이내 방문한 나라\n3 최근 1달 이내 국내 신종감염병 위험지역 또는 병원 방문\n5 신종 감염병 의심환자\n추정진단\nPrimary peritoneal carcinomatosis\n해당없음\n없음\n있음\n없음\n있음\n해당없음\n아니오\n아니오 예\nPlan\nOP\nGYN sono\nConservative management\nChemotherapy\nothers\n퇴원계획\n퇴원 후 치료식이 여부\nN ☐ Y\n추후 관리 계획\n|가정간호사업소\n호스피스\n타 병원 전원\n외래\n전자서명자: 김상운\n3/4\n출력일: 2025-03-28\n세브란스병원\nSEVERANCE HOSPITAL\n출력자: 조예은\n원본대조필\n\n등록번호: 7314152\n주민등록번호: 651226-264**** 여/59세\n환자명: 김태현\n사회 복지서비스 연계 필요성\n✓ N ☐ Y\n기타 퇴원시 요구사항\n치료계획\n+\nEI\nProblem\nPrimary peritoneal\ncarcinomatosis\n기록자명\n김지환(의사)\n<약어 설명>\nG: gravida\nP: para\nL: living\nD: dead\nGoal\n목표일\nCTX AH ECOG GOG criteria 2025-02-28\n에 맞추어\n수정목표일 계획일\n2025-02-21\nDOE dyspnea on exertion\nPAP Papanicolaou\nPMI point of maximum intensity\nGYN: Gynecology\nHSIL High Grade Squamous Intraepithelial Lesion\nICS intercostal space\nA Abortion\nabnl abnormal\nA-V Anteversion\nBTL bilateral tubal ligation\nC/sec cesarian section\nIUD intrauterine device\nPMP previous menstrual period\nPul Tbc pulmonary tuberculosis\n:\nLBTL laparoscopic bilateral tubal ligation RCC: renal cell carcinoma\nLMCL Left Midclavicular Line\nLNMP last normal menstrual period\nRHB regular heart beat\nRT: Right\nLSIL: Low Grade Squamous Intraepithelial Lesion\nLT Left\nCVA cerebrovascular accident\nD&E Dilatation and evacuation\nDM diabetes mellitus\nM: Month\nnl: Normal\nR-V Retroversion\nVAS Visual analog pain scale\nY: Year\nAG-H atypical glandular cells cannot exclude a high-grade squamous intraepithelial lesion\nAGUS atypical glandular cells of undetermined significance\nASC-H atypical squamous cells cannot exclude a high-grade squamous intraepithelial lesion\nASCUS atypical squamous cells of undetermined significance\n입원기록\n전자서명자: 김상운\n세브란스병원\n4/4\n출력일: 2025-03-28\n출력자: 조예은\n원본대조필\nSEVERANCE HOSPITAL\n\n등록번호: 7314152\n주민등록번호 : 651226-264**** 여/59세\n환자명 : 김태현\n연령 구분\n|영유아기 ) 학령전기\n학령기\n청소년기\n성인\n분류\n일반 ○ 산모 ㅇ 정신\n현병력\n주 증상 및 내원 과정 금번 C2 위해 입원함 간호정보조사\n2025-02-21\n복용중인 약\n없음 있음\n투약 상태\n1회 투여개수\n1회 투여량\n약품명\n횟수\n용법 및 투여시간\n약품코드 유효함량\n수량 단위\n용량\n단위\nMagmil S [250 mg/T]\n1\nT\n250\nmg\n3\nPO\nD2MAGMO 250\nViscum Finj[0.02mg/\nA]\n1\nml\n0.02\nmg\n3\nS.C(월,수,금)\n2\nD1VISC02 0.020\n내원 시 환자 상태\n통증\n없음 있음\n입원 전에 있었음\n과거력\n과거병력\nㅇ 없음\n있음\n□ 고혈압\n입원 및 수술 이력\n당뇨 □ 결핵 □ 암 □ 간염\n없음 있음 ㅇ 알 수 없음\n□ 경련 | 기타 DL, 당뇨전단계\n입원 및 수술 이력\n입원시 진단명 및 수술명\n복막염 수술\n제왕절개 수술\nDiagnostic laparoscopy (GYN), NAC C1 [Genexol 175BSA+\n입원 및 수술 시기\n1984\n1993,1996\n25.01.30-2.2\nNeoplatin 5AUC]\n가족력\n없음 있음\n모: 자궁암\n음주력\nnondrinker\nex-drinker\ncurrent drinker\n흡연력\nAllergy\n약 □ 식품\n© nonsmoker ☐ ex-smoker ☐ current smoker\n□ 없음\n일반정보(심적/사회적/경제적/영적/문화/종교적 평가)\n결혼 상태 미혼 기혼 ㅇ 별거 ○ 이혼 ○사별 ㅇ 해당 없음\nㅇ없음 ○ 기독교 ○ 천주교 불교 ○ 기타\n종교\n원목 연락 원함 원하지 않음\n보호자 (Main caregiver)\n□ 없음 □ 배우자 □ 부\n□ 간병인 □ 기타\n모 □ 자녀\n□ 조부\n조모\n형제\n|자매\n입원비 지불의 어려움 ㅇ 있음 없음 ㅇ기타\n입원비 지불과 관련한 사회 사업팀 상담 필요\n지난 2주동안 기분이 가라앉거나, 우울하거나, 희망이 없다고 느낀 기간\n있음 없음 ○ 기타\n) 없음 ○ 2~3일 이상 ○7일 이상 ○ 거의 매일 ㅇ 확인 불가능\n지난 2주동안 평소 하던 일에 대한 흥미가 없어지거나 즐거움을 느끼지 못한 기간\n없음 ○ 2~3일 이상 ○ 7일 이상 ○ 거의 매일 ○ 확인불가능\n정서 평가 0\n*The Patient Health Questionnaire-2(PHQ-2) (2003) 주 사용 언어 한국어\n영어 □ 일본어 □ 중국어 □ 러시아어\n기타\n전자서명자: 이송미\n1/3\n출력일: 2025-03-28\n출력자: 조예은\n세브란스병원\n원본대조필\nSEVERANCE HOSPITAL\n\n등록번호: 7314152\n주민등록번호: 651226-264****여/59세\n환자명 : 김태현\n간호정보조사\n2025-02-21\n읽고 쓰는데 어려움\n없음 ㅇ있음\n교육과 진료에 영향을 주는 가치와 신념(Value & belief)\n없음 있음\n퇴원\n퇴원 후 보호자 (Main care giver) □ 배우자\n□ 부\n|자매\n간병인\n모 □ 자녀\n기타\n□ 조부\n조모\n형제\n없음\n퇴원 예정지\n자택 ㅇ 친척집\n타병원\n요양시설 기타\n퇴원 예정 교통수단(Discharge transportation)\n자가\n대중 교통\n항공\n□ 구급차\n|기타\n교육 요구도\n교육 대상자\n원하는 교육 내용\n선호하는 교육 방법\n영양 상태\n□ 환자 보호자\n질병 약물 □ 검사 □ 수술 |자가 간호\n구두 □ 유인물 □ 시범 보이기 □ 시청각 자료\n기타\n영양 □ 기타\n1개월간 체중변화 「없음 ㅇ 증가함 ㅇ 감소함\n체중변화 kg\n) 감소\n최근 1주일간 식사량 변화 없음 ㅇ 증가\n식이 주의 사항 ● 없음 ○ 열량 조절 ㅇ 체중 조절 ㅇ 염분 제한 ㅇ 수분 제한 ㅇ 단백질 제한 지방 제한\n수면상태\n기타\n수면장애\n기능 평가\n없음 ○ 잠들기 어려움 ㅇ 수면 후 개운하지 않음 수면중 3회 이상 깸 원하는 시간보다 일찍 깸\n보조기 사용\n기능 평가\n없음 ㅇ 목발 ㅇ 지팡이 Owalker ○ 휠체어 ○ 기타\n일상생활 수행 능력 ) 독립적 수행 부분 보조 필요 ㅇ 완전 보조\n식사\n개인 위생\n목욕\n옷입기\n화장실\n계단\n걷기\n독립적 수행 가능 ㅇ 준비 시 도움받아 독립적 수행 가능 ㅇ일부의 과정에서 도움이 필요함\n모든 과정에서 도움이 필요함 ㅇ 전혀 수행할 수 없음\n독립적 수행 가능 ㅇ준비 시 도움받아 독립적 수행 가능 ㅇ일부의 과정에서 도움이 필요함\n모든 과정에서 도움이 필요함 ㅇ 전혀 수행할 수 없음\n독립적 수행 가능 ㅇ 감독하에 독립적 수행 가능 ㅇ 일부의 과정에서 도움이 필요함\n모든 과정에서 도움이 필요함 ㅇ 전혀 수행할 수 없음\n독립적 수행 가능 ㅇ 최소의 도움(단추, 지퍼 등)으로 독립적 수행 가능 ○ 도움을 받아 입고 벗을 수 있음\n|수행 시 약간의 참여가 가능함 ㅇ 전혀 수행할 수 없음\n독립적 수행 가능 ㅇ 감독하에 독립적 수행 가능 ○일부의 과정에서 도움이 필요함\n모든 과정에서 도움이 필요함 ㅇ 전혀 수행할 수 없음\n「독립적 수행 가능 ○ 감독하에 독립적 수행 가능 Owalking aid 사용 없이 일부의 과정에서 도움이 필요함\nWalking aid 사용을 포함하여 모든 과정에서 도움이 필요함 ㅇ 전혀 수행할 수 없음\n독립적 수행 가능 (휠체어를 제외한 walking aid 사용할 수 있음) ㅇ 도움이나 감시 없이는 50m 이상 혼자 걷지 못함\n지속적인 Walking aid와 자주 다른 사람의 도움이 필요함 ㅇ 지속적으로 한사람 이상의 도움이 필요함\nㆍ전적으로 도움이 필요함\n이동 (의자와 침대)\n「독립적 수행 가능 ㅇ 감독하에 독립적 수행 가능 ○이동시 일부의 과정에서 도움이 필요함\n)지속적으로 한 사람 이상의 도움이 필요함 ㅇ 전적인 도움이 필요함\n배변 조절\n조절에 문제 없음\n)조절이 잘 되나 가끔 문제가 발생함\n'자주 문제가 발생하며 기저귀의 도움이 필요함 ㅇ자세를 취해주고 배변 시 도움이 필요함\n변실금이 지속됨\n전자서명자: 이송미\n세브란스병원\nSEVERANCE HOSPITAL\n2/3\n출력일: 2025-03-28\n출력자: 조예은\n원본대조필\n\n등록번호: 7314152\n주민등록번호: 651226-264**** 여/59세\n환자명: 김태현\n간호정보조사\n2025-02-21\n배뇨 조절\n조절에 문제 없음 ㅇ가끔 문제가 발생\n실금이 있으나 기구의 도움으로 해결\n낮에는 조절 가능하나 밤에는 도움 필요\n실금이 지속됨(유치 도뇨관)\n기능평가 점수 합계 100\n신체사정\n신경계\n시간 지남력\n장소 지남력\n사람 지남력\n의사 소통\n있음\n있음\n명확치 않음\n명확치 않음\n없음\n없음\n있음 ㅇ 명확치 않음\n원만함\n없음\n) 어려움 ○ 불가능함\n마비\n없음 있음 ㅇ 확인 불가능\nWeakness\n없음\n있음 ㅇ 확인 불가능\n시각\n시각장애\n없음\n있음\n청각\n청각장애\n없음\n있음\n소화기계\n소화기 관련증상\n없음\n있음\n순환기계\nPacemaker\n없음\n있음\n부종\n없음\n순환기 관련증상\n있음\n없음\n있음\n호흡기계\n호흡기 관련증상\n없음\n있음\n피부\n피부 온도\n따뜻함 ㅇ뜨거움\n차가움\n피부 습도\n•\n적당함\n건조함\n축축함\n피부색\n이상없음\n피부 변화\n창백\n없음 ㅇ있음\n) 홍조 ○ 청색증\n황달\n전자서명자: 이송미\n세브란스병원\nSEVERANCE HOSPITAL\n3/3\n출력일: 2025-03-28\n출력자: 조예은\n원본대조필\n\n등록번호: 7314152\n주민등록번호: 651226-264****여/59세\n환자명 : 김태현\n입원정보\n입원일자 2025-03-14\n입원과 산부인과\n퇴원정보\n입원주치의 김상운\n퇴원일자 2025-03-15\n퇴원과\n산부인과\n퇴원주치의 남은지\n최종진단명(*)\n순\n한국질병\n구분\n확진\n진단명\n서\n분류번호\n1 주진단\n확진\nPrimary peritoneal carcinomatosis\nC48.2\n2\n기타진단 확진\nOvarian cancer\nC56.9\n과거진단명\n과거진단코드\n주호소 (*)\nCTX\n과거력 및 현재병력 본 59세 G3 P2 L2 DO A1 married woman은 DL, 당뇨전단계, s/pop d/t perforated\nappendix (19세), s/pc/s 외 특이 과거력 없는 분으로, 하복부 불편감으로 대,소변 보\n기 어려워 타병원 내원하여 EGD,Colonoscopy 시행하여 특이 소견 없음에도 증상 지\n속되어 시행한 APCT 상r/o peritoneal carcinomatosis r/o associated Lt interiliac\nlymphandecnopathy with bilateral periovarian metastatic lesions or solid ovarian\ntumor 확인되어 further evaluation 및 proper management 위해 김상운 교수님께\nrefer, s/p D-lapa('25-1-31) 시행후 NAC C2 [Genexol 175BSA+ Neoplatin 5AUC]\n('25.02.01~) 후 퇴원한 분으로 금번 C3 시행 후 이상소견 없이 퇴원함 이상 진찰 소견 및 검사소견 (*)\nn-c\n투여된 약물 중 잔류효과로 퇴원 후 주의가 필요한 약물 (★)\n없음 있음\n경과요약 (*)\nNAC C3 [Genexol 175BSA+ Neoplatin 5AUC]\n수술/처치명\nNAC C3 [Genexol 175BSA+ Neoplatin 5AUC]\n수술/처치코드\nImplantable Medical Device 사용 여부 No Yes\n치료결과 (*)\n완쾌\n활력증상\n퇴원형태 (*)\n경쾌 호전안됨 ㅇ진단뿐\nㅇ48시간이내 사망 48시간 이후 사망\n혈압 120/80 mmHg 맥박수 72 회/분\n퇴원지시후 ㅇ타병원전원 ㅇ자의퇴원\n가망없는 퇴원\n체온 36.5 °℃ 호흡수 20 회/분\nㅇ 탈원\n향후 치료계획\n「외래 추후관리 2주후 영상 검사/3주후 외래내원하여 수술일 결정\n전자서명자: 남은지\n세브란스병원\nSEVERANCE HOSPITAL\n재입원\n없음\n퇴원요약\n1/2\n출력일: 2025-03-28\n출력자: 조예은\n원본대조필 |\n\n등록번호: 7314152\n주민등록번호: 651226-264**** 여/59세\n환자명 : 김태현\n퇴원요약\n기타\n담당 전공의사명\n없음\n기록자명\n김지환(의사)\n주치의사명\n남은지\n<약어 설명>\nA repair Anterior repair\nANC Antenatal care\nBO Bilateral oophorectomy\nBOC Bilateral ovarian cystectomy\nBS : Bilateral salpingectomy\nC/S Cesarean section\n:\nCPD Cephalopelvic disproportion\nDCB: Dilatation, curettage, biopsy\nET Embryo transplantation\nIDS Internal debulking operation\nIM Intramural lapa: Laparoscopic\nLOC Left ovarian cystectomy\nLS: Left salpingectomy\nP repair Posterior repair\nPALND: Para-aortic lymph node dissection\nPLD Pelvic lymphnode dissection\nPPD Postpartum day\nROC Right ovarian cystectomy\nROP Right occiput posterior\nRS Right salpingectomy\nSLND: Sentinel lymphnode dissection\nSPA Single port access\n전자서명자: 남은지\n2/2\n출력일: 2025-03-28\n출력자: 조예은\n세브란스병원\nSEVERANCE HOSPITAL\n원본대조필\n\n등록번호: 7314152\n주민등록번호: 651226-264**** 여/59세\n환자명 : 김태현\n연령 구분\n분류\n영유아기 학령전기 학령기 |청소년기\n일반 ○ 산모 정신\n성인\n현병력\n주 증상 및 내원 과정 금번 C3 위해 입원함 간호정보조사\n2025-03-14\n복용중인 약\n없음 있음\n투약 상태\n1회 투여개수\n1회 투여량\n약품명\n횟수\n용법 및 투여시간\n약품코드 유효함량\nMagmil S [250 mg/T]\n수량 단위\n2\n용량\n단위\nT\n500\nmg\n3\nPO\n2\nMegace F susp(취급자 1\nPack\n5\nml\n1\nPO (7am)\nD2MAGMO 250\nD3MEGA06 5\n[주의) [5ml/Pack]\n[A]\nViscum Finj[0.02mg/ 1\n내원 시 환자 상태\n0.02\nmg\n3\nS.C(월,수,금) 9:30am\nD1VISC02 0.02\n통증\n없음 ㅇ있음\n입원 전에 있었음\n과거력\n과거병력\n없음\n있음\n□ 고혈압\n입원 및 수술 이력\n당뇨 □ 결핵 □ 암 □ 간염\n없음\n있음 ㅇ 알 수 없음\n경련 □ 기타 DL, 당뇨전단계\n입원 및 수술 이력\n입원시 진단명 및 수술명\n복막염 수술\n제왕절개 수술\nDiagnostic laparoscopy (GYN), NAC C1 [Genexol 175BSA+\nNeoplatin 5AUC]\nNAC C2 [Genexol 175BSA+ Neoplatin 5AUC]\n입원 및 수술 시기\n1984\n1993,1996\n25.01.30-2.2\n(25.02.01~)\n가족력\n없음 | 있음\n모: 자궁암\n음주력\nex-drinker\ncurrent drinker\n흡연력\ncurrent smoker\nOnondrinker\nnonsmoker O ex-smoker\nAllergy □ 없음 □ 약 □ 식품\n일반정보(심적/사회적/경제적/영적/문화/종교적 평가)\n결혼 상태 ㅇ 미혼 기혼 ㅇ 별거 ㅇ 이혼 ㅇ 사별 ㅇ 해당 없음\n종교\n없음 ○ 기독교 천주교 불교 ㅇ기타\n원목 연락 ㅇ원함 원하지 않음\n보호자 (Main care giver) □ 없음\n배우자 □ 부\n모\n자녀\n조부\n조모\n형제\n자매\n□ 간병인 □ 기타\n입원비 지불의 어려움 ㅇ있음 없음 ㅇ기타\n입원비 지불과 관련한 사회 사업팀 상담 필요 ㅇ 있음 없음 ㅇ기타\n지난 2주동안 기분이 가라앉거나, 우울하거나, 희망이 없다고 느낀 기간\n없음 ○ 2~3일 이상 ○7일 이상 ○ 거의 매일 확인 불가능\n지난 2주동안 평소 하던 일에 대한 흥미가 없어지거나 즐거움을 느끼지 못한 기간\n없음 ○ 2~3일 이상 ○7일 이상 ○ 거의 매일 ○ 확인불가능\n정서 평가 0\n전자서명자: 권대연\n세브란스병원\nSEVERANCE HOSPITAL\n1/3\n출력일: 2025-03-28\n출력자: 조예은\n원본대조필\n\n등록번호: 7314152\n주민등록번호: 651226-264****여/59세\n간호정보조사\n2025-03-14\n환자명 : 김태현\n*The Patient Health Questionnaire -2(PHQ-2) (2003) 주 사용 언어 한국어\n읽고 쓰는데 어려움\n영어 □ 일본어 중국어 □ 러시아어 □ 기타\n없음 ㅇ있음\n교육과 진료에 영향을 주는 가치와 신념(Value & belief)\n없음 있음\n퇴원\n퇴원 후 보호자 (Main care giver)\n배우자 □ 부\n모\n자녀 □ 조부\n조모\n형제\n자매 □ 간병인\n기타\n없음\n퇴원 예정지\n•자택 ㅇ 친척집 ○ 타병원\n퇴원 예정 교통수단(Discharge transportation)\n요양시설 기타\n자가 □ 대중 교통\n기타\n□ 항공\n□ 구급차\n교육 요구도\n교육 대상자\n|환자\n보호자\n기타\n원하는 교육 내용\n√ 질병\n약물 □ 검사 □ 수술\n□자가 간호\n시청각 자료\n영양\n기타\n선호하는 교육 방법 구두 □ 유인물 □ 시범 보이기\n영양 상태\n1개월간 체중변화 없음 ㅇ 증가함 ㅇ 감소함\n체중변화\nkg\n최근 1주일간 식사량 변화 없음 ㅇ 증가 감소\n식이 주의 사항 없음 ㅇ 열량 조절 체중 조절 염분 제한 수분 제한 단백질 제한 지방 제한\n기타\n수면상태\n수면장애\n기능 평가\n없음\n잠들기 어려움 ㅇ수면 후 개운하지 않음 수면중 3회 이상 깸\n)원하는 시간보다 일찍 깸\n보조기 사용\n없음 목발 지팡이 Owalker ○ 휠체어 ㅇ기타\n기능 평가\n일상생활 수행 능력\n식사\n독립적 수행 ㅇ부분 보조 필요 ㅇ완전 보조\n독립적 수행 가능 ㅇ 준비 시 도움받아 독립적 수행 가능\n모든 과정에서 도움이 필요함 ㅇ 전혀 수행할 수 없음\n일부의 과정에서 도움이 필요함\n개인 위생\n독립적 수행 가능 ㅇ준비 시 도움받아 독립적 수행 가능\n모든 과정에서 도움이 필요함 ㅇ 전혀 수행할 수 없음\n일부의 과정에서 도움이 필요함\n목욕\n독립적 수행 가능 ㅇ 감독하에 독립적 수행 가능 ㅇ 일부의 과정에서 도움이 필요함\n모든 과정에서 도움이 필요함 ㅇ 전혀 수행할 수 없음\n옷입기\n독립적 수행 가능 ㅇ 최소의 도움(단추, 지퍼 등)으로 독립적 수행 가능\n수행 시 약간의 참여가 가능함 ㅇ 전혀 수행할 수 없음\n도움을 받아 입고 벗을 수 있음\n화장실\n계단\n걷기\n독립적 수행 가능 ㅇ 감독하에 독립적 수행 가능 ○일부의 과정에서 도움이 필요함\n모든 과정에서 도움이 필요함 ㅇ 전혀 수행할 수 없음\n독립적 수행 가능 ㅇ 감독하에 독립적 수행 가능 OWalking aid 사용 없이 일부의 과정에서 도움이 필요함\nWalking aid 사용을 포함하여 모든 과정에서 도움이 필요함 ㅇ 전혀 수행할 수 없음\n독립적 수행 가능 (휠체어를 제외한 walking aid 사용할 수 있음) ㅇ 도움이나 감시 없이는 50m 이상 혼자 걷지 못함\n) 지속적인 Walking aid와 자주 다른 사람의 도움이 필요함 ㅇ 지속적으로 한사람 이상의 도움이 필요함\n전적으로 도움이 필요함\n이동 (의자와 침대)\n'독립적 수행 가능 ㅇ 감독하에 독립적 수행 가능 ○이동시 일부의 과정에서 도움이 필요함\nㅇ 지속적으로 한 사람 이상의 도움이 필요함 ㅇ 전적인 도움이 필요함\n전자서명자: 권대연\n세브란스병원\nSEVERANCE HOSPITAL\n2/3\n출력일: 2025-03-28\n출력자: 조예은\n원본대조필\n\n등록번호: 7314152\n주민등록번호: 651226-264**** 여/59세\n환자명 : 김태현\n배변 조절\n조절에 문제 없음 ㅇ조절이 잘 되나 가끔 문제가 발생함\n간호정보조사\n2025-03-14\n자주 문제가 발생하며 기저귀의 도움이 필요함 ○ 자세를 취해주고 배변 시 도움이 필요함\n변실금이 지속됨\n배뇨 조절\n조절에 문제 없음 ㅇ가끔 문제가 발생\nㅇ실금이 있으나 기구의 도움으로 해결\nㅇ낮에는 조절 가능하나 밤에는 도움 필요\n실금이 지속됨(유치 도뇨관)\n기능평가 점수 합계 100\n신체사정\n신경계\n시간 지남력\n있음\n명확치 않음\n없음\n장소 지남력\n사람 지남력\n의사 소통\n있음\n있음\n원만함\n명확치 않음\n없음\nㅇ명확치 않음 ㅇ 없음\n어려움 ㅇ 불가능함\n마비\n없음 있음\n「확인 불가능\nWeakness\n없음 ㅇ있음 ㅇ 확인 불가능\n시각\n시각장애\n없음 있음\n청각\n청각장애\n없음 있음\n소화기계\n소화기 관련증상\n없음\n있음\n순환기계\nPacemaker\n없음\n있음\n부종\n없음\n순환기 관련증상\n있음\n없음\n있음\n호흡기계\n호흡기 관련증상\n없음\n있음\n피부\n피부 온도\n피부색\n따뜻함 뜨거움 ㅇ 차가움\n피부 변화\n이상없음 ㅇ창백 ㅇ 홍조 ㅇ 청색증\n없음 ㅇ있음\n피부 습도\n황달\n적당함\n) 건조함\n축축함\n전자서명자: 권대연\n3/3\n출력일: 2025-03-28\n출력자: 조예은\n세브란스병원\nSEVERANCE HOSPITAL\n원본대조필\n\n등록번호: 7314152\n주민등록번호: 651226-264**** 여/59세\n환자명 : 김태현\n영상검사 일반촬영\n검사명\nChest PA\n검사방법\n검사일자\n판독일자\nDescription\n2025.03.14 11:11\n2025.03.15 09:44\nNo active lung disease 판독의/전문의\n손진우/손진우/손진우\n전자서명자: 손진우\n세브란스병원\nSEVERANCE HOSPITAL\n영상검사 일반촬영\n촬영실\n암)촬영실 4호(흉부)\n1/1\n출력일: 2025-03-28\n출력자: 조예은\n원본대조필",
      "검사내용및결과": "검사 정보 없음",
      "치료사항": "보존적 치료",
      "과거력": "과거력 확인됨",
      "기타사항": "환자명: 김태현, DNA 시퀀싱 처리: 1개 유전자 분석"
    },
    "validation": {
      "score": 0.8,
      "completeness": 1
    },
    "statistics": {
      "overall_confidence": 0.75,
      "genes_analyzed": 1,
      "processing_method": "DNA_SEQUENCING_MOCK"
    }
  }
}